Workbook

Sheet Product list
A1: Standardize | B1: Product Code | C1: Income Account | D1: Expense Account | E1: Product Category | F1: Product Type | G1: Product Name TH | H1: Product Name EN | I1: UOM TH | J1: UOM EN | K1: Code Supplier | L1: Supplier Name | M1: Sellable/Not Sellable | N1: Selling Price | O1: Cost Price
A2: Standard | B2: AX-3M233-TH | C2: 513025 | D2: 513025 | E2: Tape | F2: Storable Product | G2: เทปกาว 3M | H2: Masking tape | I2: ชิ้น | J2: PC | K2: AP-CST000 | L2: =IFERROR(VLOOKUP(K2,'Supplier list'!B:C,2,0),"") | M2: Not Sellable | O2: 202
A3: Standard | B3: AX-513004-TH | C3: 513025 | D3: 513025 | E3: buy-sell | F3: Storable Product | G3: ซื้อมา-ขายไป | H3: Buy-Sell | I3: ชิ้น | J3: PC | K3: - | L3: =IFERROR(VLOOKUP(K3,'Supplier list'!B:C,2,0),"") | M3: Not Sellable | O3: 0
A4: Standard | B4: AX-513006-TH | C4: 513025 | D4: 513025 | E4: Service | F4: Storable Product | G4: ค่าใช้จ่าย-นำเข้า | H4: Import Fee | I4: งาน | J4: JOB | K4: - | L4: =IFERROR(VLOOKUP(K4,'Supplier list'!B:C,2,0),"") | M4: Not Sellable | O4: 0
A5: Standard | B5: AX-513007-TH | C5: 513025 | D5: 513025 | E5: Service | F5: Storable Product | G5: ค่าใช้จ่าย-ส่งออก | H5: Export Fee | I5: งาน | J5: JOB | K5: - | L5: =IFERROR(VLOOKUP(K5,'Supplier list'!B:C,2,0),"") | M5: Not Sellable | O5: 0
A6: Standard | B6: AX-531016-TH | C6: 513025 | D6: 513025 | E6: Service | F6: Storable Product | G6: ค่าสวัสดิการอื่นๆ-เลี้ยงข้าวพนักงาน | H6: Other welfare expenses - food for employees | I6: งาน | J6: JOB | K6: - | L6: =IFERROR(VLOOKUP(K6,'Supplier list'!B:C,2,0),"") | M6: Not Sellable | O6: 0
A7: Standard | B7: AX-CGM00-TH | C7: 513025 | D7: 513025 | E7: Tape | F7: Storable Product | G7: เทปกาว | H7: Masking tape | I7: ชิ้น | J7: PC | K7: AP-BNT000 | L7: =IFERROR(VLOOKUP(K7,'Supplier list'!B:C,2,0),"") | M7: Not Sellable | O7: 84
A8: Standard | B8: AX-PH007-TH | C8: 513025 | D8: 513025 | E8: Carpet | F8: Storable Product | G8: พื้นพรมแผ่นรุ่น PH07 | H8: Carpet floor sheet model PH07 | I8: ตรม. | J8: SQM | K8: AP-SFL000 | L8: =IFERROR(VLOOKUP(K8,'Supplier list'!B:C,2,0),"") | M8: Not Sellable | O8: 680
A9: Standard | B9: AX-PT00-001 | C9: 513025 | D9: 513025 | E9: Cardboard cylinder | F9: Storable Product | G9: Paper Tube/กระบอกภาชนะกระดาษแข็ง | H9: Cardboard cylinder with spray paint | I9: ชิ้น | J9: PC | K9: AP-QNL000 | L9: =IFERROR(VLOOKUP(K9,'Supplier list'!B:C,2,0),"") -> CO.,LTD QINGDAO NEW LIBERTY INT'L TRADING CO.LTD. | M9: Not Sellable | O9: 0.35
A10: Standard | B10: AX-PT00-002 | C10: 513025 | D10: 513025 | E10: Service | F10: Storable Product | G10: ค่าส่งสินค้าอื่นๆ | H10: Other shipping costs | I10: งาน | J10: JOB | K10: - | L10: =IFERROR(VLOOKUP(K10,'Supplier list'!B:C,2,0),"") | M10: Not Sellable | O10: 0
A11: Standard | B11: FC-0001 | C11: 513025 | D11: 513025 | E11: Honeycomb | F11: Storable Product | G11: กระดาษรังผึ้ง honeycomb กว้าง60xยาว30 หนา10 cm. | H11: Honey Comb 60x30x10 cm. | I11: ชิ้น | J11: PC | K11: AP-QNL000 | L11: =IFERROR(VLOOKUP(K11,'Supplier list'!B:C,2,0),"") -> CO.,LTD QINGDAO NEW LIBERTY INT'L TRADING CO.LTD. | M11: Not Sellable | O11: 5.7
A12: Standard | B12: FC-0002 | C12: 513025 | D12: 513025 | E12: Tool | F12: Storable Product | G12: เครื่องเจียร์ไฟฟ้า 4" MAKITA 9500NB | H12: Electric Grinder 4MAKITA9500NB" | I12: ชิ้น | J12: PC | K12: AP-GDL000 | L12: =IFERROR(VLOOKUP(K12,'Supplier list'!B:C,2,0),"") -> หจก. กรีน ดิสทริบิวชั่น | M12: Not Sellable | O12: 2990
A13: Standard | B13: FC-0003 | C13: 513025 | D13: 513025 | E13: Tool | F13: Storable Product | G13: ถังกาพ่น M-871 | H13: Spray Gun M-871 | I13: ชิ้น | J13: PC | K13: - | L13: =IFERROR(VLOOKUP(K13,'Supplier list'!B:C,2,0),"") | M13: Not Sellable | O13: 4200
... A23: Standard | B23: FC-0013 | C23: 513025 | D23: 513025 | E23: Light bulb | F23: Storable Product | G23: หลอดไฟ (ยาว) | H23: Light bulb (long) | I23: หลอด | J23: TUBE | K23: AP-TPK001 | L23: =IFERROR(VLOOKUP(K23,'Supplier list'!B:C,2,0),"") -> บริษัท ที.พี.เค ไทยเมท แมชชีนทูลล์ จำกัด | M23: Not Sellable | O23: 229
A24: Standard | B24: FC-0014 | C24: 513025 | D24: 513025 | E24: Light bulb | F24: Storable Product | G24: หลอดไฟ (สั้น) | H24: Light bulb (short) | I24: หลอด | J24: TUBE | L24: =IFERROR(VLOOKUP(K24,'Supplier list'!B:C,2,0),"") | M24: Not Sellable | O24: 63
A25: Standard | B25: FC-0015 | C25: 513025 | D25: 513025 | E25: Tool | F25: Storable Product | G25: หัวปืน M-871 (จีน) | H25: Gun head M-871 (China) | I25: ชิ้น | J25: PC | K25: - | L25: =IFERROR(VLOOKUP(K25,'Supplier list'!B:C,2,0),"") | M25: Not Sellable | O25: 0
A26: Standard | B26: FC-0016 | C26: 513025 | D26: 513025 | E26: Tool | F26: Storable Product | G26: หัวจี้ลม แกน 3 mm. | H26: Air pendant 3 mm. | I26: ชิ้น | J26: PC | K26: - | L26: =IFERROR(VLOOKUP(K26,'Supplier list'!B:C,2,0),"") | M26: Not Sellable | O26: 0
A27: Standard | B27: FC-0017 | C27: 513025 | D27: 513025 | E27: Screw | F27: Storable Product | G27: สกรูมิลดำ 12x55+หัว+อีแปะ | H27: Hexagon Screw Black 12x55 | I27: ชุด | J27: SET | K27: AP-KSR001 | L27: =IFERROR(VLOOKUP(K27,'Supplier list'!B:C,2,0),"") -> บริษัท เกรียงศิริพัฒนา (1995) จำกัด | M27: Not Sellable | O27: 15
A28: Standard | B28: FC-0020 | C28: 513025 | D28: 513025 | E28: Joint | F28: Storable Product | G28: คอปเปอร์ 3 ทาง T | H28: Coupler 3 Way Multi Pass ,T | I28: ชิ้น | J28: PC | K28: AP-KSR001 | L28: =IFERROR(VLOOKUP(K28,'Supplier list'!B:C,2,0),"") -> บริษัท เกรียงศิริพัฒนา (1995) จำกัด | M28: Not Sellable | O28: 190
A29: Standard | B29: FC-0021 | C29: 513025 | D29: 513025 | E29: Joint | F29: Storable Product | G29: ข้อต่อคอปเปอร์ 20pm. | H29: Coupler joint, model 20PM | I29: ชิ้น | J29: PC | K29: AP-KSR001 | L29: =IFERROR(VLOOKUP(K29,'Supplier list'!B:C,2,0),"") -> บริษัท เกรียงศิริพัฒนา (1995) จำกัด | M29: Not Sellable | O29: 20
A30: Standard | B30: FC-0023 | C30: 513025 | D30: 513025 | E30: Drill bits | F30: Storable Product | G30: ดอกเจาะกระจก 8มม. | H30: Glass drill bit 8 mm. | I30: ชิ้น | J30: PC | K30: AP-KSR001 | L30: =IFERROR(VLOOKUP(K30,'Supplier list'!B:C,2,0),"") -> บริษัท เกรียงศิริพัฒนา (1995) จำกัด | M30: Not Sellable | O30: 200
A31: Standard | B31: FC-0024 | C31: 513025 | D31: 513025 | E31: Battery | F31: Storable Product | G31: 005.23.601 BRUSH ET-BG 240V CT26/36 | H31: 005.23.601 BRUSH ET-BG 240V CT26/36 | I31: ชิ้น | J31: PC | K31: AP-HAF001 | L31: =IFERROR(VLOOKUP(K31,'Supplier list'!B:C,2,0),"") -> บริษัท เฮเฟเล่ (ประเทศไทย) จำกัด | M31: Not Sellable | O31: 1776
A32: Standard | B32: FC-0026 | C32: 513025 | D32: 513025 | E32: Wheel | F32: Storable Product | G32: ล้อไนลอนขาวชุดชุบโครเมียม แป้นเป็น 4" | H32: Wheels, white nylon, chrome plated set, backplate 4" | I32: กล่อง | J32: BOX | K32: AP-KCR000 | L32: =IFERROR(VLOOKUP(K32,'Supplier list'!B:C,2,0),"") | M32: Not Sellable | O32: 435
A33: Standard | B33: FC-0027 | C33: 513025 | D33: 513025 | E33: Bathroom cleaner | F33: Storable Product | G33: น้ำยาล้างห้องน้ำ (เป็ดโปร) | H33: Bathroom cleaner (Duck Pro) | I33: ขวด | J33: BOTTLES | K33: AP-SMK000 | L33: =IFERROR(VLOOKUP(K33,'Supplier list'!B:C,2,0),"") -> บริษัท สยามแม็คโคร จำกัด (มหาชน) | M33: Not Sellable | O33: 209
A34: Standard | B34: FC-0028 | C34: 513025 | D34: 513025 | E34: Screw | F34: Storable Product | G34: สกรูมิล JF M4x8-0.70 | H34: Hexagon Screw JF M4x8-0.70 | I34: ชิ้น | J34: PC | K34: AP-KCR000 | L34: =IFERROR(VLOOKUP(K34,'Supplier list'!B:C,2,0),"") -> บริษัท ก.เจริญฮาร์ดแวร์ จำกัด | M34: Not Sellable | O34: 0.25
A35: Standard | B35: FC-0029 | C35: 513025 | D35: 513025 | E35: Drill bits | F35: Storable Product | G35: โฮลซอเจาะไม้ 7 ใบ/ชุด 26-63มม. | H35: Hole Saw 7 wood drill bits/set 26-63mm. | I35: ชุด | J35: SET | K35: AP-SHM000 | L35: =IFERROR(VLOOKUP(K35,'Supplier list'!B:C,2,0),"") -> บริษัท ซูเปอร์โฮมมาร์ท จำกัด (สำนักงานใหญ่) | M35: Not Sellable | O35: 115
A36: Standard | B36: FC-0030 | C36: 513025 | D36: 513025 | E36: EPE Foam | F36: Storable Product | G36: EPE Foam Laminate inside (handle J) | H36: EPE Foam Laminate inside (handle J) | I36: ชิ้น | J36: PC | K36: AP-PCP000 | L36: =IFERROR(VLOOKUP(K36,'Supplier list'!B:C,2,0),"") | M36: Not Sellable | O36: 4.5
... A63: Standard | B63: FS-FUFIT-002 | C63: 114003 | D63: 114003 | E63: Rubber Bump Button | F63: Storable Product | G63: 483.01.996 ปุ่มยางกันกระแทก | H63: 483.01.996 Rubber Bump Button | I63: แผง | J63: PANEL | K63: AP-HAF001 | L63: =IFERROR(VLOOKUP(K63,'Supplier list'!B:C,2,0),"") -> บริษัท เฮเฟเล่ (ประเทศไทย) จำกัด | M63: Not Sellable | O63: 178
A64: Standard | B64: FS-FUFIT-003 | C64: 114003 | D64: 114003 | E64: Triangle Claw Bumper | F64: Storable Product | G64: กันชนก้ามปูสามเหลี่ยม BARCO | H64: BARCO Triangle Claw Bumper | I64: ชิ้น | J64: PC | L64: =IFERROR(VLOOKUP(K64,'Supplier list'!B:C,2,0),"") | M64: Not Sellable | O64: 28
A65: Standard | B65: FS-FUFIT-004 | C65: 114003 | D65: 114003 | E65: Push Catches | F65: Storable Product | G65: กดเปิดหน้าบานแบบแม่เหล็ก XL | H65: Press to open the magnetic door XL | I65: ชิ้น | J65: PC | L65: =IFERROR(VLOOKUP(K65,'Supplier list'!B:C,2,0),"") | M65: Not Sellable | O65: 68
A66: Standard | B66: FS-FUFIT-008 | C66: 114003 | D66: 114003 | E66: Staples | F66: Storable Product | G66: ลูกแม็กขาคู่รุ่น1010J ขนาด 10x10 | H66: Double leg alloy, model 1010J, size 10x10 | I66: กล่อง | J66: BOX | K66: AP-KSR001 | L66: =IFERROR(VLOOKUP(K66,'Supplier list'!B:C,2,0),"") | M66: Not Sellable | O66: 100
A67: Standard | B67: FS-FUFIT-009 | C67: 114003 | D67: 114003 | E67: Nails | F67: Storable Product | G67: ตะปูยิงงานฝีมือ HI-TOP # PINS/25 | H67: HI-TOP Craft Nails # PINS/25 | I67: กล่อง | J67: BOX | L67: =IFERROR(VLOOKUP(K67,'Supplier list'!B:C,2,0),"") | M67: Not Sellable | O67: 261
A68: Standard | B68: FS-FUFIT-010 | C68: 114003 | D68: 114003 | E68: Power cord with jack | F68: Storable Product | G68: สายไฟพร้อมแจ๊คเสียบ | H68: Power cord with jack | I68: เส้น | J68: STRIP | L68: =IFERROR(VLOOKUP(K68,'Supplier list'!B:C,2,0),"") | M68: Not Sellable | O68: 60
A69: Standard | B69: FS-FUFIT-011 | C69: 114003 | D69: 114003 | E69: Staples | F69: Storable Product | G69: ลูกแม็กขาคู่รุ่น416J ขนาด 4x16 | H69: Staples Double pin model 416J, size 4x16 | I69: กล่อง | J69: BOX | L69: =IFERROR(VLOOKUP(K69,'Supplier list'!B:C,2,0),"") | M69: Not Sellable | O69: 93
A70: Standard | B70: FS-FUFIT-012 | C70: 114003 | D70: 114003 | E70: Staples | F70: Storable Product | G70: ลูกแม็กขาคู่รุ่น410J ขนาด 4x10 | H70: Staples Double pin model 416J, size 4x10 | I70: กล่อง | J70: BOX | L70: =IFERROR(VLOOKUP(K70,'Supplier list'!B:C,2,0),"") | M70: Not Sellable | O70: 93
A71: Standard | B71: FS-FUFIT-013 | C71: 114003 | D71: 114003 | E71: Power plug | F71: Storable Product | G71: ปลั๊ก3ขา | H71: 3 pin plug | I71: ชิ้น | J71: PC | K71: AP-GDL000 | L71: =IFERROR(VLOOKUP(K71,'Supplier list'!B:C,2,0),"") -> หจก. กรีน ดิสทริบิวชั่น | M71: Not Sellable | O71: 28
A72: Standard | B72: FS-FUFIT-014 | C72: 114003 | D72: 114003 | E72: Power plug | F72: Storable Product | G72: ปลั๊ก2ขา | H72: 2 pin plug | I72: ชิ้น | J72: PC | K72: AP-GDL000 | L72: =IFERROR(VLOOKUP(K72,'Supplier list'!B:C,2,0),"") -> หจก. กรีน ดิสทริบิวชั่น | M72: Not Sellable | O72: 20
A73: Standard | B73: FS-FUFIT-015 | C73: 114003 | D73: 114003 | E73: Glue | F73: Storable Product | G73: กาวลาเท็กซ์ 32 ออน 12ขวด/ลัง | H73: Latex Glue 32 ounces, 12 bottles/box | I73: ขวด | J73: BOTTLES | K73: AP-KSR001 | L73: =IFERROR(VLOOKUP(K73,'Supplier list'!B:C,2,0),"") | M73: Not Sellable | O73: 55
A74: Standard | B74: FS-FUFIT-016 | C74: 114003 | D74: 114003 | E74: Chalk | F74: Storable Product | G74: ชอล์กTOUTH-UPSTLCK NO.101 | H74: Chalk TOUTH-UPSTTLCK NO.101 | I74: แท่ง | J74: STICK | K74: AP-MKW000 | L74: =IFERROR(VLOOKUP(K74,'Supplier list'!B:C,2,0),"") -> บริษัท เอ็มเค วู้ดเทค จำกัด | M74: Not Sellable | O74: 80
A75: Standard | B75: FS-FUFIT-017 | C75: 114003 | D75: 114003 | E75: Chalk | F75: Storable Product | G75: ชอล์กTOUTH-UPSTLCK NO.106 | H75: Chalk TOUTH-UPSTTLCK NO.106 | I75: แท่ง | J75: STICK | K75: AP-MKW000 | L75: =IFERROR(VLOOKUP(K75,'Supplier list'!B:C,2,0),"") -> บริษัท เอ็มเค วู้ดเทค จำกัด | M75: Not Sellable | O75: 80
A76: Standard | B76: FS-FUFIT-018 | C76: 114003 | D76: 114003 | E76: Chalk | F76: Storable Product | G76: ชอล์กTOUTH-UPSTLCK NO.313 | H76: Chalk TOUTH-UPSTTLCK NO.313 | I76: แท่ง | J76: STICK | K76: AP-MKW000 | L76: =IFERROR(VLOOKUP(K76,'Supplier list'!B:C,2,0),"") -> บริษัท เอ็มเค วู้ดเทค จำกัด | M76: Not Sellable | O76: 80
A77: Standard | B77: FS-FUFIT-019 | C77: 114003 | D77: 114003 | E77: Chalk | F77: Storable Product | G77: ชอล์กTOUTH-UPSTLCK NO.2638 | H77: Chalk TOUTH-UPSTTLCK NO.2638 | I77: แท่ง | J77: STICK | K77: AP-MKW000 | L77: =IFERROR(VLOOKUP(K77,'Supplier list'!B:C,2,0),"") -> บริษัท เอ็มเค วู้ดเทค จำกัด | M77: Not Sellable | O77: 80
A78: Standard | B78: FS-FUFIT-020 | C78: 114003 | D78: 114003 | E78: Chalk | F78: Storable Product | G78: ชอล์กTOUTH-UPSTLCK NO.3200 | H78: Chalk TOUTH-UPSTTLCK NO.3200 | I78: แท่ง | J78: STICK | K78: AP-MKW000 | L78: =IFERROR(VLOOKUP(K78,'Supplier list'!B:C,2,0),"") -> บริษัท เอ็มเค วู้ดเทค จำกัด | M78: Not Sellable | O78: 80
A79: Standard | B79: FS-FUFIT-021 | C79: 114003 | D79: 114003 | E79: Chalk | F79: Storable Product | G79: ชอล์กTOUTH-UPSTLCK NO.3325 | H79: Chalk TOUTH-UPSTTLCK NO.3325 | I79: แท่ง | J79: STICK | K79: AP-MKW000 | L79: =IFERROR(VLOOKUP(K79,'Supplier list'!B:C,2,0),"") -> บริษัท เอ็มเค วู้ดเทค จำกัด | M79: Not Sellable | O79: 80
A80: Standard | B80: FS-FUFIT-022 | C80: 114003 | D80: 114003 | E80: Chalk | F80: Storable Product | G80: ชอล์กTOUTH-UPSTLCK NO.3357 | H80: Chalk TOUTH-UPSTTLCK NO.3357 | I80: แท่ง | J80: STICK | K80: AP-MKW000 | L80: =IFERROR(VLOOKUP(K80,'Supplier list'!B:C,2,0),"") -> บริษัท เอ็มเค วู้ดเทค จำกัด | M80: Not Sellable | O80: 80
A81: Standard | B81: FS-FUFIT-023 | C81: 114003 | D81: 114003 | E81: Chalk | F81: Storable Product | G81: ชอล์กTOUTH-UPSTLCK NO.3258 | H81: Chalk TOUTH-UPSTTLCK NO.3258 | I81: แท่ง | J81: STICK | K81: AP-MKW000 | L81: =IFERROR(VLOOKUP(K81,'Supplier list'!B:C,2,0),"") -> บริษัท เอ็มเค วู้ดเทค จำกัด | M81: Not Sellable | O81: 80
A82: Standard | B82: FS-FUFIT-024 | C82: 114001 | D82: 114001 | E82: Chalk | F82: Storable Product | G82: ชอล์กTOUTH-UPSTLCK NO.3125 | H82: Chalk TOUTH-UPSTTLCK NO.3125 | I82: แท่ง | J82: STICK | K82: AP-MKW000 | L82: =IFERROR(VLOOKUP(K82,'Supplier list'!B:C,2,0),"") -> บริษัท เอ็มเค วู้ดเทค จำกัด | M82: Not Sellable | O82: 80
... A84: Standard | B84: FS-FUFIT-026 | C84: 114001 | D84: 114001 | E84: Turpentine | F84: Storable Product | G84: น้ำมันสน | H84: Turpentine | I84: ปี๊ป | J84: BUCKET | K84: AP-TPK001 | L84: =IFERROR(VLOOKUP(K84,'Supplier list'!B:C,2,0),"") -> บริษัท ที.พี.เค ไทยเมท แมชชีนทูลล์ จำกัด | M84: Not Sellable | O84: 400
A85: Standard | B85: FS-FUFIT-027 | C85: 114001 | D85: 114001 | E85: Silicone | F85: Storable Product | G85: ซิลิโคน สีเทา | H85: Silicone gray | I85: หลอด | J85: TUBE | L85: =IFERROR(VLOOKUP(K85,'Supplier list'!B:C,2,0),"") | M85: Not Sellable | O85: 65
A86: Standard | B86: FS-FUFIT-028 | C86: 114001 | D86: 114001 | E86: PVC pipe binder | F86: Storable Product | G86: น้ำยาประสานท่อพีวีซี-100g | H86: PVC pipe binder-100g | I86: กระป๋อง | J86: CAN | K86: AP-KSR001 | L86: =IFERROR(VLOOKUP(K86,'Supplier list'!B:C,2,0),"") | M86: Not Sellable | O86: 30
A87: Standard | B87: FS-FUFIT-029 | C87: 114001 | D87: 114001 | E87: Glue | F87: Storable Product | G87: กาวตะปู Maxbond Fuller | H87: Maxbond Fuller Nail Glue | I87: หลอด | J87: TUBE | K87: AP-GDL000 | L87: =IFERROR(VLOOKUP(K87,'Supplier list'!B:C,2,0),"") -> หจก. กรีน ดิสทริบิวชั่น | M87: Not Sellable | O87: 90
A88: Standard | B88: FS-FUFIT-030 | C88: 114001 | D88: 114001 | E88: Glue | F88: Storable Product | G88: กาวร้อน | H88: Hot glue | I88: หลอด | J88: TUBE | K88: AP-PNPI000 | L88: =IFERROR(VLOOKUP(K88,'Supplier list'!B:C,2,0),"") -> บริษัท พีเอ็นพี อินเตอร์แพค | M88: Not Sellable | O88: 10
A89: Standard | B89: FS-FUFIT-031 | C89: 114001 | D89: 114001 | E89: Purpose spray | F89: Storable Product | G89: สเปรย์เอนกประสงค์ SONAX | H89: Sonax multi -purpose spray | I89: กระป๋อง | J89: CAN | K89: AP-GDL000 | L89: =IFERROR(VLOOKUP(K89,'Supplier list'!B:C,2,0),"") -> หจก. กรีน ดิสทริบิวชั่น | M89: Not Sellable | O89: 95
A90: Standard | B90: FS-FUFIT-032 | C90: 114001 | D90: 114001 | E90: Paint equipment | F90: Storable Product | G90: ลูกกลิ้งทาสี (ใหญ่) | H90: Paint roller (large) | I90: ชิ้น | J90: PC | L90: =IFERROR(VLOOKUP(K90,'Supplier list'!B:C,2,0),"") | M90: Not Sellable | O90: 69
A91: Standard | B91: FS-FUFIT-033 | C91: 114001 | D91: 114001 | E91: Paint equipment | F91: Storable Product | G91: แปรงทาสี | H91: Paint brush | I91: ชิ้น | J91: PC | K91: AP-KSR001 | L91: =IFERROR(VLOOKUP(K91,'Supplier list'!B:C,2,0),"") -> บริษัท เกรียงศิริพัฒนา (1995) จำกัด | M91: Not Sellable | O91: 40
A92: Standard | B92: FS-FUFIT-034 | C92: 114001 | D92: 114001 | E92: Honeycomb | F92: Storable Product | G92: กระดาษแข็งรังผึ้ง(Honeycomb) | H92: Honeycomb cardboard | I92: ชิ้น | J92: PC | K92: AP-CMP000 | L92: =IFERROR(VLOOKUP(K92,'Supplier list'!B:C,2,0),"") -> บริษัท จิ่นเหม่ยเปเปอร์ จำกัด | M92: Not Sellable | O92: 5.7
A93: Standard | B93: FS-FUFIT-035 | C93: 114001 | D93: 114001 | E93: Stretch Film | F93: Storable Product | G93: ฟิล์มยืด พันพาเลท 15 | H93: Wrapped film, Pallet | I93: ม้วน | J93: ROLL | K93: AP-YYG000 | L93: =IFERROR(VLOOKUP(K93,'Supplier list'!B:C,2,0),"") -> บริษัท เหย่ายี่ กรุ๊ป จำกัด | M93: Not Sellable | O93: 105
A94: Standard | B94: FS-FUFIT-036 | C94: 114001 | D94: 114001 | E94: EPS Foam | F94: Storable Product | G94: EPS FOAM 710x1320x20mm./0.65 Ib G.ธรรมดา | H94: EPS FOAM 710x1320x20mm./0.65 IB G. | I94: แผ่น | J94: SHEET | L94: =IFERROR(VLOOKUP(K94,'Supplier list'!B:C,2,0),"") | M94: Not Sellable | O94: 43
A95: Standard | B95: FS-FUFIT-037 | C95: 114001 | D95: 114001 | E95: EPS Foam | F95: Storable Product | G95: EPS FOAM 812x1523x20mm./0.65 Ib G.ธรรมดา | H95: EPS FOAM 812x1523x20mm./0.65 IB G. | I95: แผ่น | J95: SHEET | K95: AP-ATC000 | L95: =IFERROR(VLOOKUP(K95,'Supplier list'!B:C,2,0),"") -> บริษัท เอ.ที.คอน อินซูเลชั่น จำกัด | M95: Not Sellable | O95: 43.25
A96: Standard | B96: FS-FUFIT-038 | C96: 114001 | D96: 114001 | E96: Glue | F96: Storable Product | G96: กาวเม็ด White hot melt 7640 | H96: White Hot Melt 7640 | I96: กิโลกรัม | J96: KG | L96: =IFERROR(VLOOKUP(K96,'Supplier list'!B:C,2,0),"") | M96: Not Sellable | O96: 144
A97: Standard | B97: FS-FUFIT-039 | C97: 114001 | D97: 114001 | E97: Battery | F97: Storable Product | G97: แปรงถ่าน Carbon brushes (BOSCH) | H97: Carbon Brushes batteries (Bosch) | I97: ชิ้น | J97: PC | L97: =IFERROR(VLOOKUP(K97,'Supplier list'!B:C,2,0),"") | M97: Not Sellable | O97: 60
A98: Standard | B98: FS-FUFIT-040 | C98: 114001 | D98: 114001 | E98: Glue | F98: Storable Product | G98: HM 9585.0 กาวเม็ดสีเหลือง ใช้กับเครื่องปิดขอบ | H98: HM 9585.0 Yellow granules Used with the edge closing machine | I98: กิโลกรัม | J98: KG | K98: AP-STN002 | L98: =IFERROR(VLOOKUP(K98,'Supplier list'!B:C,2,0),"") -> บริษัท สไตเนอร์ท จำกัด | M98: Not Sellable | O98: 145
A99: Standard | B99: FS-FUFIT-041 | C99: 114001 | D99: 114001 | E99: Polyurethane Tube | F99: Storable Product | G99: สายลม PU 8*12 mm สีส้ม | H99: Wind PU 8*12 mm Orange | I99: เมตร | J99: M | K99: AP-KCR000 | L99: =IFERROR(VLOOKUP(K99,'Supplier list'!B:C,2,0),"") -> บริษัท ก.เจริญฮาร์ดแวร์ จำกัด | M99: Not Sellable | O99: 2250
A100: Standard | B100: FS-FUFIT-042 | C100: 114001 | D100: 114001 | E100: Grease | F100: Storable Product | G100: จารบี TRANE #SUPER HT 5 กก | H100: Grease TRANE #SUPER HT 5 kg. | I100: กระปุก | J100: BOWL | L100: =IFERROR(VLOOKUP(K100,'Supplier list'!B:C,2,0),"") | M100: Not Sellable | O100: 1078
A101: Standard | B101: FS-FUFIT-043 | C101: 114001 | D101: 114001 | E101: Staples | F101: Storable Product | G101: ลูกแม๊กซ์ F20 VIGO | H101: Staples F20 VIGO | I101: กล่อง | J101: BOX | L101: =IFERROR(VLOOKUP(K101,'Supplier list'!B:C,2,0),"") | M101: Not Sellable | O101: 68
A102: Standard | B102: FS-FUFIT-044 | C102: 114001 | D102: 114001 | E102: Staples | F102: Storable Product | G102: ลูกแม๊กซ์ F30 VIGO | H102: Staples F30 VIGO | I102: กล่อง | J102: BOX | L102: =IFERROR(VLOOKUP(K102,'Supplier list'!B:C,2,0),"") | M102: Not Sellable | O102: 60
A103: Standard | B103: FS-FUFIT-045 | C103: 114001 | D103: 114001 | E103: Silicone | F103: Storable Product | G103: ซิลิโคน V-Tech สีใส 24หลอด/ลัง | H103: V-Tech silicone, clear, 24 tubes/box | I103: หลอด | J103: TUBE | K103: AP-GDL000 | L103: =IFERROR(VLOOKUP(K103,'Supplier list'!B:C,2,0),"") -> หจก. กรีน ดิสทริบิวชั่น | M103: Not Sellable | O103: 65
A104: Standard | B104: FS-FUFIT-046 | C104: 114001 | D104: 114001 | E104: Silicone | F104: Storable Product | G104: ซิลิโคน V-Tech สีขาว 24หลอด/ลัง | H104: V-Tech silicone, white, 24 tubes/box | I104: หลอด | J104: TUBE | K104: AP-GDL000 | L104: =IFERROR(VLOOKUP(K104,'Supplier list'!B:C,2,0),"") -> หจก. กรีน ดิสทริบิวชั่น | M104: Not Sellable | O104: 65
A105: Standard | B105: FS-FUFIT-047 | C105: 114001 | D105: 114001 | E105: Silicone | F105: Storable Product | G105: ซิลิโคน (สีดำ) | H105: Silicone (Black) | I105: หลอด | J105: TUBE | K105: AP-GDL000 | L105: =IFERROR(VLOOKUP(K105,'Supplier list'!B:C,2,0),"") -> หจก. กรีน ดิสทริบิวชั่น | M105: Not Sellable | O105: 65
A106: Standard | B106: FS-FUFIT-048 | C106: 114001 | D106: 114001 | E106: Tape | F106: Storable Product | G106: 9089 เทปกาวOPP สีใส 2” x 100 y*45mic 72Pc/Box | H106: Clear Tape Tiger-45 2x100yards 90rolls/box | I106: ม้วน | J106: ROLL | K106: AP-PNPI000 | L106: =IFERROR(VLOOKUP(K106,'Supplier list'!B:C,2,0),"") -> บริษัท พีเอ็นพี อินเตอร์แพค | M106: Not Sellable | O106: 20.5
A107: Standard | B107: FS-FUFIT-049 | C107: 114001 | D107: 114001 | E107: Tape | F107: Storable Product | G107: เทปใส 3(บาง)" | H107: Clear tape 3(thin)" | I107: ม้วน | J107: ROLL | K107: AP-PNPI000 | L107: =IFERROR(VLOOKUP(K107,'Supplier list'!B:C,2,0),"") -> บริษัท พีเอ็นพี อินเตอร์แพค | M107: Not Sellable | O107: 39.24
A108: Standard | B108: FS-FUFIT-050 | C108: 114001 | D108: 114001 | E108: Tape | F108: Storable Product | G108: กระดาษกาวย่น 1.1/2 | H108: Masking tape 1.1/2 | I108: ม้วน | J108: ROLL | K108: AP-CCR000 | L108: =IFERROR(VLOOKUP(K108,'Supplier list'!B:C,2,0),"") -> บริษัท โชคเจริญ 2020 จำกัด | M108: Not Sellable | O108: 14.6
A109: Standard | B109: FS-FUFIT-051 | C109: 114001 | D109: 114001 | E109: Tape | F109: Storable Product | G109: เทปพันเกลียว | H109: Spiral tape | I109: ม้วน | J109: ROLL | K109: AP-TPK001 | L109: =IFERROR(VLOOKUP(K109,'Supplier list'!B:C,2,0),"") -> บริษัท ที.พี.เค ไทยเมท แมชชีนทูลล์ จำกัด | M109: Not Sellable | O109: 10
A110: Standard | B110: FS-FUFIT-052 | C110: 114001 | D110: 114001 | E110: Tape | F110: Storable Product | G110: เทปพันสายไฟ | H110: Wire tape | I110: ม้วน | J110: ROLL | K110: AP-GDL000 | L110: =IFERROR(VLOOKUP(K110,'Supplier list'!B:C,2,0),"") -> หจก. กรีน ดิสทริบิวชั่น | M110: Not Sellable | O110: 12
A111: Standard | B111: FS-FUFIT-053 | C111: 114001 | D111: 114001 | E111: Tape | F111: Storable Product | G111: เทปใส 2 บาง 48mmX45" | H111: Clear tape 2, thin 48mmx45 " | I111: ม้วน | J111: ROLL | L111: =IFERROR(VLOOKUP(K111,'Supplier list'!B:C,2,0),"") | M111: Not Sellable | O111: 169
A112: Standard | B112: FS-FUFIT-054 | C112: 114001 | D112: 114001 | E112: Tape | F112: Storable Product | G112: เทปกาว 2 หน้าบาง 12 มม. 10หลา | H112: 2 -sided adhesive tape 12 mm 10 yards | I112: ม้วน | J112: ROLL | L112: =IFERROR(VLOOKUP(K112,'Supplier list'!B:C,2,0),"") | M112: Not Sellable | O112: 9
A113: Standard | B113: FS-FUFIT-055 | C113: 114001 | D113: 114001 | E113: Detergent | F113: Storable Product | G113: ผงซักฟอกบรีส @ 3000 กรัม | H113: Breeze detergent @ 3000 grams | I113: ถุง | J113: BAG | K113: AP-SMK000 | L113: =IFERROR(VLOOKUP(K113,'Supplier list'!B:C,2,0),"") -> บริษัท สยามแม็คโคร จำกัด (มหาชน) | M113: Not Sellable | O113: 504
A114: Standard | B114: FS-FUFIT-056 | C114: 114001 | D114: 114001 | E114: soap | F114: Storable Product | G114: สบู่ | H114: soap | I114: ก้อน | J114: BAR | K114: AP-SMK000 | L114: =IFERROR(VLOOKUP(K114,'Supplier list'!B:C,2,0),"") -> บริษัท สยามแม็คโคร จำกัด (มหาชน) | M114: Not Sellable | O114: 45
A115: Standard | B115: FS-FUFIT-057 | C115: 114001 | D115: 114001 | E115: Hard broom | F115: Storable Product | G115: ไม้กวาดแข็ง | H115: Hard broom | I115: ด้าม | J115: HANDLE | K115: AP-KSR001 | L115: =IFERROR(VLOOKUP(K115,'Supplier list'!B:C,2,0),"") | M115: Not Sellable | O115: 55
A116: Standard | B116: FS-FUFIT-058 | C116: 114001 | D116: 114001 | E116: Soft broom | F116: Storable Product | G116: ไม้กวาดอ่อน | H116: Soft broom | I116: ด้าม | J116: HANDLE | K116: AP-KSR001 | L116: =IFERROR(VLOOKUP(K116,'Supplier list'!B:C,2,0),"") | M116: Not Sellable | O116: 55
A117: Standard | B117: FS-FUFIT-059 | C117: 114001 | D117: 114001 | E117: Chemical pen | F117: Storable Product | G117: ปากกาเคมี น้ำเงิน | H117: Blue Chemical pen | I117: ชิ้น | J117: PC | K117: AP-COL000 | L117: =IFERROR(VLOOKUP(K117,'Supplier list'!B:C,2,0),"") | M117: Not Sellable | O117: 42.06
A118: Standard | B118: FS-FUFIT-060 | C118: 114001 | D118: 114001 | E118: Chemical pen | F118: Storable Product | G118: ปากกาเคมี ดำ | H118: Black chemical pen | I118: ชิ้น | J118: PC | K118: AP-COL000 | L118: =IFERROR(VLOOKUP(K118,'Supplier list'!B:C,2,0),"") | M118: Not Sellable | O118: 42.06
A119: Standard | B119: FS-FUFIT-061 | C119: 114001 | D119: 114001 | E119: Mop | F119: Storable Product | G119: ไม้ถูพื้น | H119: Mop | I119: ชิ้น | J119: PC | K119: AP-KSR001 | L119: =IFERROR(VLOOKUP(K119,'Supplier list'!B:C,2,0),"") | M119: Not Sellable | O119: 110
A120: Standard | B120: FS-FUFIT-062 | C120: 114001 | D120: 114001 | E120: Mop | F120: Storable Product | G120: ผ้าม๊อบ 12 นิ้ว | H120: 12 inch mob fabric | I120: ชิ้น | J120: PC | L120: =IFERROR(VLOOKUP(K120,'Supplier list'!B:C,2,0),"") | M120: Not Sellable | O120: 119
A121: Standard | B121: FS-FUFIT-063 | C121: 114001 | D121: 114001 | E121: Garbage scoop | F121: Storable Product | G121: ที่ตักขยะ (เหล็ก) | H121: Garbage scoop (steel) | I121: ชิ้น | J121: PC | L121: =IFERROR(VLOOKUP(K121,'Supplier list'!B:C,2,0),"") | M121: Not Sellable | O121: 145
A122: Standard | B122: FS-FUFIT-064 | C122: 114001 | D122: 114001 | E122: Garbage scoop | F122: Storable Product | G122: ที่ตักขยะ (พลาสติก) | H122: Garbage scoop (plastic) | I122: ชิ้น | J122: PC | K122: AP-KSR001 | L122: =IFERROR(VLOOKUP(K122,'Supplier list'!B:C,2,0),"") | M122: Not Sellable | O122: 60
A123: Standard | B123: FS-FUFIT-065 | C123: 114001 | D123: 114001 | E123: Brush | F123: Storable Product | G123: แปรงซักผ้า | H123: Washing brush | I123: ชิ้น | J123: PC | L123: =IFERROR(VLOOKUP(K123,'Supplier list'!B:C,2,0),"") | M123: Not Sellable | O123: 28
A124: Standard | B124: FS-FUFIT-066 | C124: 114001 | D124: 114001 | E124: Brush | F124: Storable Product | G124: แปรง (ห้องน้ำ) | H124: Brush (bathroom) | I124: ชิ้น | J124: PC | K124: AP-COL000 | L124: =IFERROR(VLOOKUP(K124,'Supplier list'!B:C,2,0),"") | M124: Not Sellable | O124: 60.75
A125: Standard | B125: FS-FUFIT-067 | C125: 114001 | D125: 114001 | E125: Brush | F125: Storable Product | G125: สมอแปรงขนทอง (ห้องน้ำ) | H125: Golden hair brush anchor (bathroom) | I125: ชิ้น | J125: PC | L125: =IFERROR(VLOOKUP(K125,'Supplier list'!B:C,2,0),"") | M125: Not Sellable | O125: 28
A126: Standard | B126: FS-FUFIT-068 | C126: 114001 | D126: 114001 | E126: Tape | F126: Storable Product | G126: ตัวตัดเทปใส | H126: Clear tape cutter | I126: ชิ้น | J126: PC | L126: =IFERROR(VLOOKUP(K126,'Supplier list'!B:C,2,0),"") | M126: Not Sellable | O126: 149
A127: Standard | B127: FS-FUFIT-069 | C127: 114001 | D127: 114001 | E127: Polyurethane Tube | F127: Storable Product | G127: สายลม PU 5*8 MM. | H127: Wind PU 5*8 MM. | I127: เมตร | J127: M | K127: AP-KCR000 | L127: =IFERROR(VLOOKUP(K127,'Supplier list'!B:C,2,0),"") -> บริษัท ก.เจริญฮาร์ดแวร์ จำกัด | M127: Not Sellable | O127: 1020
A128: Standard | B128: FS-FUFIT-070 | C128: 114001 | D128: 114001 | E128: Cloth Colour Sheets | F128: Storable Product | G128: ผ้าเย็บวนสีขาว 25 กก. | H128: White Cloth Colour Sheets 25 kg. | I128: กระสอบ | J128: SACK | L128: =IFERROR(VLOOKUP(K128,'Supplier list'!B:C,2,0),"") | M128: Not Sellable | O128: 650
A129: Standard | B129: FS-FUFIT-071 | C129: 114001 | D129: 114001 | E129: Cable tie | F129: Storable Product | G129: เคเบิ้ลไทร์ 12นิ้ว | H129: Cable tie 12 inch | I129: ห่อ | J129: PACK | L129: =IFERROR(VLOOKUP(K129,'Supplier list'!B:C,2,0),"") | M129: Not Sellable | O129: 108
A130: Standard | B130: FS-FUFIT-072 | C130: 114001 | D130: 114001 | E130: Cable tie | F130: Storable Product | G130: เคเบิ้ลไทร์ 6นิ้ว | H130: Cable tie 6 inch | I130: ห่อ | J130: PACK | K130: AP-KSR001 | L130: =IFERROR(VLOOKUP(K130,'Supplier list'!B:C,2,0),"") | M130: Not Sellable | O130: 100
A131: Standard | B131: FS-FUFIT-073 | C131: 114001 | D131: 114001 | E131: Gloves | F131: Storable Product | G131: ถุงมือผ้า 12/โหล | H131: Cloth gloves 12/dozen | I131: คู่ | J131: PAIR | K131: AP-PNPI000 | L131: =IFERROR(VLOOKUP(K131,'Supplier list'!B:C,2,0),"") -> บริษัท พีเอ็นพี อินเตอร์แพค | M131: Not Sellable | O131: 40
A132: Standard | B132: FS-FUFIT-074 | C132: 114001 | D132: 114001 | E132: Mask | F132: Storable Product | G132: ผ้าปิดจมูก 12/โหล | H132: Nose mask 12/dozen | I132: ชิ้น | J132: PC | K132: AP-PNPI000 | L132: =IFERROR(VLOOKUP(K132,'Supplier list'!B:C,2,0),"") -> บริษัท พีเอ็นพี อินเตอร์แพค | M132: Not Sellable | O132: 27.5
A133: Standard | B133: FS-FUFIT-075 | C133: 114001 | D133: 114001 | E133: Strap | F133: Storable Product | G133: สายรัด (สีเหลือง) 12mm.*7.5kg. | H133: Strap (yellow) 12mm.*7.5kg. | I133: ม้วน | J133: ROLL | K133: AP-KCR000 | L133: =IFERROR(VLOOKUP(K133,'Supplier list'!B:C,2,0),"") -> บริษัท ก.เจริญฮาร์ดแวร์ จำกัด | M133: Not Sellable | O133: 390
A134: Standard | B134: FS-FUFIT-076 | C134: 114001 | D134: 114001 | E134: Cable tie | F134: Storable Product | G134: เคเบิ้ลไทร์ 8นิ้ว | H134: Cable tie 8 inch | I134: ห่อ | J134: PACK | L134: =IFERROR(VLOOKUP(K134,'Supplier list'!B:C,2,0),"") | M134: Not Sellable | O134: 145
A135: Standard | B135: FS-FUFIT-077 | C135: 114001 | D135: 114001 | E135: Cable tie | F135: Storable Product | G135: เคเบิ้ลไทร์ 10นิ้ว | H135: Cable tie 10 inch | I135: ห่อ | J135: PACK | L135: =IFERROR(VLOOKUP(K135,'Supplier list'!B:C,2,0),"") | M135: Not Sellable | O135: 83
A136: Standard | B136: FS-FUFIT-078 | C136: 114001 | D136: 114001 | E136: Battery | F136: Storable Product | G136: ถ่านหินเจีย BOSCH 00-06-019 | H136: Coal Grinding BOSCH 00-06-019 | I136: ชุด | J136: SET | K136: AP-TPK001 | L136: =IFERROR(VLOOKUP(K136,'Supplier list'!B:C,2,0),"") -> บริษัท ที.พี.เค ไทยเมท แมชชีนทูลล์ จำกัด | M136: Not Sellable | O136: 55
...

Sheet Supplier list
B1: Code | C1: Name | D1: Street | E1: Street2 | F1: City | G1: City Old | H1: State Old | I1: Country | J1: Zip Code | K1: Company Phone | L1: Email | M1: Tax-ID | N1: Account Receivable | O1: Account Payable | P1: Branch | Q1: Note | R1: payment terms | S1: contact name | T1: contact phone | U1: Credit | V1: discount | W1: credit limit amount | X1: debit limit amount | Y1: account number | Z1: Supplier Rank
A2: 1 | B2: AP-9889000 | C2: บริษัท 9889 Thailnd | D2: 51/44 หมู่ที่4 ต.นาดี | F2: =CONCATENATE(G2,", ",H2) -> อ.เมือง, จ.สมุทรสาคร | G2: อ.เมือง | H2: จ.สมุทรสาคร | I2: Thailand | J2: 74000 | K2: 034-441-398 | L2: sales@9889.co.th | M2: 0105553040468 | P2: สำนักงานใหญ่ | Q2: จำหน่ายอุปกรณ์ตกแต่งภายในที่อยู่อาศัย และเฟอร์นิเจอร์ | S2: คุณแนน | T2: 087-9889-389 | U2: 30 DAYS | Z2: 1
B3: AP-AFA000 | C3: บริษัท เฟรมอลูมิเนียม เฟอร์นิเจอร์ แอนด์ ดีไซด์ จำกัด | D3: 100/102 ซ.พระยามนธาตุราชศรีพิจิตร แยก 29 แขวงคลองบางบอน | F3: =CONCATENATE(G3,", ",H3) -> เขตบางบอน, จ.กรุงเทพฯ | G3: เขตบางบอน | H3: จ.กรุงเทพฯ | I3: Thailand | J3: 10150 | K3: 098-010-6976 | L3: sales@alcustom48@gmail.com | M3: 0105562149744 | P3: สำนักงานใหญ่ | Q3: การผลิตอะลูมิเนียมและผลิตภัณฑ์อะลูมิเนียม | S3: คุณนลิน | T3: - | U3: 0 DAYS | Z3: 1
B4: AP-AGF000 | C4: บริษัท อะโกร ไฟเบอร์ จำกัด | D4: เลขที่ 138 หมู่ 7 ต.ท่าตูม | F4: =CONCATENATE(G4,", ",H4) -> อ.ศรีมหาโพธิ, จ.ปราจีนบุรี | G4: อ.ศรีมหาโพธิ | H4: จ.ปราจีนบุรี | I4: Thailand | J4: 25140 | K4: 038-538-347 | L4: Mkt.agrofiber@gmail.com | M4: 0255547000319 | P4: สำนักงานใหญ่ | Q4: การผลิตแผ่นไม้บางและผลิตภัณฑ์ไม้ | S4: - | T4: - | U4: 30 DAYS | Z4: 1
B5: AP-ALL000 | C5: บริษัท ออล อินดัสตรี เคม จำกัด | D5: 68/40 ซ.นวลน้อย แขวงคลองตันเหนือ | F5: =CONCATENATE(G5,", ",H5) -> เขตวัฒนา, จ.กรุงเทพฯ | G5: เขตวัฒนา | H5: จ.กรุงเทพฯ | I5: Thailand | J5: 10110 | K5: 02-7114458 | L5: admin@allindustrychem.com | M5: 0105551084930 | P5: สำนักงานใหญ่ | Q5: การผลิตเคมีภัณฑ์อนินทรีย์ขั้นมูลฐานอื่น ๆ | S5: คุณฉัตรชัย | T5: 081-9076035 | U5: 30 DAYS | Z5: 1
B6: AP-AMJ000 | C6: Amjay Exports Private Limited | D6: 114 B, Pocket-6, Mayur Vihar Phase-3, | F6: =CONCATENATE(G6,", ",H6) -> New Delhi, Delhi | G6: New Delhi | H6: Delhi | I6: India | J6: 110096 | K6: +91-99102-13095 | L6: mlg@amjayexp.com | M6: AAKCA5721B | P6: สำนักงานใหญ่ | S6: K.Moti | T6: +91-11-22616379 | U6: 0 DAYS | Z6: 1
B7: AP-ARN000 | C7: บริษัท อารีนาเทค จำกัด | D7: 40/134 หมู่ที่14 ต.บางแก้ว | F7: =CONCATENATE(G7,", ",H7) -> อ.บางพลี, จ.สมุทรปราการ | G7: อ.บางพลี | H7: จ.สมุทรปราการ | I7: Thailand | J7: 10540 | K7: 02-334-0996 | L7: arenatech21@gmail.com | M7: 0115564011642 | P7: สำนักงานใหญ่ | S7: คุณเมธวี | T7: 065-0598798 | U7: 0 DAYS | Z7: 1
B8: AP-ASC000 | C8: บริษัท เอเชี่ยน ไซเอนติฟิค จำกัด | D8: 199/1กม.10ม.3ซ.วงษ์แพทย์ถ.เทพารักษ์ ต.บางพลีใหญ่ | F8: =CONCATENATE(G8,", ",H8) -> อ.บางพลี, จ.สมุทรปราการ | G8: อ.บางพลี | H8: จ.สมุทรปราการ | I8: Thailand | J8: 10540 | K8: 02-7574515 | L8: sales@asc-th.com | M8: 0105537002964 | P8: สำนักงานใหญ่ | S8: คุณนุช | T8: ต่อ 105 | U8: 0 DAYS | Z8: 1
B9: AP-ASO000 | C9: บริษัท แอสเซนท์ คอนสตรัคชั่น ซัพพลาย จำกัด | D9: 138/25 ซอยสายไหม 34 (พัธนชัย) ถนนสายไหม แขวงสายไหม | F9: =CONCATENATE(G9,", ",H9) -> เขตสายไหม, จ.กรุงเทพฯ | G9: เขตสายไหม | H9: จ.กรุงเทพฯ | I9: Thailand | J9: 10220 | K9: 02-9915109 | L9: - | M9: 0105556168392 | P9: สำนักงานใหญ่ | S9: - | T9: - | U9: 30 DAYS | Z9: 1
B10: AP-BDM000 | C10: บริษัท ตราเพชร จำกัด | D10: 87 หมู่ 10 ถ.ปู่เจ้าสมิงพราย ต.สำโรงใต้ | F10: =CONCATENATE(G10,", ",H10) -> อ.พระประแดง, จ.สมุทรปราการ | G10: อ.พระประแดง | H10: จ.สมุทรปราการ | I10: Thailand | J10: 10130 | K10: 02-757-6100 | L10: - | M10: 0105516008670 | P10: สำนักงานใหญ่ | S10: คุณจิราวัฒน์ | T10: 097-424-5524 | U10: 60 DAYS | Z10: 1
B11: AP-BES000 | C11: บริษัท เบสต้า กู้ด โปร จำกัด | D11: 103/2 หมู่ 6 ต.บางพลี | F11: =CONCATENATE(G11,", ",H11) -> อ.บางพลี, จ.สมุทรปราการ | G11: อ.บางพลี | H11: จ.สมุทรปราการ | I11: Thailand | J11: 10540 | K11: 02-337-3401-3 | L11: sales@bestapaint.com | M11: 0115547002959 | P11: สำนักงานใหญ่ | Q11: ผลิตและจำหน่ายสีน้ำมัน,สีทา,สีเคลือบ,สีพ่นรับจ้างพ่นสี | S11: - | T11: - | U11: 15 DAYS | V11: 0.2 | Z11: 1
B12: AP-BEST00 | C12: Best Solid Surfaces Corp. | D12: Xishan Economic Developent Zone | F12: =CONCATENATE(G12,", ",H12) -> Wuxi, Jiangsu | G12: Wuxi | H12: Jiangsu | I12: China | J12: 214101 | K12: - | L12: - | M12: - | P12: สำนักงานใหญ่ | S12: - | T12: - | U12: 0 DAYS | Z12: 1
B13: AP-BKM000 | C13: บริษัท บางกอก มาสเตอร์ จำกัด | D13: 276 ซ. อ่อนนุช 35 ถ.อ่อนนุช แขวงสวนหลวง | F13: =CONCATENATE(G13,", ",H13) -> เขตสวนหลวง, กรุงเทพมหานคร | G13: เขตสวนหลวง | H13: กรุงเทพมหานคร | I13: Thailand | J13: 10250 | K13: 02-721-5238 | L13: - | M13: - | P13: สำนักงานใหญ่ | S13: - | T13: - | U13: 0 DAYS | Z13: 1
B14: AP-BPP000 | C14: บริษัท บางพลี แพค (บีพีพี) จำกัด | D14: 113/7 หมู่ 7 ต.บางพลีใหญ่ | F14: =CONCATENATE(G14,", ",H14) -> อ.บางพลี, จ.สมุทรปราการ | G14: อ.บางพลี | H14: จ.สมุทรปราการ | I14: Thailand | J14: 10540 | K14: 02-070-1133 | L14: - | M14: 0115559004196 | P14: สำนักงานใหญ่ | Q14: ผลิตและจัดจำหน่ายน้ำดื่ม | S14: - | T14: - | U14: 0 DAYS | Z14: 1
B15: AP-BTV000 | C15: บริษัท บุญถาวรเซรามิค จำกัด | D15: 15/2 หมู่ที่ 14 ถ.บางนาตราด ต.บางพลีใหญ่ | F15: =CONCATENATE(G15,", ",H15) -> อ.บางพลี, จ.สมุทรปราการ | G15: อ.บางพลี | H15: จ.สมุทรปราการ | I15: Thailand | J15: 10540 | K15: 02-1746888 | L15: CONTACT_CENTER@BOONTHAVORN.COM | M15: 0105535130116 | P15: สำนักงานใหญ่ | Q15: กระเบื้องเซรามิค,สุขภัณฑ์,เฟอร์นิเจอร์,ชุดครัว,หินอ่อน,หินแกรนิต | S15: - | T15: - | U15: 0 DAYS | Z15: 1
B16: AP-BUC001 | C16: ร้าน บุญช่วยรุ่งเรืองค้าไม้ | D16: 44หมู่6 ต.บางเพรียง | F16: =CONCATENATE(G16,", ",H16) -> อ.บางบ่อ, จ.สมุทรปราการ | G16: อ.บางบ่อ | H16: จ.สมุทรปราการ | I16: Thailand | J16: 10560 | K16: 085-0216907,086-2311185 | L16: - | M16: - | P16: สำนักงานใหญ่ | S16: - | T16: - | U16: 0 DAYS | Z16: 1
B17: AP-BUI000 | C17: บริษัท บลู อินเตอร์เนชั่นแนล จำกัด | D17: 8,10,12ซ.รามคำแหง26/1 ถ.รามคำแหง แขวงหัวหมาก | F17: =CONCATENATE(G17,", ",H17) -> เขตบางกะปิ, กรุงเทพมหานคร | G17: เขตบางกะปิ | H17: กรุงเทพมหานคร | I17: Thailand | J17: 10240 | K17: 02-3747744 | L17: - | M17: 0105524001824 | P17: สำนักงานใหญ่ | S17: คุณสมชาย | T17: 084-639-5142 | U17: 30 DAYS | V17: 0.2 | Z17: 1
B18: AP-CAG000 | C18: บริษัท ฉัตรเกศ จำกัด | D18: 61/9 หมู่9 ถ.เทพารักษ์ ต.บางพลีใหญ่ | F18: =CONCATENATE(G18,", ",H18) -> อ.บางพลี, จ.สมุทรปราการ | G18: อ.บางพลี | H18: จ.สมุทรปราการ | I18: Thailand | J18: 10540 | K18: 02-7505880 | L18: - | M18: 0105535095736 | P18: สำนักงานใหญ่ | S18: - | T18: - | U18: 0 DAYS | Z18: 1
B19: AP-CBO000 | C19: ซีโบ เจเนรัล แอนด์ ซัพพลาย | D19: 189/331 ม.6 ต.แพรกษา | F19: =CONCATENATE(G19,", ",H19) -> อ.เมืองสมุทรปราการ, จ.สมุทรปราการ | G19: อ.เมืองสมุทรปราการ | H19: จ.สมุทรปราการ | I19: Thailand | J19: 10280 | K19: 086-5657004 | L19: chiraphat.koi@gmail.com | M19: 3250400406597 | P19: สำนักงานใหญ่ | S19: - | T19: - | U19: 0 DAYS | Z19: 1
B20: AP-CCG000 | C20: บริษัท เซ็นทรัล เคมีคอล 1999 กรุ๊ป จำกัด | D20: 884/1 หมู่ 7 ต.บางปูใหม่ | F20: =CONCATENATE(G20,", ",H20) -> อ.เมืองสมุทรปราการ, จ.สมุทรปราการ | G20: อ.เมืองสมุทรปราการ | H20: จ.สมุทรปราการ | I20: Thailand | J20: 10280 | K20: 02-0699776 | L20: - | M20: 0115555021657 | P20: สำนักงานใหญ่ | S20: คุณแป้ง | T20: 086-334-5087 | U20: 30 DAYS | Z20: 1
B21: AP-CE9000 | C21: บริษัท เจริญอิเล็กทริค999 จำกัด | D21: 49/174 หมู่ 6 ต.บางโพ | F21: =CONCATENATE(G21,", ",H21) -> -, จ.นนทบุรี | G21: - | H21: จ.นนทบุรี | I21: Thailand | J21: 11110 | K21: 094-928-9009 | L21: arnat033@gmail.com | M21: 0105560118949 | P21: สำนักงานใหญ่ | S21: - | T21: - | U21: 0 DAYS | Z21: 1
B22: AP-CHE000 | C22: บริษัท ฉิ้นฮง เอ็นเตอร์ไพรส์ จำกัด | D22: 2 ซอยฉลองกรุง 53 ถนนฉลองกรุง แขวงลำปลาทิว | F22: =CONCATENATE(G22,", ",H22) -> เขตลาดกระบัง, กรุงเทพมหานคร | G22: เขตลาดกระบัง | H22: กรุงเทพมหานคร | I22: Thailand | J22: 10520 | K22: 02-3605087-88 | L22: - | M22: 0105546037252 | P22: สำนักงานใหญ่ | S22: - | T22: - | U22: 30 DAYS | Z22: 1
B23: AP-CHNM00 | C23: Chanzhou Huaeri New Material.co.,Ltd. | D23: NO.2DONGGANG ROND 3 XINBEI DISTRICT | F23: =CONCATENATE(G23,", ",H23) -> Changzhou, Jiangsu | G23: Changzhou | H23: Jiangsu | I23: China | J23: 213127 | K23: - | L23: - | M23: - | P23: สำนักงานใหญ่ | S23: - | T23: - | U23: 0 DAYS | Z23: 1
B24: AP-CIT000 | C24: บริษัท ซิตี้อาร์ตอลูมิเนียมเวอร์ค จำกัด | D24: 56/56 ถ.พระราม 1 แขวงรองเมือง | F24: =CONCATENATE(G24,", ",H24) -> เขตปทุมวัน, กรุงเทพมหานคร | G24: เขตปทุมวัน | H24: กรุงเทพมหานคร | I24: Thailand | J24: 10330 | K24: 02-2151512 | L24: contact@cityart.co.th | M24: 0105531054989 | P24: สำนักงานใหญ่ | S24: - | T24: - | U24: 0 DAYS | Z24: 1
B25: AP-CPS000 | C25: บริษัท ซีพีเอส สเปเซียลตี้ จำกัด | D25: 111/213 หมู่ 8 ถ.ฉลองกรุง แขวงลำปลาทิว | F25: =CONCATENATE(G25,", ",H25) -> เขตลาดกระบัง , กรุงเทพมหานคร | G25: เขตลาดกระบัง | H25: กรุงเทพมหานคร | I25: Thailand | J25: 10520 | K25: 02-7381855 | L25: - | M25: 0135562022400 | P25: สำนักงานใหญ่ | S25: คุณสุวรรณา | T25: - | U25: 0 DAYS | Z25: 1
B26: AP-CPTCP00 | C26: บริษัท แคปิตอล คาร์เปท จำกัด | D26: 32 ซอยอุดมสุข31 แขวงบางจาก | F26: =CONCATENATE(G26,", ",H26) -> เขตพระโขนง , กรุงเทพมหานคร | G26: เขตพระโขนง | H26: กรุงเทพมหานคร | I26: Thailand | J26: 10260 | K26: 02-3838850 | L26: capitalcarpet@hotmail.com,32capital@gmail.com | M26: 0105545076939 | P26: สำนักงานใหญ่ | S26: คุณโก๋ | T26: 081-934-5150 | U26: 0 DAYS | Z26: 1
B27: AP-CRC000 | C27: บริษัท ซีอาร์ซี ไทวัสดุ | D27: 11/15 หมู่ที่ 9 ตำบลบางปลา | F27: =CONCATENATE(G27,", ",H27) -> อ.บางพลี, จ.สมุทรปราการ | G27: อ.บางพลี | H27: จ.สมุทรปราการ | I27: Thailand | J27: 10540 | K27: 02-101-2500 | L27: - | M27: 0105555021215 | P27: สำนักงานใหญ่ | S27: - | T27: - | U27: 0 DAYS | Z27: 1
B28: AP-CRC001 | C28: บริษัท ซีอาร์ซี ไทวัสดุ จำกัด (สาขาบางนา) | D28: 54 หมู่ที่ 13 ตำบลบางแก้ว | F28: =CONCATENATE(G28,", ",H28) -> อำเภอบางพลี, จ.สมุทรปราการ | G28: อำเภอบางพลี | H28: จ.สมุทรปราการ | I28: Thailand | J28: 10540 | K28: 02-101-2500 | L28: - | M28: 0105555021215 | P28: สำนักงานใหญ่ | S28: - | T28: - | U28: 0 DAYS | Z28: 1
B29: AP-CSG000 | C29: บริษัท ซี.เอส.กลาส โพลิชชิ่ง | D29: 33/21 หมู่ที่ 7 ตำบลบางพลีใหญ่ | F29: =CONCATENATE(G29,", ",H29) -> อ.บางพลี, จ.สมุทรปราการ | G29: อ.บางพลี | H29: จ.สมุทรปราการ | I29: Thailand | J29: 10540 | K29: 02-7064394 | L29: - | M29: 0115557001661 | P29: สำนักงานใหญ่ | S29: - | T29: 086-334-8482 | U29: 0 DAYS | Z29: 1
... B80: AP-IYR000 | C80: บริษัท ไอยรา เลเซอร์ ปริ้นท์ จำกัด | D80: 641/90 ถ.อนามัยงามเจริญ แขวงท่าข้าม | F80: =CONCATENATE(G80,", ",H80) -> เขตบางขุนเทียน, กรุงเทพมหานคร | G80: เขตบางขุนเทียน | H80: กรุงเทพมหานคร | I80: Thailand | J80: 10150 | K80: 02-4083465 | L80: - | M80: 0105560004277 | P80: สำนักงานใหญ่ | S80: - | T80: - | U80: 30 DAYS | Z80: 1
B81: AP-JBA000 | C81: บริษัท จัมโบ้เอ อินดัสทรี จำกัด | D81: 23 ม.4 ถ.ติวานนท์ ต.บ้านใหม่ | F81: =CONCATENATE(G81,", ",H81) -> อ.ปากเกร็ด, จ.นนทบุรี | G81: อ.ปากเกร็ด | H81: จ.นนทบุรี | I81: Thailand | J81: 11120 | K81: 086-3050534 | L81: - | M81: 0125534000774 | P81: สำนักงานใหญ่ | Q81: การผลิตโซ่ ลวดสปริง สลักเกลียว และตะปูควง | S81: - | T81: - | U81: 0 DAYS | Z81: 1
B82: AP-JIB000 | C82: บริษัท เจ ไอ บี คอมพิวเตอร์ กรุ๊ป จำกัด | D82: 21 ถ.พหลโยทิน แขวงสนามบิน | F82: =CONCATENATE(G82,", ",H82) -> เขตดอนเมือง, กรุงเทพมหานคร | G82: เขตดอนเมือง | H82: กรุงเทพมหานคร | I82: Thailand | J82: 10210 | K82: 02-7912000 | L82: - | M82: 0135544005281 | P82: สำนักงานใหญ่ | Q82: จำหน่ายคอมพิวเตอร์และอุปกรณ์ที่เกี่ยวข้อง | S82: - | T82: - | U82: 0 DAYS | Z82: 1
B83: AP-JNE000 | C83: บริษัท เจ แนค จำกัด | D83: 339/107 ม.5 ซ.คลองอาเสี่ย ถ.พุทธรักษา ต.แพรกษาใหม่ | F83: =CONCATENATE(G83,", ",H83) -> อ.เมือง, จ.สมุทรปราการ | G83: อ.เมือง | H83: จ.สมุทรปราการ | I83: Thailand | J83: 10280 | K83: 0800161700 | L83: info@jnac.co.th. ,jnac.co.th@gmail.com | M83: 0115553004976 | P83: สำนักงานใหญ่ | Q83: กระดาษทราย จานทรายซ้อน ใบเจียร ใบตัด วัสดุปรับปรุงอาคารและอุปกรณ์ งานขัด ตัด เจาะ เจียร ทุกชนิด | S83: - | T83: - | U83: 0 DAYS | Z83: 1
B84: AP-JPR000 | C84: ร้าน จั่นเพชร รีไซเคิล | D84: 999/8 ม.2 ต.บางปูใหม่ | F84: =CONCATENATE(G84,", ",H84) -> อ.เมือง, จ.สมุทรปราการ | G84: อ.เมือง | H84: จ.สมุทรปราการ | I84: Thailand | J84: 10280 | K84: 02-7095518 | L84: - | M84: - | P84: สำนักงานใหญ่ | S84: คุณนพ | T84: 083-456-7918 | U84: 0 DAYS | Z84: 1
B85: AP-JRP000 | C85: หจก. เจอาร์พีฟลอร์ จำกัด | D85: 108/256 ซ.เฉลิมพระเกียรติ ร.9 แยก28 แขวงดอกไม้ | F85: =CONCATENATE(G85,", ",H85) -> เขตประเวศ, กรุงเทพมหานคร | G85: เขตประเวศ | H85: กรุงเทพมหานคร | I85: Thailand | J85: 10250 | K85: 089-840-2251 | L85: y.jeerasak@hotmail.com | M85: 0103560010666 | P85: สำนักงานใหญ่ | Q85: การก่อสร้างอาคารที่ไม่ใช่ที่พักอาศัย | S85: - | T85: - | U85: 0 DAYS | Z85: 1
B86: AP-JSM000 | C86: บริษัท เจ เอส เมคคานิค จำกัด | D86: 52/10 ม. ถ.เทพกาญจนา ต.คอกกระบือ | F86: =CONCATENATE(G86,", ",H86) -> อ.เมือง, จ.สมุทรสาคร | G86: อ.เมือง | H86: จ.สมุทรสาคร | I86: Thailand | J86: 74000 | K86: 034-441114 | L86: jsm_online@jsmechanic.co.th | M86: 0105545092055 | P86: สำนักงานใหญ่ | Q86: กระดาษทราย | S86: คุณกระแต | T86: 087-496-7865 | U86: 0 DAYS | Z86: 1
B87: AP-K&MAG00 | C87: K&MAG MACHINERY CO.,LTD | D87: No.2,west 8 Road,Jiangcun,Leliu,Shunde, | F87: =CONCATENATE(G87,", ",H87) -> Foshan, Guangdong | G87: Foshan | H87: Guangdong | I87: China | J87: 528322 | K87: - | L87: - | M87: - | P87: สำนักงานใหญ่ | S87: - | T87: - | U87: 0 DAYS | Z87: 1
B88: AP-KAK000 | C88: บริษัท โกรว์ แอนด์ โกลว์ จำกัด | D88: 120/408 ม. 4 ซ. อุ่นอารี ถ. พุทธรักษา ต. ท้ายบ้านใหม่ | F88: =CONCATENATE(G88,", ",H88) -> อ.เมืองสมุทรปราการ, จ.สมุทรปราการ | G88: อ.เมืองสมุทรปราการ | H88: จ.สมุทรปราการ | I88: Thailand | J88: 10280 | K88: 02-3827432 | L88: - | M88: 0115533000428 | P88: สำนักงานใหญ่ | Q88: รับจ้างทากาวผ้า หนัง ฟองน้ำ สำหรับทำเครื่องหนังทุกชนิด | S88: คุณโอ๋ | T88: - | U88: 30 DAYS | Z88: 1
B89: AP-KBK000 | C89: บริษัท คิงบางกอก อินเตอร์เทรด จำกัด | D89: 69/9-11 หมู่ 7 ถนนรามอินทรา กม 4 แขวงท่าแร้ง | F89: =CONCATENATE(G89,", ",H89) -> เขตบางเขน , กรุงเทพมหานคร | G89: เขตบางเขน | H89: กรุงเทพมหานคร | I89: Thailand | J89: 10220 | K89: 02-5093850 | L89: kingproshop.official@gmail.com | M89: 0105545012035 | P89: สำนักงานใหญ่ | Q89: จำหน่ายและติดตั้งเครื่องใช้ไฟฟ้าทุกชนิด | S89: คุณมุ่น | T89: - | U89: 30 DAYS | Z89: 1
B90: AP-KIG000 | C90: บริษัท เค อินฟินิตี้ กรุ๊ป จำกัด(สำนักงานใหญ่) | D90: 47/76 ม.5 ต.ไร่ขิง | F90: =CONCATENATE(G90,", ",H90) -> อ.สามพราน, จ.นครปฐม | G90: อ.สามพราน | H90: จ.นครปฐม | I90: Thailand | J90: 73210 | K90: 098-6152996 | L90: Kinfinitygroup@Gmail.Com | M90: 0735564000149 | P90: สำนักงานใหญ่ | S90: คุณก้อย | T90: - | U90: 0 DAYS | Z90: 1
B91: AP-KKK000 | C91: ร้าน เครื่องครัว | D91: 165/1 หมู่ 11 ต.บางพลีใหญ่ | F91: =CONCATENATE(G91,", ",H91) -> อ.บางพลี, จ.สมุทรปราการ | G91: อ.บางพลี | H91: จ.สมุทรปราการ | I91: Thailand | J91: 10540 | K91: - | L91: - | M91: - | P91: สำนักงานใหญ่ | S91: - | T91: - | U91: 0 DAYS | Z91: 1
B92: AP-KKK001 | C92: ร้าน เครื่องครัว | D92: 13 หมู่ 18 ต.บางพลีใหญ่ | F92: =CONCATENATE(G92,", ",H92) -> อ.บางพลี, จ.สมุทรปราการ | G92: อ.บางพลี | H92: จ.สมุทรปราการ | I92: Thailand | J92: 10540 | K92: - | L92: - | M92: - | P92: สำนักงานใหญ่ | S92: - | T92: - | U92: 0 DAYS | Z92: 1
B93: AP-KKR000 | C93: CO.,LTD Kingkonree International China Surface | D93: Room No. 2408-2508, Building 5A, Longguang Jiuzuan, | F93: =CONCATENATE(G93,", ",H93) -> Longhua District,, Shenzhen, | G93: Longhua District, | H93: Shenzhen, | I93: China | J93: 518000 | K93: +86 -755-82875700 | L93: szkkr@kingkonree.com | M93: - | P93: สำนักงานใหญ่ | S93: Helen Luo | T93: - | U93: 0 DAYS | Z93: 1
B94: AP-KNA000 | C94: บริษัท ก้าวหน้า คอนสตรัคชั่น (2013) | D94: 39/314 หมู่11 ต.บางแก้ว | F94: =CONCATENATE(G94,", ",H94) -> อ.บางพลี, จ.สมุทรปราการ | G94: อ.บางพลี | H94: จ.สมุทรปราการ | I94: Thailand | J94: 10540 | K94: 02-3910919 | L94: - | M94: 0115556015847 | P94: สำนักงานใหญ่ | Q94: รับถมที่ | S94: - | T94: - | U94: 0 DAYS | Z94: 1
B95: AP-KPA000 | C95: บริษัท เคพีเอ แพคกิ้ง แอนด์ โปรดักส์ จำกัด | D95: 144/60 ซ.พระรามเก้า 41 ถ.เสรี 9 แขวงสวนหลวง | F95: =CONCATENATE(G95,", ",H95) -> เขตสวนหลวง, กรุงเทพมหานคร | G95: เขตสวนหลวง | H95: กรุงเทพมหานคร | I95: Thailand | J95: 10250 | K95: 02-85979224-6 | L95: kpa.kanda@gmail.com,kaewchairak@gmail.com | M95: 0105556182514 | P95: สำนักงานใหญ่ | Q95: แผ่นโฟม โฟมพลาสติก ถุงพลาสติก กระสอบพลาสติก | S95: คุณกานดา | T95: - | U95: 30 DAYS | Z95: 1
B96: AP-KPS000 | C96: บริษัท รักษาความปลอดภัย คชรินธร์ ไพศาล เซอร์วิช จำกัด | D96: 58/93 หมู่ 5 ถ.เทพารักษ์ ต.บางพลีใหญ่ | F96: =CONCATENATE(G96,", ",H96) -> อ.บางพลี, จ.สมุทรปราการ | G96: อ.บางพลี | H96: จ.สมุทรปราการ | I96: Thailand | J96: 10540 | K96: 02-3855203 | L96: - | M96: 0115550001712 | P96: สำนักงานใหญ่ | Q96: รักษาความปลอดภัย | S96: - | T96: - | U96: 0 DAYS | Z96: 1
B97: AP-KPS001 | C97: ร้าน การประเสริฐค้าไม้ | D97: 28/30 หมู่13 ต.คลองสอง | F97: =CONCATENATE(G97,", ",H97) -> อ.คลองหลวง, จ.ปทุมธานี | G97: อ.คลองหลวง | H97: จ.ปทุมธานี | I97: Thailand | J97: 12120 | K97: 080-9926127 | L97: - | M97: - | P97: สำนักงานใหญ่ | S97: - | T97: - | U97: 0 DAYS | Z97: 1
B98: AP-KRR000 | C98: นางสาว สุดใจ อินอยู่ (กิจรุ่งเรืองซัพพลาย) | D98: 7/7 ม.21 ต.บางพลีใหญ่ | F98: =CONCATENATE(G98,", ",H98) -> อ.บางพลี, จ.สมุทรปราการ | G98: อ.บางพลี | H98: จ.สมุทรปราการ | I98: Thailand | J98: 10540 | K98: 02-3825170 | L98: - | M98: 3100100451644 | P98: สำนักงานใหญ่ | S98: - | T98: - | U98: 0 DAYS | Z98: 1
B99: AP-KSA000 | C99: นาย คมสันต์ อัศวานุชิต | D99: 152 ถนนนาคนิวาส แขวงลาดพร้าว | F99: =CONCATENATE(G99,", ",H99) -> เขตลาดพร้าว, กรุงเทพมหานคร | G99: เขตลาดพร้าว | H99: กรุงเทพมหานคร | I99: Thailand | J99: 10230 | K99: - | L99: - | M99: 3101702183801 | P99: สำนักงานใหญ่ | S99: - | T99: - | U99: 0 DAYS | Z99: 1
B100: AP-KSP000 | C100: บริษัท เกาสุ แพคกิ้ง อินดัสตรี้ จำกัด | D100: 484 หมู่ 4 ถนนพุทธรักษา ตำบลแพรกษา | F100: =CONCATENATE(G100,", ",H100) -> อำเภอเมือง, จ.สมุทรปราการ | G100: อำเภอเมือง | H100: จ.สมุทรปราการ | I100: Thailand | J100: 10280 | K100: 02-3826750 | L100: alex@kaosu-iwa.com | M100: 0105531030826 | P100: สำนักงานใหญ่ | Q100: โฟมบรรจุหีบห่อ | S100: - | T100: - | U100: 30 DAYS | Z100: 1
B101: AP-KSR000 | C101: บริษัท เคียวเซร่า ด็อคคิวเม้นท์ โซลูชั่นส์ (ประเทศไทย) จำกัด | D101: 335 ถ.รัชดาภิเษก แขวงวงศ์สว่าง | F101: =CONCATENATE(G101,", ",H101) -> เขตบางซื่อ, กรุงเทพมหานคร | G101: เขตบางซื่อ | H101: กรุงเทพมหานคร | I101: Thailand | J101: 10800 | K101: 02-5860333 | L101: - | M101: 0105527026411 | P101: สำนักงานใหญ่ | Q101: การขายเครื่องถ่ายเอกสาร | S101: คุณวาสนา/คุณวีระวัฒน์ | T101: - | U101: 30 DAYS | Z101: 1
B102: AP-KSR001 | C102: บริษัท เกรียงศิริพัฒนา (1995) จำกัด | D102: 34/45 หมู่ 9 ถ.เทพารักษ์ ต.บางพลีใหญ่ | F102: =CONCATENATE(G102,", ",H102) -> อ.บางพลี, จ.สมุทรปราการ | G102: อ.บางพลี | H102: จ.สมุทรปราการ | I102: Thailand | J102: 10540 | K102: 02-3122291,086-4487563 | L102: sale@ksrtool.com | M102: 0115560029628 | P102: สำนักงานใหญ่ | Q102: วัสดุก่อสร้าง | S102: คุณจอย | T102: - | U102: 30 DAYS | Z102: 1
B103: AP-KTW000 | C103: บริษัท กิติวัฒนาพลาสเทค จำกัด | D103: 94/9 หมู่ 8 ถ.ปู่เจ้าสมิงพราย ต.สำโรงใต้ | F103: =CONCATENATE(G103,", ",H103) -> อ.พระประแดง , จ.สมุทรปราการ | G103: อ.พระประแดง | H103: จ.สมุทรปราการ | I103: Thailand | J103: 10130 | K103: 02-1832851 | L103: contact@kitiwitana.com | M103: 0115545006761 | P103: สำนักงานใหญ่ | Q103: จำหน่ายสายยางพลาสติก | S103: - | T103: - | U103: 0 DAYS | Z103: 1
B104: AP-LAB000 | C104: หจก. แล็ป วัลเล่ย์ | D104: 1111/32 โครงการเดอะฮาบิแทท ศรีราวา ถนนศรีวรา แขวงพลับพลา | F104: =CONCATENATE(G104,", ",H104) -> เขตวังทองหลาง, กรุงเทพมหานคร | G104: เขตวังทองหลาง | H104: กรุงเทพมหานคร | I104: Thailand | J104: 10310 | K104: 02-5593509 | L104: labvalley@gmail.com | M104: 0103545018741 | P104: สำนักงานใหญ่ | S104: - | T104: - | U104: 0 DAYS | Z104: 1
B105: AP-LEY000 | C105: บริษัท ลี่หยาง จำกัด | D105: 96 หมู่ 1 ต.คลองนิยมยาตรา | F105: =CONCATENATE(G105,", ",H105) -> อ.บางบ่อ, จ.สมุทรปราการ | G105: อ.บางบ่อ | H105: จ.สมุทรปราการ | I105: Thailand | J105: 10560 | K105: 02-3175505 | L105: Liyang.co@gmail.com | M105: 0115549001879 | P105: สำนักงานใหญ่ | Q105: จำหน่ายวัสดุปะผิว | S105: คุณยุทธ | T105: 088-022-9033 | U105: 0 DAYS | Z105: 1
B106: AP-LHT000 | C106: หจก. ลิ้มเฮง เทพารักษ์(1999) | D106: 1506/605,606 หมู่ 6 ถ.เทพารักษ์ ต.เทพารักษ์ | F106: =CONCATENATE(G106,", ",H106) -> อ.เมือง, จ.สมุทรปราการ | G106: อ.เมือง | H106: จ.สมุทรปราการ | I106: Thailand | J106: 10270 | K106: 02-3851522 | L106: limheng_tepharak@hotmail.com | M106: 0113550003179 | P106: สำนักงานใหญ่ | Q106: น็อต สกรู อะไหล่เครื่องจักร เครื่องยนต์ อุปกรณ์ไฟฟ้า ฮาร์ดแวร์ ทุกชนิด | S106: - | T106: - | U106: 0 DAYS | Z106: 1
B107: AP-LOF000 | C107: บริษัท ลอฟท์ (ประเทศไทย) จำกัด | D107: 221 รามคำแหง 2 ซ.8 แขวงดอกไม้ | F107: =CONCATENATE(G107,", ",H107) -> เขตประเวศ, กรุงเทพมหานคร | G107: เขตประเวศ | H107: กรุงเทพมหานคร | I107: Thailand | J107: 10250 | K107: 0923199914-7 | L107: - | M107: 0105556184673 | P107: สำนักงานใหญ่ | Q107: การขายส่งวัสดุก่อสร้าง | S107: - | T107: - | U107: 0 DAYS | Z107: 1
B108: AP-LRE000 | C108: บริษัท ลีเรคโก (ประเทศไทย) จำกัด | D108: อาคารภิรัช ทาวเวอร์ แอท ไบเทค เลขที่ 4345 ชั้น 16 ถนนสุขุมวิท แขวงบางนา | F108: =CONCATENATE(G108,", ",H108) -> เขตบางนา, กรุงเทพมหานคร | G108: เขตบางนา | H108: กรุงเทพมหานคร | I108: Thailand | J108: 10200 | K108: 02-338-0200 | L108: - | M108: 0105544109337 | P108: สำนักงานใหญ่ | Q108: เครื่องเขียน อุปกรณ์สำนักงาน | S108: คุณสิริลักษณ์(เปิ้ล) | T108: 084-387-8607 | U108: 30 DAYS | Z108: 1
B109: AP-LTN000 | C109: บริษัท ไลท์เทนน่า จำกัด | D109: 282 ถ.วงศ์สว่าง แขวงวงค์สว่าง | F109: =CONCATENATE(G109,", ",H109) -> เขตบางซื่อ, กรุงเทพมหานคร | G109: เขตบางซื่อ | H109: กรุงเทพมหานคร | I109: Thailand | J109: 10800 | K109: 02-9131451 | L109: info@lightenna.co.th | M109: 0105552023659 | P109: สำนักงานใหญ่ | Q109: ขายปลีกอุปกรณ์ไฟฟ้าและแสงสว่าง | S109: - | T109: - | U109: 0 DAYS | Z109: 1
B110: AP-LWK000 | C110: บริษัท เลิศวัฒนกิจ จำกัด | D110: 9 ซ.สุขสวัสดิ์50 แยก 3 ถ.สุขสวัสดิ์ แขวงราษฏร์บูรณะ | F110: =CONCATENATE(G110,", ",H110) -> เขตราษฏร์บูรณะ, กรุงเทพมหานคร | G110: เขตราษฏร์บูรณะ | H110: กรุงเทพมหานคร | I110: Thailand | J110: 10140 | K110: 02-8734809 | L110: - | M110: 0105520009537 | P110: สำนักงานใหญ่ | Q110: จำหน่ายเคมีภัณฑ์ทุกชนิด | S110: - | T110: - | U110: 0 DAYS | Z110: 1
B111: AP-MAP000 | C111: บจ. มิตรอภัย | D111: 1001 ถ.ลาดพร้าว แขวงจันทรเกษม | F111: =CONCATENATE(G111,", ",H111) -> เขตจตุจักร, กรุงเทพมหานคร | G111: เขตจตุจักร | H111: กรุงเทพมหานคร | I111: Thailand | J111: 10900 | K111: 02-9381790 | L111: info@mitrapai.com | M111: 0105520019281 | P111: สำนักงานใหญ่ | Q111: อิฐหินปูนทรายและผลิตภัณฑ์คอนกรีต | S111: - | T111: - | U111: 0 DAYS | Z111: 1
B112: AP-MAY001 | C112: ร้าน มยุรี ค้าไม้ฉำฉา | D112: 479 ม.3 ต.บางปู | F112: =CONCATENATE(G112,", ",H112) -> อ.เมือง, จ.สมุทรปราการ | G112: อ.เมือง | H112: จ.สมุทรปราการ | I112: Thailand | J112: 10280 | K112: 085-3341517,089-5358667 | L112: - | M112: - | P112: สำนักงานใหญ่ | S112: คุณมยุรี | T112: - | U112: 0 DAYS | Z112: 1
B113: AP-MBA000 | C113: บริษัท เอ็ม บี เอ อินเตอร์เนชั่นแนล จำกัด | D113: 55/3 ม.3 ถ.นครอินทร์ ต.บางขุนเทียน | F113: =CONCATENATE(G113,", ",H113) -> อ.บางกรวย, จ.นนทบุรี | G113: อ.บางกรวย | H113: จ.นนทบุรี | I113: Thailand | J113: 11130 | K113: 02-4228422 | L113: - | M113: 0105528021951 | P113: สำนักงานใหญ่ | S113: คุณธนสาร | T113: - | U113: 0 DAYS | Z113: 1
B114: AP-MCC000 | C114: บริษัท เอ็ม.ซี.ซี.เอ็กซิบิชั่น ออกาไนเซอร์ จำกัด | D114: 60 ศูนย์การประชุมแห่งชาติสิริกิติ์ ถ.รัชดาภิเษกตัดใหม่ แขวงคลองเตย | F114: =CONCATENATE(G114,", ",H114) -> เขตคลองเตย, กรุงเทพมหานคร | G114: เขตคลองเตย | H114: กรุงเทพมหานคร | I114: Thailand | J114: 10110 | K114: 02-2293000 | L114: - | M114: 0105537148063 | P114: สำนักงานใหญ่ | Q114: บริการจัดงานแสดงสินค้า จัดประชุมสัมมนา และนิทรรศการ | S114: - | T114: - | U114: 0 DAYS | Z114: 1
B115: AP-MCF000 | C115: บริษัท ไมโคร ไฟเบอร์อุตสาหกรรม จำกัด | D115: 54 ถนนกิ่งแก้ว หมู่ 12 ต.ราชาเทวะ | F115: =CONCATENATE(G115,", ",H115) -> อ.บางพลี, จ.สมุทรปราการ | G115: อ.บางพลี | H115: จ.สมุทรปราการ | I115: Thailand | J115: 10540 | K115: 02-3155500 | L115: inquiry@microfiber.co.th | M115: 0105514005851 | P115: สำนักงานใหญ่ | Q115: ฉนวนกันความร้อนและอุปกรณ์ | S115: คุณจตุพร | T115: 087-321-0114 | U115: 0 DAYS | Z115: 1
B116: AP-MDC000 | C116: บริษัท โมเดอนเคมีเคิล จำกัด | D116: 82/80 ซ.เอกมัย 22(นวลน้อย) ถ.สุขุมวิท 63 แขวงคลองตันเหนือ | F116: =CONCATENATE(G116,", ",H116) -> เขตวัฒนา, กรุงเทพมหานคร | G116: เขตวัฒนา | H116: กรุงเทพมหานคร | I116: Thailand | J116: 10110 | K116: 02-7158979 | L116: service@modernchemical.co.th | M116: 0105514006432 | P116: สำนักงานใหญ่ | Q116: จำหน่ายสารเคมี | S116: คุณอดิศักดิ์ ทองนพรัตน์ หรือคุณแต้ | T116: - | U116: 0 DAYS | Z116: 1
B117: AP-MDC002 | C117: บจ. ไมด้า เคมิคอล | D117: 115/10 ม.3 ซ.ขจรวิทย์ ต.บางพลีใหญ่ | F117: =CONCATENATE(G117,", ",H117) -> อ.บางพลี, จ.สมุทรปราการ | G117: อ.บางพลี | H117: จ.สมุทรปราการ | I117: Thailand | J117: 10540 | K117: 02-1788882,099-323519 | L117: arunya@maidaone.com | M117: 0115559004382 | P117: สำนักงานใหญ่ | Q117: จำหน่ายสารเคมี | S117: คุณบลู | T117: - | U117: 30 DAYS | Z117: 1
B118: AP-MDG000 | C118: บริษัท มาเด กลาส จากัด | D118: 19/1,19/2 ถนนเจ้าคุณทหาร แขวงลำปลาทิว | F118: =CONCATENATE(G118,", ",H118) -> เขตลาดกระบัง, กรุงเทพมหานคร | G118: เขตลาดกระบัง | H118: กรุงเทพมหานคร | I118: Thailand | J118: 10520 | K118: 02-7372297-8 | L118: info.madeglass@gmail.com | M118: 0105563097616 | P118: สำนักงานใหญ่ | Q118: รับแปรรูปกระจก เจียรไนกระจก | S118: คุณยุภา | T118: - | U118: 0 DAYS | Z118: 1
B119: AP-MEA000 | C119: การไฟฟ้านครหลวง | D119: อาคารวัฒนวิภาส เลขที่ 1192 ถ.พระรามที่4 แขวงคลองเตย | F119: =CONCATENATE(G119,", ",H119) -> เขตคลองเตย, กรุงเทพมหานคร | G119: เขตคลองเตย | H119: กรุงเทพมหานคร | I119: Thailand | J119: 10110 | K119: - | L119: webmaster@mea.or.th | M119: 0994000165200 | P119: สำนักงานใหญ่ | Q119: ค่าไฟ | S119: - | T119: - | U119: 0 DAYS | Z119: 1
B120: AP-MEG000 | C120: บริษัท เมกไกวส์ (ไทยแลนด์) จำกัด | D120: 78 อาคารเกียรตินาคิน ชั้น3 ถ.เจริญกรุง 30 แขวงสีลม | F120: =CONCATENATE(G120,", ",H120) -> เขตบางรัก , กรุงเทพมหานคร | G120: เขตบางรัก | H120: กรุงเทพมหานคร | I120: Thailand | J120: 10500 | K120: 02-6390404 | L120: info@meguiars.co.th | M120: 0105544024358 | P120: สำนักงานใหญ่ | Q120: จำหน่ายน้ำยาขัด | S120: คุณเมย์ | T120: 092-435-3337 | U120: 30 DAYS | Z120: 1
B121: AP-MER000 | C121: บริษัท Merck จำกัด | D121: 622 ถนนสุขุมวิท อาคารอิมโพเรียม ชั้น 19 แขวงคลองตัน | F121: =CONCATENATE(G121,", ",H121) -> เขตคลองเตย, กรุงเทพมหานคร | G121: เขตคลองเตย | H121: กรุงเทพมหานคร | I121: Thailand | J121: 10110 | K121: 02-6678000 | L121: service@merckgroup.com | M121: 0105534019122 | P121: สำนักงานใหญ่ | Q121: สินค้าทางเภสัชกรรม เวชภัณฑ์และสินค้าทางการแพทย์ขายปลีกเคมีภัณฑ์ | S121: คุณบงกช | T121: 081-566-1010 | U121: 0 DAYS | Z121: 1
B122: AP-MET000 | C122: บริษัท เมโทร ปาร์ติเกิล จำกัด | D122: 39/5 หมู่ 4 ถนนฤชุพันธ์ ตำบลไทรใหญ๋ | F122: =CONCATENATE(G122,", ",H122) -> อำเภอไทรน้อย , จ.นนทบุรี | G122: อำเภอไทรน้อย | H122: จ.นนทบุรี | I122: Thailand | J122: 11150 | K122: 02-9680800 ต่อ7535 | L122: metro@metroply.com | M122: 0125545007309 | P122: สำนักงานใหญ่ | Q122: แผ่นไม้อัด PARTICLE BOARD | S122: คุณณิชา (ไก่) | T122: 088-022-7814 | U122: 0 DAYS | Z122: 1
B123: AP-MET001 | C123: เมธีกุล (แปดริ้ว) | D123: 888/89 ม.2 ต.แพรกษาใหม่ | F123: =CONCATENATE(G123,", ",H123) -> อ.เมืองสมุทรปราการ, จ.สมุทรปราการ | G123: อ.เมืองสมุทรปราการ | H123: จ.สมุทรปราการ | I123: Thailand | J123: 10280 | K123: 02-3384199 | L123: - | M123: 0105538116262 | P123: สำนักงานใหญ่ | Q123: ซื้อมาขายไป สายไฟและอุปกรณ์ไฟฟ้าทุกชนิด | S123: - | T123: - | U123: 0 DAYS | Z123: 1
B124: AP-MHT000 | C124: มายโฮม เคอร์เท่น | D124: 6/514 ซ.พระยาสุเรนทร์ 33 แขวงบางชัน | F124: =CONCATENATE(G124,", ",H124) -> เขตคลองสามวา, กรุงเทพมหานคร | G124: เขตคลองสามวา | H124: กรุงเทพมหานคร | I124: Thailand | J124: 10510 | K124: - | L124: jirapan@ymail.com | M124: 3540500262101 | P124: สำนักงานใหญ่ | S124: - | T124: - | U124: 0 DAYS | Z124: 1
B125: AP-MKI000 | C125: บริษัท หมิง กว้าน อินดัสตรี้ จำกัด | D125: 10/10 หมู่ 8 ถ.พุทธรักษา ต.ท้ายบ้าน | F125: =CONCATENATE(G125,", ",H125) -> อ.เมือง, จ.สมุทรปราการ | G125: อ.เมือง | H125: จ.สมุทรปราการ | I125: Thailand | J125: 10280 | K125: 02-3952548 | L125: - | M125: 0115547010242 | P125: สำนักงานใหญ่ | S125: - | T125: - | U125: 30 DAYS | Z125: 1
B126: AP-MKP000 | C126: บริษัท เอ็มเค โพลีเอสเตอร์เรซิ่น จำกัด | D126: 27/12 หมู่ที่ 1 ต.บางน้ำจืด | F126: =CONCATENATE(G126,", ",H126) -> อ.เมือง, จ.สมุทรสาคร | G126: อ.เมือง | H126: จ.สมุทรสาคร | I126: Thailand | J126: 74000 | K126: 088-809-5271 | L126: sale-mk@hotmail.com | M126: 0105545061311 | P126: สำนักงานใหญ่ | Q126: การตกแต่งและการเคลือบโลหะ | S126: คุณยุทธนา | T126: - | U126: 0 DAYS | Z126: 1
B127: AP-MKW000 | C127: บริษัท เอ็มเค วู้ดเทค จำกัด | D127: 78 หมู่ 4 ซ.คลองมะเดื่อ 13 ถ.เศรษฐกิจ ต.คลองมะเดื่อ | F127: =CONCATENATE(G127,", ",H127) -> อ.กระทุ่มแบน, จ.สมุทรสาคร | G127: อ.กระทุ่มแบน | H127: จ.สมุทรสาคร | I127: Thailand | J127: 74110 | K127: 034-878070 | L127: mkw@mkw.co.th | M127: 0745546000868 | P127: สำนักงานใหญ่ | Q127: ผลิต รับจ้าง ผลิตภัณฑ์ไม้เพื่อทำเฟอร์นิเจอร์ | S127: คุณเดือน | T127: 089-8101519 | U127: 60 DAYS | Z127: 1
B128: AP-MMA000 | C128: บริษัท เมลามีน อาร์ท จำกัด | D128: 59/1 หมู่ 2 ต.ท่าทราย | F128: =CONCATENATE(G128,", ",H128) -> อ.เมือง, จ.สมุทรสาคร | G128: อ.เมือง | H128: จ.สมุทรสาคร | I128: Thailand | J128: 74000 | K128: 086-6160473 | L128: contact@melamineart.info | M128: 0745548003783 | P128: สำนักงานใหญ่ | Q128: จำหน่ายไม้แปรรูปและผลิตภัณฑ์ทำจากไม้ | S128: - | T128: - | U128: 7 DAYS | Z128: 1
B129: AP-MMI000 | C129: บจ. แม แม อินดัสเตรียล | D129: 630 ม.4 ถ.สุขุมวิท ต.แพรกษา | F129: =CONCATENATE(G129,", ",H129) -> อ.เมือง, จ.สมุทรปราการ | G129: อ.เมือง | H129: จ.สมุทรปราการ | I129: Thailand | J129: 10280 | K129: 02-7093027 | L129: contact@maemae.co.th | M129: 0105532073031 | P129: สำนักงานใหญ่ | Q129: ผลิตและจำหน่ายกล่องกระดาษและสติ๊กเกอร์ | S129: - | T129: - | U129: 0 DAYS | Z129: 1
B130: AP-MRC000 | C130: บริษัท ไมร่า คอมพิวเตอร์ อินเตอร์เนชั่นแนล จำกัด | D130: 509,511 ถนนรามอินทรา แขวง คันนายาว | F130: =CONCATENATE(G130,", ",H130) -> เขตคันนายาว, กรุงเทพมหานคร | G130: เขตคันนายาว | H130: กรุงเทพมหานคร | I130: Thailand | J130: 10230 | K130: 02-9431890-9 | L130: marketing@miratechs.com,pan1121@miratechs.com | M130: 0105534121555 | P130: สำนักงานใหญ่ | Q130: จำหน่ายคอมพิวเตอร์และอุปกรณ์ที่เกี่ยวข้อง | S130: คุณสุปราณี ชื่นฤทัย(บัว) | T130: 095-1648761 | U130: 0 DAYS | Z130: 1
B131: AP-MSM000 | C131: บจ. เอ็มเอส แอสซิสแตนซ์ (ประเทศไทย) | D131: 256/1,256/2 ถ.เพชรเกษม ต.หัวหิน | F131: =CONCATENATE(G131,", ",H131) -> อ.หัวหิน , จ.ประจวบคีรีขันธ์ | G131: อ.หัวหิน | H131: จ.ประจวบคีรีขันธ์ | I131: Thailand | J131: 77110 | K131: - | L131: - | M131: 0775563001460 | P131: สำนักงานใหญ่ | Q131: ขายส่งเฟอร์นิเจอร์ อุปกรณ์ตกแต่งบ้านได้รับค่าตอบแทนตามสัญญาจ้าง | S131: - | T131: - | U131: 0 DAYS | Z131: 1
B132: AP-MTD000 | C132: บริษัท เอ็ม.ที.ดี.อิเลคทริคคอล เวิร์ค จำกัด | D132: 176/28 หมู่ 4 ต.ปลวกแดง | F132: =CONCATENATE(G132,", ",H132) -> อ.ปลวกแดง, จ.ระยอง | G132: อ.ปลวกแดง | H132: จ.ระยอง | I132: Thailand | J132: 21140 | K132: 088-355-2465 | L132: - | M132: 0215559008972 | P132: สำนักงานใหญ่ | Q132: การติดตั้งไฟฟ้า | S132: - | T132: - | U132: 0 DAYS | Z132: 1
B133: AP-MTK000 | C133: หจก. ไมตรีการพิมพ์ | D133: 1024/33 34 ซอยเจริญสุข ถนนพระราม 4 | F133: =CONCATENATE(G133,", ",H133) -> เขตพระโขนง, กรุงเทพมหานคร | G133: เขตพระโขนง | H133: กรุงเทพมหานคร | I133: Thailand | J133: 10110 | K133: 02-258-3021 | L133: - | M133: 0103525016165 | P133: สำนักงานใหญ่ | Q133: รับจ้างพิมพ์สิ่งพิมพ์ต่างๆ | S133: คุณไมตรี | T133: - | U133: 30 DAYS | Z133: 1
B134: AP-MTM000 | C134: บริษัท เมโทร เอ็ม.ดี.เอฟ จำกัด | D134: 99/9 หมู่ 5 ต.หวายเหนียว | F134: =CONCATENATE(G134,", ",H134) -> อ.ท่ามะกา , จ.กาญจนบุรี | G134: อ.ท่ามะกา | H134: จ.กาญจนบุรี | I134: Thailand | J134: 71120 | K134: 089-819-5444 | L134: metro@metroply.com | M134: 0715557000015 | P134: สำนักงานใหญ่ | Q134: แผ่นใยไม้อัดความหนาแน่นปานกลางและสูง | S134: คุณอ้อม | T134: 089-819-5444 | U134: 0 DAYS | Z134: 1
B135: AP-MTP000 | C135: บริษัท มัลติเพิลพลัส จำกัด | D135: 29/12 ม.5 ต.กระทุ่มล้ม | F135: =CONCATENATE(G135,", ",H135) -> อ.สามพราน , จ.นครปฐม | G135: อ.สามพราน | H135: จ.นครปฐม | I135: Thailand | J135: 73220 | K135: 02-8131020 | L135: SALES@MULTIPLEPLUS.COM | M135: 0125548002600 | P135: สำนักงานใหญ่ | Q135: จำหน่ายเคมีภัณฑ์ | S135: คุณภุมวรรณ (อุ๋ย) | T135: 090-678-4697,086-665-6339 | U135: 30 DAYS | Z135: 1
B136: AP-MTP001 | C136: บริษัท เมโทรพูนทรัพย์ จำกัด | D136: เลขที่ 46 ชั้นที่ 1 ซอยนนทบุรี 8 ถ.นนทบุรี 1 ต.บางกระสอ | F136: =CONCATENATE(G136,", ",H136) -> อ.เมืองนนทบุรี, จ.นนทบุรี | G136: อ.เมืองนนทบุรี | H136: จ.นนทบุรี | I136: Thailand | J136: 11000 | K136: 087-5442525 | L136: - | M136: 0125528000270 | P136: สำนักงานใหญ่ | Q136: ผลิตและจำหน่ายไม้แปรรูป | S136: คุณบุญชัย | T136: 087-5442525 | U136: 0 DAYS | Z136: 1
B137: AP-MTPB00 | C137: บริษัท เมโทร ปาร์ติเกิล จำกัด | D137: 39/5 หมู่4 ต.ไทรใหญ่ | F137: =CONCATENATE(G137,", ",H137) -> อ.ไทรน้อย, จ.นนทบุรี | G137: อ.ไทรน้อย | H137: จ.นนทบุรี | I137: Thailand | J137: 11150 | K137: 02 044 5555 | L137: metro@metroply.com | M137: 0125545007309 | P137: สำนักงานใหญ่ | Q137: ผลิตและจำหน่ายไม้แปรรูป | S137: - | T137: - | U137: 0 DAYS | Z137: 1
... B139: AP-MWT000 | C139: บริษัท เอ็ม วอเตอร์ จำกัด | D139: 1 ซอยวิภาวดีรังสิต 1 แยก 1 แขวงสนามบิน | F139: =CONCATENATE(G139,", ",H139) -> เขตดอนเมือง, กรุงเทพมหานคร | G139: เขตดอนเมือง | H139: กรุงเทพมหานคร | I139: Thailand | J139: 10210 | K139: 02-5334630 | L139: info@sprinkle-th.com | M139: 0105528012502 | P139: สำนักงานใหญ่ | Q139: จำหน่ายน้ำดื่ม | S139: - | T139: - | U139: 30 DAYS | Z139: 1
B140: AP-NN000 | C140: บริษัท แนวหน้าค้าไม้ จำกัด | D140: 113-125 ซอยเอกชัย 69 แขวงคลองบางบอน | F140: =CONCATENATE(G140,", ",H140) -> เขตบางบอน , กรุงเทพมหานคร | G140: เขตบางบอน | H140: กรุงเทพมหานคร | I140: Thailand | J140: 10150 | K140: 02-8995779-81 | L140: nalna@hotmail.co.th | M140: 0105556005787 | P140: สำนักงานใหญ่ | S140: - | T140: - | U140: 0 DAYS | Z140: 1
B141: AP-NCC000 | C141: บริษัท เอ็น.ซี.ซี. อิมเมจ | D141: 90อาคารซีดับเบิ้ลยู ทาวเวอร์ ชั้น 5 ถ.รัชดาภิเษก แขวงห้วยขวาง | F141: =CONCATENATE(G141,", ",H141) -> เขตห้วยขวาง, กรุงเทพมหานคร | G141: เขตห้วยขวาง | H141: กรุงเทพมหานคร | I141: Thailand | J141: 10310 | K141: - | L141: csimage@qsncc.com | M141: 0105538011258 | P141: สำนักงานใหญ่ | S141: - | T141: - | U141: 0 DAYS | Z141: 1
B142: AP-NNK000 | C142: บริษัท แนวหน้าค้าไม้ จำกัด (สำนักงานใหญ่) | D142: 113 125 ซอยเอกชัย 69 แขวงคลองบางบอน | F142: =CONCATENATE(G142,", ",H142) -> เขตบางบอน, กรุงเทพมหานคร | G142: เขตบางบอน | H142: กรุงเทพมหานคร | I142: Thailand | J142: 10150 | K142: 02-8995779-81 | L142: nalna@hotmail.co.th | M142: 0105556005787 | P142: สำนักงานใหญ่ | Q142: การขายส่งไม้และผลิตภัณฑ์จากไม้แปรรูปขั้นต้น | S142: - | T142: - | U142: 0 DAYS | Z142: 1
B143: AP-NTK000 | C143: หจก. นำทองค้าไม้ | D143: 46-46/1 ซ.บรมบรรพด ถ.จักรพรรดิพงษ์ ต.บ้านบาตร | F143: =CONCATENATE(G143,", ",H143) -> อ.ป้อมปราบศัตรูพ่าย , กรุงเทพมหานคร | G143: อ.ป้อมปราบศัตรูพ่าย | H143: กรุงเทพมหานคร | I143: Thailand | J143: 10100 | K143: 02 621 1342 | L143: numthongwood@gmail.com | M143: 0103525010612 | P143: สำนักงานใหญ่ | Q143: ประกอบกิจการขายไม้แปรรูป | S143: - | T143: - | U143: 0 DAYS | Z143: 1
B144: AP-NVK000 | C144: บริษัท นวกิจประกันภัย จำกัด (มหาชน) | D144: 100/47 55,90/3-6 ถนนสาทรเหนือ แขวงสีลม | F144: =CONCATENATE(G144,", ",H144) -> เขตบางรัก , กรุงเทพมหานคร | G144: เขตบางรัก | H144: กรุงเทพมหานคร | I144: Thailand | J144: 10500 | K144: 02-6617777 | L144: - | M144: 0107538000862 | P144: สำนักงานใหญ่ | Q144: ประกันภัย | S144: - | T144: - | U144: 0 DAYS | Z144: 1
B145: AP-ORI000 | C145: บริษัท โอเรียนสตาร์ อินเตอร์เนชั่นแนล โลจีสติคส์ จำกัด | D145: 71/30ถนนบรมราชชนนี แขวงอรุณอมรินทร์ | F145: =CONCATENATE(G145,", ",H145) -> เขตบางกอกน้อย, กรุงเทพมหานคร | G145: เขตบางกอกน้อย | H145: กรุงเทพมหานคร | I145: Thailand | J145: 10700 | K145: 02-8848666 | L145: - | M145: 0105543061195 | P145: สำนักงานใหญ่ | S145: คุณลีน | T145: - | U145: 0 DAYS | Z145: 1
B146: AP-OSH000 | C146: บริษัท สมาคมส่งเสริมความปลอดภัยและอนามัยในการทำงาน (ประเทศไทย) | D146: 141 ถนนบรมราชชนนี แขวงฉิมพลี | F146: =CONCATENATE(G146,", ",H146) -> เขตตลิ่งชัน, กรุงเทพมหานคร | G146: เขตตลิ่งชัน | H146: กรุงเทพมหานคร | I146: Thailand | J146: 10170 | K146: 02-880-4803,02-884-1852,02-403-1606-12 | L146: - | M146: - | P146: สำนักงานใหญ่ | S146: - | T146: - | U146: 0 DAYS | Z146: 1
B147: AP-PAT000 | C147: บริษัท พลาโท ออดิโอ คอร์ปอเรชั่น | D147: 128 ซอยสุภาพงษ์ 1 แขวงหนองบอน | F147: =CONCATENATE(G147,", ",H147) -> เขตประเวศ, กรุงเทพมหานคร | G147: เขตประเวศ | H147: กรุงเทพมหานคร | I147: Thailand | J147: 10250 | K147: 02-7482496 | L147: - | M147: 0105538131849 | P147: สำนักงานใหญ่ | Q147: รับเป็นที่ปรึกษาและให้คำแนะนำปัญหาเกี่ยวกับด้านบริหารงานพาณิชยกรรม อุตสาหกรรม รวมทั้งปัญหาการผลิต | S147: จิรดา | T147: - | U147: 0 DAYS | Z147: 1
B148: AP-PCF000 | C148: บริษัท แปซิฟิค ค้าไม้ จำกัด | D148: 56/8 ถ.สมเด็จพระเจ้าตากสิน แขวงบุคคโล | F148: =CONCATENATE(G148,", ",H148) -> เขตธนบุรี , กรุงเทพมหานคร | G148: เขตธนบุรี | H148: กรุงเทพมหานคร | I148: Thailand | J148: 10600 | K148: 02-8905051-5 | L148: pacific@pacific-wood.com | M148: 0105532037859 | P148: สำนักงานใหญ่ | Q148: ซื้อ ขายส่ง-ปลีก นำเข้า ส่งออกไม้สำหรับทำพื้น | S148: - | T148: - | U148: 0 DAYS | Z148: 1
B149: AP-PCL000 | C149: บริษัท เพมโก้ อินเตอร์ไลท์ จำกัด | D149: 61 ท่าข้าม 9 ถ.พระรา2 แขวงแสมดำ | F149: =CONCATENATE(G149,", ",H149) -> เขตบางขุนเทียน, กรุงเทพมหานคร | G149: เขตบางขุนเทียน | H149: กรุงเทพมหานคร | I149: Thailand | J149: 10150 | K149: 02-7502795-8 | L149: - | M149: 0105540008960 | P149: สำนักงานใหญ่ | Q149: จำหน่ายโคมไฟประดับและเฟอร์นิเจอร์ | S149: - | T149: - | U149: 0 DAYS | Z149: 1
B150: AP-PCS000 | C150: บริษัท พรีซิชั่นไลน์ จำกัด | D150: 93 หมู่ 5 ตำบลลำลูกกา | F150: =CONCATENATE(G150,", ",H150) -> อ.ลำลูกกา , จ.ปทุมธานี | G150: อ.ลำลูกกา | H150: จ.ปทุมธานี | I150: Thailand | J150: 12150 | K150: 02-1992518 | L150: marketing.p@furniline.co.th | M150: 0105537134178 | P150: สำนักงานใหญ่ | Q150: อุปกรณ์เครื่องเฟอร์นิเจอร์ | S150: - | T150: - | U150: 60 DAYS | Z150: 1
B151: AP-PIL000 | C151: บริษัท ไพลอต โลจิสติคส์ จำกัด | D151: 2024/137ถนนริมทางรถไฟสายปากน้ำ แขวงพระโขนง | F151: =CONCATENATE(G151,", ",H151) -> เขตคลองเตย, กรุงเทพมหานคร | G151: เขตคลองเตย | H151: กรุงเทพมหานคร | I151: Thailand | J151: 10260 | K151: - | L151: qualityservice@pilotlogistics.net | M151: 015547016275 | P151: สำนักงานใหญ่ | Q151: นายหน้าตัวแทนพิธีการศุลกากร | S151: คุณจูน | T151: - | U151: 0 DAYS | Z151: 1
...

Sheet Category
A1: Product Category
A2: Tape
A3: buy-sell
A4: Service
A5: Carpet
A6: Cardboard cylinder
A7: Honeycomb
A8: Tool
A9: Sandpaper
A10: Battery
A11: Drill bits
A12: Light bulb
... A179: Non Standard

Sheet Accounts
A1: Product Account
A2: 513010
A3: 513010
A4: 513010
A5: 513010
A6: 513010
A7: 513010
A8: 513010
A9: 513010
A10: 513010
A11: 513025
A12: 513025
A13: 513025
... A1709: 513004

Sheet UOM
A1: UOM EN
A2: PC
A3: JOB
A4: SQM
A5: SHEET
A6: TUBE
A7: SET
A8: BOX
A9: BOTTLES
A10: STRIP
A11: ROLL
A12: PANEL
... A32: DISK

Sheet Country
A1: Country
A3: Thailand
A4: Thailand
A5: Thailand
A6: Thailand
A7: India
A8: Thailand
A9: Thailand
A10: Thailand
A11: Thailand
A12: Thailand
A13: China
... A621: Thailand

Sheet Payment Terms
A1: Credit
A2: 30 DAYS
A3: 0 DAYS
A4: 60 DAYS
A5: 15 DAYS
A6: 7 DAYS
A7: 90 DAYS

Sheet Product 1-651
A1: Standardize | B1: Product Code | C1: Income Account | D1: Expense Account | E1: Product Category | F1: Product Type | G1: Product Name TH | H1: Product Name EN | I1: UOM TH | J1: UOM EN | K1: Code Supplier | L1: Supplier Name | M1: True/False | N1: Selling Price | O1: Cost Price
A2: Standard | B2: AX-3M233-TH | C2: 513010 | D2: 513010 | E2: Tape | F2: Storable Product | G2: เทปกาว 3M | H2: Masking tape | I2: ชิ้น | J2: PC | K2: AP-CST000 | L2: =IFERROR(VLOOKUP(K2,'Supplier list'!B:C,2,0),"") | M2: =FALSE() -> 0 | O2: 202
A3: Standard | B3: AX-513004-TH | C3: 513010 | D3: 513010 | E3: buy-sell | F3: Storable Product | G3: ซื้อมา-ขายไป | H3: Buy-Sell | I3: ชิ้น | J3: PC | K3: - | L3: =IFERROR(VLOOKUP(K3,'Supplier list'!B:C,2,0),"") | M3: =FALSE() -> 0 | O3: 0
A4: Standard | B4: AX-513006-TH | C4: 513010 | D4: 513010 | E4: Service | F4: Storable Product | G4: ค่าใช้จ่าย-นำเข้า | H4: Import Fee | I4: งาน | J4: JOB | K4: - | L4: =IFERROR(VLOOKUP(K4,'Supplier list'!B:C,2,0),"") | M4: =FALSE() -> 0 | O4: 0
A5: Standard | B5: AX-513007-TH | C5: 513010 | D5: 513010 | E5: Service | F5: Storable Product | G5: ค่าใช้จ่าย-ส่งออก | H5: Export Fee | I5: งาน | J5: JOB | K5: - | L5: =IFERROR(VLOOKUP(K5,'Supplier list'!B:C,2,0),"") | M5: =FALSE() -> 0 | O5: 0
A6: Standard | B6: AX-531016-TH | C6: 513010 | D6: 513010 | E6: Service | F6: Storable Product | G6: ค่าสวัสดิการอื่นๆ-เลี้ยงข้าวพนักงาน | H6: Other welfare expenses - food for employees | I6: งาน | J6: JOB | K6: - | L6: =IFERROR(VLOOKUP(K6,'Supplier list'!B:C,2,0),"") | M6: =FALSE() -> 0 | O6: 0
A7: Standard | B7: AX-CGM00-TH | C7: 513010 | D7: 513010 | E7: Tape | F7: Storable Product | G7: เทปกาว | H7: Masking tape | I7: ชิ้น | J7: PC | K7: AP-BNT000 | L7: =IFERROR(VLOOKUP(K7,'Supplier list'!B:C,2,0),"") | M7: =FALSE() -> 0 | O7: 84
A8: Standard | B8: AX-PH007-TH | C8: 513010 | D8: 513010 | E8: Carpet | F8: Storable Product | G8: พื้นพรมแผ่นรุ่น PH07 | H8: Carpet floor sheet model PH07 | I8: ตรม. | J8: SQM | K8: AP-SFL000 | L8: =IFERROR(VLOOKUP(K8,'Supplier list'!B:C,2,0),"") | M8: =FALSE() -> 0 | O8: 680
A9: Standard | B9: AX-PT00-001 | C9: 513010 | D9: 513010 | E9: Cardboard cylinder | F9: Storable Product | G9: Paper Tube/กระบอกภาชนะกระดาษแข็ง | H9: Cardboard cylinder with spray paint | I9: ชิ้น | J9: PC | K9: AP-QNL000 | L9: =IFERROR(VLOOKUP(K9,'Supplier list'!B:C,2,0),"") -> CO.,LTD QINGDAO NEW LIBERTY INT'L TRADING CO.LTD. | M9: =FALSE() -> 0 | O9: 0.35
A10: Standard | B10: AX-PT00-002 | C10: 513010 | D10: 513010 | E10: Service | F10: Storable Product | G10: ค่าส่งสินค้าอื่นๆ | H10: Other shipping costs | I10: งาน | J10: JOB | K10: - | L10: =IFERROR(VLOOKUP(K10,'Supplier list'!B:C,2,0),"") | M10: =FALSE() -> 0 | O10: 0
A11: Standard | B11: FC-0001 | C11: 513025 | D11: 513025 | E11: Honeycomb | F11: Storable Product | G11: กระดาษรังผึ้ง honeycomb กว้าง60xยาว30 หนา10 cm. | H11: Honey Comb 60x30x10 cm. | I11: ชิ้น | J11: PC | K11: AP-QNL000 | L11: =IFERROR(VLOOKUP(K11,'Supplier list'!B:C,2,0),"") -> CO.,LTD QINGDAO NEW LIBERTY INT'L TRADING CO.LTD. | M11: =FALSE() -> 0 | O11: 5.7
A12: Standard | B12: FC-0002 | C12: 513025 | D12: 513025 | E12: Tool | F12: Storable Product | G12: เครื่องเจียร์ไฟฟ้า 4" MAKITA 9500NB | H12: Electric Grinder 4MAKITA9500NB" | I12: ชิ้น | J12: PC | K12: AP-GDL000 | L12: =IFERROR(VLOOKUP(K12,'Supplier list'!B:C,2,0),"") -> หจก. กรีน ดิสทริบิวชั่น | M12: =FALSE() -> 0 | O12: 2990
A13: Standard | B13: FC-0003 | C13: 513025 | D13: 513025 | E13: Tool | F13: Storable Product | G13: ถังกาพ่น M-871 | H13: Spray Gun M-871 | I13: ชิ้น | J13: PC | K13: - | L13: =IFERROR(VLOOKUP(K13,'Supplier list'!B:C,2,0),"") | M13: =FALSE() -> 0 | O13: 4200
... A23: Standard | B23: FC-0013 | C23: 513025 | D23: 513025 | E23: Light bulb | F23: Storable Product | G23: หลอดไฟ (ยาว) | H23: Light bulb (long) | I23: หลอด | J23: TUBE | K23: AP-TPK001 | L23: =IFERROR(VLOOKUP(K23,'Supplier list'!B:C,2,0),"") -> บริษัท ที.พี.เค ไทยเมท แมชชีนทูลล์ จำกัด | M23: =FALSE() -> 0 | O23: 229
A24: Standard | B24: FC-0014 | C24: 513025 | D24: 513025 | E24: Light bulb | F24: Storable Product | G24: หลอดไฟ (สั้น) | H24: Light bulb (short) | I24: หลอด | J24: TUBE | L24: =IFERROR(VLOOKUP(K24,'Supplier list'!B:C,2,0),"") | M24: =FALSE() -> 0 | O24: 63
A25: Standard | B25: FC-0015 | C25: 513025 | D25: 513025 | E25: Tool | F25: Storable Product | G25: หัวปืน M-871 (จีน) | H25: Gun head M-871 (China) | I25: ชิ้น | J25: PC | K25: - | L25: =IFERROR(VLOOKUP(K25,'Supplier list'!B:C,2,0),"") | M25: =FALSE() -> 0 | O25: 0
A26: Standard | B26: FC-0016 | C26: 513025 | D26: 513025 | E26: Tool | F26: Storable Product | G26: หัวจี้ลม แกน 3 mm. | H26: Air pendant 3 mm. | I26: ชิ้น | J26: PC | K26: - | L26: =IFERROR(VLOOKUP(K26,'Supplier list'!B:C,2,0),"") | M26: =FALSE() -> 0 | O26: 0
A27: Standard | B27: FC-0017 | C27: 513025 | D27: 513025 | E27: Screw | F27: Storable Product | G27: สกรูมิลดำ 12x55+หัว+อีแปะ | H27: Hexagon Screw Black 12x55 | I27: ชุด | J27: SET | K27: AP-KSR001 | L27: =IFERROR(VLOOKUP(K27,'Supplier list'!B:C,2,0),"") -> บริษัท เกรียงศิริพัฒนา (1995) จำกัด | M27: =FALSE() -> 0 | O27: 15
A28: Standard | B28: FC-0020 | C28: 513025 | D28: 513025 | E28: Joint | F28: Storable Product | G28: คอปเปอร์ 3 ทาง T | H28: Coupler 3 Way Multi Pass ,T | I28: ชิ้น | J28: PC | K28: AP-KSR001 | L28: =IFERROR(VLOOKUP(K28,'Supplier list'!B:C,2,0),"") -> บริษัท เกรียงศิริพัฒนา (1995) จำกัด | M28: =FALSE() -> 0 | O28: 190
A29: Standard | B29: FC-0021 | C29: 513025 | D29: 513025 | E29: Joint | F29: Storable Product | G29: ข้อต่อคอปเปอร์ 20pm. | H29: Coupler joint, model 20PM | I29: ชิ้น | J29: PC | K29: AP-KSR001 | L29: =IFERROR(VLOOKUP(K29,'Supplier list'!B:C,2,0),"") -> บริษัท เกรียงศิริพัฒนา (1995) จำกัด | M29: =FALSE() -> 0 | O29: 20
A30: Standard | B30: FC-0023 | C30: 513025 | D30: 513025 | E30: Drill bits | F30: Storable Product | G30: ดอกเจาะกระจก 8มม. | H30: Glass drill bit 8 mm. | I30: ชิ้น | J30: PC | K30: AP-KSR001 | L30: =IFERROR(VLOOKUP(K30,'Supplier list'!B:C,2,0),"") -> บริษัท เกรียงศิริพัฒนา (1995) จำกัด | M30: =FALSE() -> 0 | O30: 200
A31: Standard | B31: FC-0024 | C31: 513025 | D31: 513025 | E31: Battery | F31: Storable Product | G31: 005.23.601 BRUSH ET-BG 240V CT26/36 | H31: 005.23.601 BRUSH ET-BG 240V CT26/36 | I31: ชิ้น | J31: PC | K31: AP-HAF001 | L31: =IFERROR(VLOOKUP(K31,'Supplier list'!B:C,2,0),"") -> บริษัท เฮเฟเล่ (ประเทศไทย) จำกัด | M31: =FALSE() -> 0 | O31: 1776
A32: Standard | B32: FC-0026 | C32: 513025 | D32: 513025 | E32: Wheel | F32: Storable Product | G32: ล้อไนลอนขาวชุดชุบโครเมียม แป้นเป็น 4" | H32: Wheels, white nylon, chrome plated set, backplate 4" | I32: กล่อง | J32: BOX | K32: AP-KCR000 | L32: =IFERROR(VLOOKUP(K32,'Supplier list'!B:C,2,0),"") | M32: =FALSE() -> 0 | O32: 435
A33: Standard | B33: FC-0027 | C33: 513025 | D33: 513025 | E33: Bathroom cleaner | F33: Storable Product | G33: น้ำยาล้างห้องน้ำ (เป็ดโปร) | H33: Bathroom cleaner (Duck Pro) | I33: ขวด | J33: BOTTLES | K33: AP-SMK000 | L33: =IFERROR(VLOOKUP(K33,'Supplier list'!B:C,2,0),"") -> บริษัท สยามแม็คโคร จำกัด (มหาชน) | M33: =FALSE() -> 0 | O33: 209
A34: Standard | B34: FC-0028 | C34: 513025 | D34: 513025 | E34: Screw | F34: Storable Product | G34: สกรูมิล JF M4x8-0.70 | H34: Hexagon Screw JF M4x8-0.70 | I34: ชิ้น | J34: PC | K34: AP-KCR000 | L34: =IFERROR(VLOOKUP(K34,'Supplier list'!B:C,2,0),"") -> บริษัท ก.เจริญฮาร์ดแวร์ จำกัด | M34: =FALSE() -> 0 | O34: 0.25
A35: Standard | B35: FC-0029 | C35: 513025 | D35: 513025 | E35: Drill bits | F35: Storable Product | G35: โฮลซอเจาะไม้ 7 ใบ/ชุด 26-63มม. | H35: Hole Saw 7 wood drill bits/set 26-63mm. | I35: ชุด | J35: SET | K35: AP-SHM000 | L35: =IFERROR(VLOOKUP(K35,'Supplier list'!B:C,2,0),"") -> บริษัท ซูเปอร์โฮมมาร์ท จำกัด (สำนักงานใหญ่) | M35: =FALSE() -> 0 | O35: 115
A36: Standard | B36: FC-0030 | C36: 513025 | D36: 513025 | E36: EPE Foam | F36: Storable Product | G36: EPE Foam Laminate inside (handle J) | H36: EPE Foam Laminate inside (handle J) | I36: ชิ้น | J36: PC | K36: AP-PCP000 | L36: =IFERROR(VLOOKUP(K36,'Supplier list'!B:C,2,0),"") | M36: =FALSE() -> 0 | O36: 4.5
... A63: Standard | B63: FS-FUFIT-002 | C63: 114003 | D63: 114003 | E63: Rubber Bump Button | F63: Storable Product | G63: 483.01.996 ปุ่มยางกันกระแทก | H63: 483.01.996 Rubber Bump Button | I63: แผง | J63: PANEL | K63: AP-HAF001 | L63: =IFERROR(VLOOKUP(K63,'Supplier list'!B:C,2,0),"") -> บริษัท เฮเฟเล่ (ประเทศไทย) จำกัด | M63: =FALSE() -> 0 | O63: 178
A64: Standard | B64: FS-FUFIT-003 | C64: 114003 | D64: 114003 | E64: Triangle Claw Bumper | F64: Storable Product | G64: กันชนก้ามปูสามเหลี่ยม BARCO | H64: BARCO Triangle Claw Bumper | I64: ชิ้น | J64: PC | L64: =IFERROR(VLOOKUP(K64,'Supplier list'!B:C,2,0),"") | M64: =FALSE() -> 0 | O64: 28
A65: Standard | B65: FS-FUFIT-004 | C65: 114003 | D65: 114003 | E65: Push Catches | F65: Storable Product | G65: กดเปิดหน้าบานแบบแม่เหล็ก XL | H65: Press to open the magnetic door XL | I65: ชิ้น | J65: PC | L65: =IFERROR(VLOOKUP(K65,'Supplier list'!B:C,2,0),"") | M65: =FALSE() -> 0 | O65: 68
A66: Standard | B66: FS-FUFIT-008 | C66: 114003 | D66: 114003 | E66: Staples | F66: Storable Product | G66: ลูกแม็กขาคู่รุ่น1010J ขนาด 10x10 | H66: Double leg alloy, model 1010J, size 10x10 | I66: กล่อง | J66: BOX | K66: AP-KSR001 | L66: =IFERROR(VLOOKUP(K66,'Supplier list'!B:C,2,0),"") | M66: =FALSE() -> 0 | O66: 100
A67: Standard | B67: FS-FUFIT-009 | C67: 114003 | D67: 114003 | E67: Nails | F67: Storable Product | G67: ตะปูยิงงานฝีมือ HI-TOP # PINS/25 | H67: HI-TOP Craft Nails # PINS/25 | I67: กล่อง | J67: BOX | L67: =IFERROR(VLOOKUP(K67,'Supplier list'!B:C,2,0),"") | M67: =FALSE() -> 0 | O67: 261
A68: Standard | B68: FS-FUFIT-010 | C68: 114003 | D68: 114003 | E68: Power cord with jack | F68: Storable Product | G68: สายไฟพร้อมแจ๊คเสียบ | H68: Power cord with jack | I68: เส้น | J68: STRIP | L68: =IFERROR(VLOOKUP(K68,'Supplier list'!B:C,2,0),"") | M68: =FALSE() -> 0 | O68: 60
A69: Standard | B69: FS-FUFIT-011 | C69: 114003 | D69: 114003 | E69: Staples | F69: Storable Product | G69: ลูกแม็กขาคู่รุ่น416J ขนาด 4x16 | H69: Staples Double pin model 416J, size 4x16 | I69: กล่อง | J69: BOX | L69: =IFERROR(VLOOKUP(K69,'Supplier list'!B:C,2,0),"") | M69: =FALSE() -> 0 | O69: 93
A70: Standard | B70: FS-FUFIT-012 | C70: 114003 | D70: 114003 | E70: Staples | F70: Storable Product | G70: ลูกแม็กขาคู่รุ่น410J ขนาด 4x10 | H70: Staples Double pin model 416J, size 4x10 | I70: กล่อง | J70: BOX | L70: =IFERROR(VLOOKUP(K70,'Supplier list'!B:C,2,0),"") | M70: =FALSE() -> 0 | O70: 93
A71: Standard | B71: FS-FUFIT-013 | C71: 114003 | D71: 114003 | E71: Power plug | F71: Storable Product | G71: ปลั๊ก3ขา | H71: 3 pin plug | I71: ชิ้น | J71: PC | K71: AP-GDL000 | L71: =IFERROR(VLOOKUP(K71,'Supplier list'!B:C,2,0),"") -> หจก. กรีน ดิสทริบิวชั่น | M71: =FALSE() -> 0 | O71: 28
A72: Standard | B72: FS-FUFIT-014 | C72: 114003 | D72: 114003 | E72: Power plug | F72: Storable Product | G72: ปลั๊ก2ขา | H72: 2 pin plug | I72: ชิ้น | J72: PC | K72: AP-GDL000 | L72: =IFERROR(VLOOKUP(K72,'Supplier list'!B:C,2,0),"") -> หจก. กรีน ดิสทริบิวชั่น | M72: =FALSE() -> 0 | O72: 20
A73: Standard | B73: FS-FUFIT-015 | C73: 114003 | D73: 114003 | E73: Glue | F73: Storable Product | G73: กาวลาเท็กซ์ 32 ออน 12ขวด/ลัง | H73: Latex Glue 32 ounces, 12 bottles/box | I73: ขวด | J73: BOTTLES | K73: AP-KSR001 | L73: =IFERROR(VLOOKUP(K73,'Supplier list'!B:C,2,0),"") | M73: =FALSE() -> 0 | O73: 55
A74: Standard | B74: FS-FUFIT-016 | C74: 114003 | D74: 114003 | E74: Chalk | F74: Storable Product | G74: ชอล์กTOUTH-UPSTLCK NO.101 | H74: Chalk TOUTH-UPSTTLCK NO.101 | I74: แท่ง | J74: STICK | K74: AP-MKW000 | L74: =IFERROR(VLOOKUP(K74,'Supplier list'!B:C,2,0),"") -> บริษัท เอ็มเค วู้ดเทค จำกัด | M74: =FALSE() -> 0 | O74: 80
A75: Standard | B75: FS-FUFIT-017 | C75: 114003 | D75: 114003 | E75: Chalk | F75: Storable Product | G75: ชอล์กTOUTH-UPSTLCK NO.106 | H75: Chalk TOUTH-UPSTTLCK NO.106 | I75: แท่ง | J75: STICK | K75: AP-MKW000 | L75: =IFERROR(VLOOKUP(K75,'Supplier list'!B:C,2,0),"") -> บริษัท เอ็มเค วู้ดเทค จำกัด | M75: =FALSE() -> 0 | O75: 80
A76: Standard | B76: FS-FUFIT-018 | C76: 114003 | D76: 114003 | E76: Chalk | F76: Storable Product | G76: ชอล์กTOUTH-UPSTLCK NO.313 | H76: Chalk TOUTH-UPSTTLCK NO.313 | I76: แท่ง | J76: STICK | K76: AP-MKW000 | L76: =IFERROR(VLOOKUP(K76,'Supplier list'!B:C,2,0),"") -> บริษัท เอ็มเค วู้ดเทค จำกัด | M76: =FALSE() -> 0 | O76: 80
A77: Standard | B77: FS-FUFIT-019 | C77: 114003 | D77: 114003 | E77: Chalk | F77: Storable Product | G77: ชอล์กTOUTH-UPSTLCK NO.2638 | H77: Chalk TOUTH-UPSTTLCK NO.2638 | I77: แท่ง | J77: STICK | K77: AP-MKW000 | L77: =IFERROR(VLOOKUP(K77,'Supplier list'!B:C,2,0),"") -> บริษัท เอ็มเค วู้ดเทค จำกัด | M77: =FALSE() -> 0 | O77: 80
A78: Standard | B78: FS-FUFIT-020 | C78: 114003 | D78: 114003 | E78: Chalk | F78: Storable Product | G78: ชอล์กTOUTH-UPSTLCK NO.3200 | H78: Chalk TOUTH-UPSTTLCK NO.3200 | I78: แท่ง | J78: STICK | K78: AP-MKW000 | L78: =IFERROR(VLOOKUP(K78,'Supplier list'!B:C,2,0),"") -> บริษัท เอ็มเค วู้ดเทค จำกัด | M78: =FALSE() -> 0 | O78: 80
A79: Standard | B79: FS-FUFIT-021 | C79: 114003 | D79: 114003 | E79: Chalk | F79: Storable Product | G79: ชอล์กTOUTH-UPSTLCK NO.3325 | H79: Chalk TOUTH-UPSTTLCK NO.3325 | I79: แท่ง | J79: STICK | K79: AP-MKW000 | L79: =IFERROR(VLOOKUP(K79,'Supplier list'!B:C,2,0),"") -> บริษัท เอ็มเค วู้ดเทค จำกัด | M79: =FALSE() -> 0 | O79: 80
A80: Standard | B80: FS-FUFIT-022 | C80: 114003 | D80: 114003 | E80: Chalk | F80: Storable Product | G80: ชอล์กTOUTH-UPSTLCK NO.3357 | H80: Chalk TOUTH-UPSTTLCK NO.3357 | I80: แท่ง | J80: STICK | K80: AP-MKW000 | L80: =IFERROR(VLOOKUP(K80,'Supplier list'!B:C,2,0),"") -> บริษัท เอ็มเค วู้ดเทค จำกัด | M80: =FALSE() -> 0 | O80: 80
A81: Standard | B81: FS-FUFIT-023 | C81: 114003 | D81: 114003 | E81: Chalk | F81: Storable Product | G81: ชอล์กTOUTH-UPSTLCK NO.3258 | H81: Chalk TOUTH-UPSTTLCK NO.3258 | I81: แท่ง | J81: STICK | K81: AP-MKW000 | L81: =IFERROR(VLOOKUP(K81,'Supplier list'!B:C,2,0),"") -> บริษัท เอ็มเค วู้ดเทค จำกัด | M81: =FALSE() -> 0 | O81: 80
A82: Standard | B82: FS-FUFIT-024 | C82: 114001 | D82: 114001 | E82: Chalk | F82: Storable Product | G82: ชอล์กTOUTH-UPSTLCK NO.3125 | H82: Chalk TOUTH-UPSTTLCK NO.3125 | I82: แท่ง | J82: STICK | K82: AP-MKW000 | L82: =IFERROR(VLOOKUP(K82,'Supplier list'!B:C,2,0),"") -> บริษัท เอ็มเค วู้ดเทค จำกัด | M82: =FALSE() -> 0 | O82: 80
... A84: Standard | B84: FS-FUFIT-026 | C84: 114001 | D84: 114001 | E84: Turpentine | F84: Storable Product | G84: น้ำมันสน | H84: Turpentine | I84: ปี๊ป | J84: BUCKET | K84: AP-TPK001 | L84: =IFERROR(VLOOKUP(K84,'Supplier list'!B:C,2,0),"") -> บริษัท ที.พี.เค ไทยเมท แมชชีนทูลล์ จำกัด | M84: =FALSE() -> 0 | O84: 400
A85: Standard | B85: FS-FUFIT-027 | C85: 114001 | D85: 114001 | E85: Silicone | F85: Storable Product | G85: ซิลิโคน สีเทา | H85: Silicone gray | I85: หลอด | J85: TUBE | L85: =IFERROR(VLOOKUP(K85,'Supplier list'!B:C,2,0),"") | M85: =FALSE() -> 0 | O85: 65
A86: Standard | B86: FS-FUFIT-028 | C86: 114001 | D86: 114001 | E86: PVC pipe binder | F86: Storable Product | G86: น้ำยาประสานท่อพีวีซี-100g | H86: PVC pipe binder-100g | I86: กระป๋อง | J86: CAN | K86: AP-KSR001 | L86: =IFERROR(VLOOKUP(K86,'Supplier list'!B:C,2,0),"") | M86: =FALSE() -> 0 | O86: 30
A87: Standard | B87: FS-FUFIT-029 | C87: 114001 | D87: 114001 | E87: Glue | F87: Storable Product | G87: กาวตะปู Maxbond Fuller | H87: Maxbond Fuller Nail Glue | I87: หลอด | J87: TUBE | K87: AP-GDL000 | L87: =IFERROR(VLOOKUP(K87,'Supplier list'!B:C,2,0),"") -> หจก. กรีน ดิสทริบิวชั่น | M87: =FALSE() -> 0 | O87: 90
A88: Standard | B88: FS-FUFIT-030 | C88: 114001 | D88: 114001 | E88: Glue | F88: Storable Product | G88: กาวร้อน | H88: Hot glue | I88: หลอด | J88: TUBE | K88: AP-PNPI000 | L88: =IFERROR(VLOOKUP(K88,'Supplier list'!B:C,2,0),"") -> บริษัท พีเอ็นพี อินเตอร์แพค | M88: =FALSE() -> 0 | O88: 10
A89: Standard | B89: FS-FUFIT-031 | C89: 114001 | D89: 114001 | E89: Purpose spray | F89: Storable Product | G89: สเปรย์เอนกประสงค์ SONAX | H89: Sonax multi -purpose spray | I89: กระป๋อง | J89: CAN | K89: AP-GDL000 | L89: =IFERROR(VLOOKUP(K89,'Supplier list'!B:C,2,0),"") -> หจก. กรีน ดิสทริบิวชั่น | M89: =FALSE() -> 0 | O89: 95
A90: Standard | B90: FS-FUFIT-032 | C90: 114001 | D90: 114001 | E90: Paint equipment | F90: Storable Product | G90: ลูกกลิ้งทาสี (ใหญ่) | H90: Paint roller (large) | I90: ชิ้น | J90: PC | L90: =IFERROR(VLOOKUP(K90,'Supplier list'!B:C,2,0),"") | M90: =FALSE() -> 0 | O90: 69
A91: Standard | B91: FS-FUFIT-033 | C91: 114001 | D91: 114001 | E91: Paint equipment | F91: Storable Product | G91: แปรงทาสี | H91: Paint brush | I91: ชิ้น | J91: PC | K91: AP-KSR001 | L91: =IFERROR(VLOOKUP(K91,'Supplier list'!B:C,2,0),"") -> บริษัท เกรียงศิริพัฒนา (1995) จำกัด | M91: =FALSE() -> 0 | O91: 40
A92: Standard | B92: FS-FUFIT-034 | C92: 114001 | D92: 114001 | E92: Honeycomb | F92: Storable Product | G92: กระดาษแข็งรังผึ้ง(Honeycomb) | H92: Honeycomb cardboard | I92: ชิ้น | J92: PC | K92: AP-CMP000 | L92: =IFERROR(VLOOKUP(K92,'Supplier list'!B:C,2,0),"") -> บริษัท จิ่นเหม่ยเปเปอร์ จำกัด | M92: =FALSE() -> 0 | O92: 5.7
A93: Standard | B93: FS-FUFIT-035 | C93: 114001 | D93: 114001 | E93: Stretch Film | F93: Storable Product | G93: ฟิล์มยืด พันพาเลท 15 | H93: Wrapped film, Pallet | I93: ม้วน | J93: ROLL | K93: AP-YYG000 | L93: =IFERROR(VLOOKUP(K93,'Supplier list'!B:C,2,0),"") -> บริษัท เหย่ายี่ กรุ๊ป จำกัด | M93: =FALSE() -> 0 | O93: 105
A94: Standard | B94: FS-FUFIT-036 | C94: 114001 | D94: 114001 | E94: EPS Foam | F94: Storable Product | G94: EPS FOAM 710x1320x20mm./0.65 Ib G.ธรรมดา | H94: EPS FOAM 710x1320x20mm./0.65 IB G. | I94: แผ่น | J94: SHEET | L94: =IFERROR(VLOOKUP(K94,'Supplier list'!B:C,2,0),"") | M94: =FALSE() -> 0 | O94: 43
A95: Standard | B95: FS-FUFIT-037 | C95: 114001 | D95: 114001 | E95: EPS Foam | F95: Storable Product | G95: EPS FOAM 812x1523x20mm./0.65 Ib G.ธรรมดา | H95: EPS FOAM 812x1523x20mm./0.65 IB G. | I95: แผ่น | J95: SHEET | K95: AP-ATC000 | L95: =IFERROR(VLOOKUP(K95,'Supplier list'!B:C,2,0),"") -> บริษัท เอ.ที.คอน อินซูเลชั่น จำกัด | M95: =FALSE() -> 0 | O95: 43.25
A96: Standard | B96: FS-FUFIT-038 | C96: 114001 | D96: 114001 | E96: Glue | F96: Storable Product | G96: กาวเม็ด White hot melt 7640 | H96: White Hot Melt 7640 | I96: กิโลกรัม | J96: KG | L96: =IFERROR(VLOOKUP(K96,'Supplier list'!B:C,2,0),"") | M96: =FALSE() -> 0 | O96: 144
A97: Standard | B97: FS-FUFIT-039 | C97: 114001 | D97: 114001 | E97: Battery | F97: Storable Product | G97: แปรงถ่าน Carbon brushes (BOSCH) | H97: Carbon Brushes batteries (Bosch) | I97: ชิ้น | J97: PC | L97: =IFERROR(VLOOKUP(K97,'Supplier list'!B:C,2,0),"") | M97: =FALSE() -> 0 | O97: 60
A98: Standard | B98: FS-FUFIT-040 | C98: 114001 | D98: 114001 | E98: Glue | F98: Storable Product | G98: HM 9585.0 กาวเม็ดสีเหลือง ใช้กับเครื่องปิดขอบ | H98: HM 9585.0 Yellow granules Used with the edge closing machine | I98: กิโลกรัม | J98: KG | K98: AP-STN002 | L98: =IFERROR(VLOOKUP(K98,'Supplier list'!B:C,2,0),"") -> บริษัท สไตเนอร์ท จำกัด | M98: =FALSE() -> 0 | O98: 145
A99: Standard | B99: FS-FUFIT-041 | C99: 114001 | D99: 114001 | E99: Polyurethane Tube | F99: Storable Product | G99: สายลม PU 8*12 mm สีส้ม | H99: Wind PU 8*12 mm Orange | I99: เมตร | J99: M | K99: AP-KCR000 | L99: =IFERROR(VLOOKUP(K99,'Supplier list'!B:C,2,0),"") -> บริษัท ก.เจริญฮาร์ดแวร์ จำกัด | M99: =FALSE() -> 0 | O99: 2250
A100: Standard | B100: FS-FUFIT-042 | C100: 114001 | D100: 114001 | E100: Grease | F100: Storable Product | G100: จารบี TRANE #SUPER HT 5 กก | H100: Grease TRANE #SUPER HT 5 kg. | I100: กระปุก | J100: BOWL | L100: =IFERROR(VLOOKUP(K100,'Supplier list'!B:C,2,0),"") | M100: =FALSE() -> 0 | O100: 1078
A101: Standard | B101: FS-FUFIT-043 | C101: 114001 | D101: 114001 | E101: Staples | F101: Storable Product | G101: ลูกแม๊กซ์ F20 VIGO | H101: Staples F20 VIGO | I101: กล่อง | J101: BOX | L101: =IFERROR(VLOOKUP(K101,'Supplier list'!B:C,2,0),"") | M101: =FALSE() -> 0 | O101: 68
A102: Standard | B102: FS-FUFIT-044 | C102: 114001 | D102: 114001 | E102: Staples | F102: Storable Product | G102: ลูกแม๊กซ์ F30 VIGO | H102: Staples F30 VIGO | I102: กล่อง | J102: BOX | L102: =IFERROR(VLOOKUP(K102,'Supplier list'!B:C,2,0),"") | M102: =FALSE() -> 0 | O102: 60
A103: Standard | B103: FS-FUFIT-045 | C103: 114001 | D103: 114001 | E103: Silicone | F103: Storable Product | G103: ซิลิโคน V-Tech สีใส 24หลอด/ลัง | H103: V-Tech silicone, clear, 24 tubes/box | I103: หลอด | J103: TUBE | K103: AP-GDL000 | L103: =IFERROR(VLOOKUP(K103,'Supplier list'!B:C,2,0),"") -> หจก. กรีน ดิสทริบิวชั่น | M103: =FALSE() -> 0 | O103: 65
A104: Standard | B104: FS-FUFIT-046 | C104: 114001 | D104: 114001 | E104: Silicone | F104: Storable Product | G104: ซิลิโคน V-Tech สีขาว 24หลอด/ลัง | H104: V-Tech silicone, white, 24 tubes/box | I104: หลอด | J104: TUBE | K104: AP-GDL000 | L104: =IFERROR(VLOOKUP(K104,'Supplier list'!B:C,2,0),"") -> หจก. กรีน ดิสทริบิวชั่น | M104: =FALSE() -> 0 | O104: 65
A105: Standard | B105: FS-FUFIT-047 | C105: 114001 | D105: 114001 | E105: Silicone | F105: Storable Product | G105: ซิลิโคน (สีดำ) | H105: Silicone (Black) | I105: หลอด | J105: TUBE | K105: AP-GDL000 | L105: =IFERROR(VLOOKUP(K105,'Supplier list'!B:C,2,0),"") -> หจก. กรีน ดิสทริบิวชั่น | M105: =FALSE() -> 0 | O105: 65
A106: Standard | B106: FS-FUFIT-048 | C106: 114001 | D106: 114001 | E106: Tape | F106: Storable Product | G106: 9089 เทปกาวOPP สีใส 2” x 100 y*45mic 72Pc/Box | H106: Clear Tape Tiger-45 2x100yards 90rolls/box | I106: ม้วน | J106: ROLL | K106: AP-PNPI000 | L106: =IFERROR(VLOOKUP(K106,'Supplier list'!B:C,2,0),"") -> บริษัท พีเอ็นพี อินเตอร์แพค | M106: =FALSE() -> 0 | O106: 20.5
A107: Standard | B107: FS-FUFIT-049 | C107: 114001 | D107: 114001 | E107: Tape | F107: Storable Product | G107: เทปใส 3(บาง)" | H107: Clear tape 3(thin)" | I107: ม้วน | J107: ROLL | K107: AP-PNPI000 | L107: =IFERROR(VLOOKUP(K107,'Supplier list'!B:C,2,0),"") -> บริษัท พีเอ็นพี อินเตอร์แพค | M107: =FALSE() -> 0 | O107: 39.24
A108: Standard | B108: FS-FUFIT-050 | C108: 114001 | D108: 114001 | E108: Tape | F108: Storable Product | G108: กระดาษกาวย่น 1.1/2 | H108: Masking tape 1.1/2 | I108: ม้วน | J108: ROLL | K108: AP-CCR000 | L108: =IFERROR(VLOOKUP(K108,'Supplier list'!B:C,2,0),"") -> บริษัท โชคเจริญ 2020 จำกัด | M108: =FALSE() -> 0 | O108: 14.6
A109: Standard | B109: FS-FUFIT-051 | C109: 114001 | D109: 114001 | E109: Tape | F109: Storable Product | G109: เทปพันเกลียว | H109: Spiral tape | I109: ม้วน | J109: ROLL | K109: AP-TPK001 | L109: =IFERROR(VLOOKUP(K109,'Supplier list'!B:C,2,0),"") -> บริษัท ที.พี.เค ไทยเมท แมชชีนทูลล์ จำกัด | M109: =FALSE() -> 0 | O109: 10
A110: Standard | B110: FS-FUFIT-052 | C110: 114001 | D110: 114001 | E110: Tape | F110: Storable Product | G110: เทปพันสายไฟ | H110: Wire tape | I110: ม้วน | J110: ROLL | K110: AP-GDL000 | L110: =IFERROR(VLOOKUP(K110,'Supplier list'!B:C,2,0),"") -> หจก. กรีน ดิสทริบิวชั่น | M110: =FALSE() -> 0 | O110: 12
A111: Standard | B111: FS-FUFIT-053 | C111: 114001 | D111: 114001 | E111: Tape | F111: Storable Product | G111: เทปใส 2 บาง 48mmX45" | H111: Clear tape 2, thin 48mmx45 " | I111: ม้วน | J111: ROLL | L111: =IFERROR(VLOOKUP(K111,'Supplier list'!B:C,2,0),"") | M111: =FALSE() -> 0 | O111: 169
A112: Standard | B112: FS-FUFIT-054 | C112: 114001 | D112: 114001 | E112: Tape | F112: Storable Product | G112: เทปกาว 2 หน้าบาง 12 มม. 10หลา | H112: 2 -sided adhesive tape 12 mm 10 yards | I112: ม้วน | J112: ROLL | L112: =IFERROR(VLOOKUP(K112,'Supplier list'!B:C,2,0),"") | M112: =FALSE() -> 0 | O112: 9
A113: Standard | B113: FS-FUFIT-055 | C113: 114001 | D113: 114001 | E113: Detergent | F113: Storable Product | G113: ผงซักฟอกบรีส @ 3000 กรัม | H113: Breeze detergent @ 3000 grams | I113: ถุง | J113: BAG | K113: AP-SMK000 | L113: =IFERROR(VLOOKUP(K113,'Supplier list'!B:C,2,0),"") -> บริษัท สยามแม็คโคร จำกัด (มหาชน) | M113: =FALSE() -> 0 | O113: 504
A114: Standard | B114: FS-FUFIT-056 | C114: 114001 | D114: 114001 | E114: soap | F114: Storable Product | G114: สบู่ | H114: soap | I114: ก้อน | J114: BAR | K114: AP-SMK000 | L114: =IFERROR(VLOOKUP(K114,'Supplier list'!B:C,2,0),"") -> บริษัท สยามแม็คโคร จำกัด (มหาชน) | M114: =FALSE() -> 0 | O114: 45
A115: Standard | B115: FS-FUFIT-057 | C115: 114001 | D115: 114001 | E115: Hard broom | F115: Storable Product | G115: ไม้กวาดแข็ง | H115: Hard broom | I115: ด้าม | J115: HANDLE | K115: AP-KSR001 | L115: =IFERROR(VLOOKUP(K115,'Supplier list'!B:C,2,0),"") | M115: =FALSE() -> 0 | O115: 55
A116: Standard | B116: FS-FUFIT-058 | C116: 114001 | D116: 114001 | E116: Soft broom | F116: Storable Product | G116: ไม้กวาดอ่อน | H116: Soft broom | I116: ด้าม | J116: HANDLE | K116: AP-KSR001 | L116: =IFERROR(VLOOKUP(K116,'Supplier list'!B:C,2,0),"") | M116: =FALSE() -> 0 | O116: 55
A117: Standard | B117: FS-FUFIT-059 | C117: 114001 | D117: 114001 | E117: Chemical pen | F117: Storable Product | G117: ปากกาเคมี น้ำเงิน | H117: Blue Chemical pen | I117: ชิ้น | J117: PC | K117: AP-COL000 | L117: =IFERROR(VLOOKUP(K117,'Supplier list'!B:C,2,0),"") | M117: =FALSE() -> 0 | O117: 42.06
A118: Standard | B118: FS-FUFIT-060 | C118: 114001 | D118: 114001 | E118: Chemical pen | F118: Storable Product | G118: ปากกาเคมี ดำ | H118: Black chemical pen | I118: ชิ้น | J118: PC | K118: AP-COL000 | L118: =IFERROR(VLOOKUP(K118,'Supplier list'!B:C,2,0),"") | M118: =FALSE() -> 0 | O118: 42.06
A119: Standard | B119: FS-FUFIT-061 | C119: 114001 | D119: 114001 | E119: Mop | F119: Storable Product | G119: ไม้ถูพื้น | H119: Mop | I119: ชิ้น | J119: PC | K119: AP-KSR001 | L119: =IFERROR(VLOOKUP(K119,'Supplier list'!B:C,2,0),"") | M119: =FALSE() -> 0 | O119: 110
A120: Standard | B120: FS-FUFIT-062 | C120: 114001 | D120: 114001 | E120: Mop | F120: Storable Product | G120: ผ้าม๊อบ 12 นิ้ว | H120: 12 inch mob fabric | I120: ชิ้น | J120: PC | L120: =IFERROR(VLOOKUP(K120,'Supplier list'!B:C,2,0),"") | M120: =FALSE() -> 0 | O120: 119
A121: Standard | B121: FS-FUFIT-063 | C121: 114001 | D121: 114001 | E121: Garbage scoop | F121: Storable Product | G121: ที่ตักขยะ (เหล็ก) | H121: Garbage scoop (steel) | I121: ชิ้น | J121: PC | L121: =IFERROR(VLOOKUP(K121,'Supplier list'!B:C,2,0),"") | M121: =FALSE() -> 0 | O121: 145
A122: Standard | B122: FS-FUFIT-064 | C122: 114001 | D122: 114001 | E122: Garbage scoop | F122: Storable Product | G122: ที่ตักขยะ (พลาสติก) | H122: Garbage scoop (plastic) | I122: ชิ้น | J122: PC | K122: AP-KSR001 | L122: =IFERROR(VLOOKUP(K122,'Supplier list'!B:C,2,0),"") | M122: =FALSE() -> 0 | O122: 60
A123: Standard | B123: FS-FUFIT-065 | C123: 114001 | D123: 114001 | E123: Brush | F123: Storable Product | G123: แปรงซักผ้า | H123: Washing brush | I123: ชิ้น | J123: PC | L123: =IFERROR(VLOOKUP(K123,'Supplier list'!B:C,2,0),"") | M123: =FALSE() -> 0 | O123: 28
A124: Standard | B124: FS-FUFIT-066 | C124: 114001 | D124: 114001 | E124: Brush | F124: Storable Product | G124: แปรง (ห้องน้ำ) | H124: Brush (bathroom) | I124: ชิ้น | J124: PC | K124: AP-COL000 | L124: =IFERROR(VLOOKUP(K124,'Supplier list'!B:C,2,0),"") | M124: =FALSE() -> 0 | O124: 60.75
A125: Standard | B125: FS-FUFIT-067 | C125: 114001 | D125: 114001 | E125: Brush | F125: Storable Product | G125: สมอแปรงขนทอง (ห้องน้ำ) | H125: Golden hair brush anchor (bathroom) | I125: ชิ้น | J125: PC | L125: =IFERROR(VLOOKUP(K125,'Supplier list'!B:C,2,0),"") | M125: =FALSE() -> 0 | O125: 28
A126: Standard | B126: FS-FUFIT-068 | C126: 114001 | D126: 114001 | E126: Tape | F126: Storable Product | G126: ตัวตัดเทปใส | H126: Clear tape cutter | I126: ชิ้น | J126: PC | L126: =IFERROR(VLOOKUP(K126,'Supplier list'!B:C,2,0),"") | M126: =FALSE() -> 0 | O126: 149
A127: Standard | B127: FS-FUFIT-069 | C127: 114001 | D127: 114001 | E127: Polyurethane Tube | F127: Storable Product | G127: สายลม PU 5*8 MM. | H127: Wind PU 5*8 MM. | I127: เมตร | J127: M | K127: AP-KCR000 | L127: =IFERROR(VLOOKUP(K127,'Supplier list'!B:C,2,0),"") -> บริษัท ก.เจริญฮาร์ดแวร์ จำกัด | M127: =FALSE() -> 0 | O127: 1020
A128: Standard | B128: FS-FUFIT-070 | C128: 114001 | D128: 114001 | E128: Cloth Colour Sheets | F128: Storable Product | G128: ผ้าเย็บวนสีขาว 25 กก. | H128: White Cloth Colour Sheets 25 kg. | I128: กระสอบ | J128: SACK | L128: =IFERROR(VLOOKUP(K128,'Supplier list'!B:C,2,0),"") | M128: =FALSE() -> 0 | O128: 650
A129: Standard | B129: FS-FUFIT-071 | C129: 114001 | D129: 114001 | E129: Cable tie | F129: Storable Product | G129: เคเบิ้ลไทร์ 12นิ้ว | H129: Cable tie 12 inch | I129: ห่อ | J129: PACK | L129: =IFERROR(VLOOKUP(K129,'Supplier list'!B:C,2,0),"") | M129: =FALSE() -> 0 | O129: 108
A130: Standard | B130: FS-FUFIT-072 | C130: 114001 | D130: 114001 | E130: Cable tie | F130: Storable Product | G130: เคเบิ้ลไทร์ 6นิ้ว | H130: Cable tie 6 inch | I130: ห่อ | J130: PACK | K130: AP-KSR001 | L130: =IFERROR(VLOOKUP(K130,'Supplier list'!B:C,2,0),"") | M130: =FALSE() -> 0 | O130: 100
A131: Standard | B131: FS-FUFIT-073 | C131: 114001 | D131: 114001 | E131: Gloves | F131: Storable Product | G131: ถุงมือผ้า 12/โหล | H131: Cloth gloves 12/dozen | I131: คู่ | J131: PAIR | K131: AP-PNPI000 | L131: =IFERROR(VLOOKUP(K131,'Supplier list'!B:C,2,0),"") -> บริษัท พีเอ็นพี อินเตอร์แพค | M131: =FALSE() -> 0 | O131: 40
A132: Standard | B132: FS-FUFIT-074 | C132: 114001 | D132: 114001 | E132: Mask | F132: Storable Product | G132: ผ้าปิดจมูก 12/โหล | H132: Nose mask 12/dozen | I132: ชิ้น | J132: PC | K132: AP-PNPI000 | L132: =IFERROR(VLOOKUP(K132,'Supplier list'!B:C,2,0),"") -> บริษัท พีเอ็นพี อินเตอร์แพค | M132: =FALSE() -> 0 | O132: 27.5
A133: Standard | B133: FS-FUFIT-075 | C133: 114001 | D133: 114001 | E133: Strap | F133: Storable Product | G133: สายรัด (สีเหลือง) 12mm.*7.5kg. | H133: Strap (yellow) 12mm.*7.5kg. | I133: ม้วน | J133: ROLL | K133: AP-KCR000 | L133: =IFERROR(VLOOKUP(K133,'Supplier list'!B:C,2,0),"") -> บริษัท ก.เจริญฮาร์ดแวร์ จำกัด | M133: =FALSE() -> 0 | O133: 390
A134: Standard | B134: FS-FUFIT-076 | C134: 114001 | D134: 114001 | E134: Cable tie | F134: Storable Product | G134: เคเบิ้ลไทร์ 8นิ้ว | H134: Cable tie 8 inch | I134: ห่อ | J134: PACK | L134: =IFERROR(VLOOKUP(K134,'Supplier list'!B:C,2,0),"") | M134: =FALSE() -> 0 | O134: 145
A135: Standard | B135: FS-FUFIT-077 | C135: 114001 | D135: 114001 | E135: Cable tie | F135: Storable Product | G135: เคเบิ้ลไทร์ 10นิ้ว | H135: Cable tie 10 inch | I135: ห่อ | J135: PACK | L135: =IFERROR(VLOOKUP(K135,'Supplier list'!B:C,2,0),"") | M135: =FALSE() -> 0 | O135: 83
A136: Standard | B136: FS-FUFIT-078 | C136: 114001 | D136: 114001 | E136: Battery | F136: Storable Product | G136: ถ่านหินเจีย BOSCH 00-06-019 | H136: Coal Grinding BOSCH 00-06-019 | I136: ชุด | J136: SET | K136: AP-TPK001 | L136: =IFERROR(VLOOKUP(K136,'Supplier list'!B:C,2,0),"") -> บริษัท ที.พี.เค ไทยเมท แมชชีนทูลล์ จำกัด | M136: =FALSE() -> 0 | O136: 55
...

Sheet Product 652-1300
A1: Standardize | B1: Product Code | C1: Income Account | D1: Expense Account | E1: Product Category | F1: Product Type | G1: Product Name TH | H1: Product Name EN | I1: UOM TH | J1: UOM EN | K1: Code Supplier | L1: Supplier Name | M1: True/False | N1: Selling Price | O1: Cost Price
A2: Standard | B2: RM-FUFIT-190 | C2: 114001 | D2: 114001 | E2: Driver | F2: Storable Product | G2: ไฟ-Haf-833.71.786-หม้อแปลง12V/40W EU PLUG2000mm. | H2: 833.71.786 DRIVER 12V/40W W.EU-PLUG 2000MM | I2: ชิ้น | J2: PC | K2: AP-HAF001 | L2: =IFERROR(VLOOKUP(K2,'Supplier list'!B:C,2,0),"") -> บริษัท เฮเฟเล่ (ประเทศไทย) จำกัด | M2: =TRUE() -> 1 | N2: 2500 | O2: 1421
A3: Standard | B3: RM-FUFIT-191 | C3: 114001 | D3: 114001 | E3: Sink edge | F3: Storable Product | G3: บานซิงค์-0-0-ขอบบานซิงค์ เตาแก๊ส 2.1 เมตร | H3: Zinc door-0-0-Sink edge, gas stove 2.1 meters | I3: เส้น | J3: STRIP | L3: =IFERROR(VLOOKUP(K3,'Supplier list'!B:C,2,0),"") | M3: =FALSE() -> 0 | O3: 988
A4: Standard | B4: RM-FUFIT-192 | C4: 114001 | D4: 114001 | E4: Sink edge | F4: Storable Product | G4: บานซิงค์-0-0-ขอบบานซิงค์ บานเดียว 2.4 เมตร | H4: Sync door-0-0-Edge of sync door, one door 2.4 m. | I4: เส้น | J4: STRIP | L4: =IFERROR(VLOOKUP(K4,'Supplier list'!B:C,2,0),"") | M4: =FALSE() -> 0 | O4: 830
A5: Standard | B5: RM-FUFIT-193 | C5: 114001 | D5: 114001 | E5: Sink edge | F5: Storable Product | G5: บานซิงค์-0-0-ขอบบานซิงค์ ใต้เตาแก๊ส 3 เมตร | H5: Zinc door-0-0-sink edge, under the gas stove 3 meters | I5: เส้น | J5: STRIP | L5: =IFERROR(VLOOKUP(K5,'Supplier list'!B:C,2,0),"") | M5: =FALSE() -> 0 | O5: 1590
A6: Standard | B6: RM-FUFIT-194 | C6: 114001 | D6: 114001 | E6: Aluminum | F6: Storable Product | G6: อลูมิเนียม-จีน-H220-มุมขอบนอก (สีเทาเข้ม) H220 | H6: Aluminum-China-H220-Outer corner (dark grey) H220 | I6: ชิ้น | J6: PC | L6: =IFERROR(VLOOKUP(K6,'Supplier list'!B:C,2,0),"") | M6: =FALSE() -> 0 | O6: 0
A7: Standard | B7: RM-FUFIT-195 | C7: 114001 | D7: 114001 | E7: Pipe clip | F7: Storable Product | G7: ติดตั้ง-0-0-คลิปจับท่อ ก้ามปู 20 PVC ท่อน้ำไทย | H7: Install-0-0-Clip to catch pipe, Claw 20 PVC, Thai water pipes | I7: ชิ้น | J7: PC | L7: =IFERROR(VLOOKUP(K7,'Supplier list'!B:C,2,0),"") | M7: =FALSE() -> 0 | O7: 6
A8: Standard | B8: RM-FUFIT-196 | C8: 114001 | D8: 114001 | E8: Pipe clip | F8: Storable Product | G8: ติดตั้ง-0-0-คลิปจับท่อ ก้ามปู 25 PVC ท่อน้ำไทย | H8: Install-0-0-Clip for pipe clamp, 25 PVC pipe, Thai water pipe | I8: ชิ้น | J8: PC | L8: =IFERROR(VLOOKUP(K8,'Supplier list'!B:C,2,0),"") | M8: =FALSE() -> 0 | O8: 10
A9: Standard | B9: RM-FUFIT-197 | C9: 114001 | D9: 114001 | E9: Pipe clip | F9: Storable Product | G9: ติดตั้ง-0-0-คลิปจับท่อ ก้ามปู 18(1/2)NPI | H9: INSTALL-0-0-Clip, pipe clamp, caliper 18(1/2)NPI | I9: ชิ้น | J9: PC | L9: =IFERROR(VLOOKUP(K9,'Supplier list'!B:C,2,0),"") | M9: =FALSE() -> 0 | O9: 15
A10: Standard | B10: RM-FUFIT-198 | C10: 114001 | D10: 114001 | E10: Joint | F10: Storable Product | G10: ติดตั้ง-0-0-ข้อ90บาง scg บางสีฟ้า35(1.1/4) | H10: Install-0-0-Article 90, some scg, some blue 35(1.1/4) | I10: ชิ้น | J10: PC | K10: AP-KSR001 | L10: =IFERROR(VLOOKUP(K10,'Supplier list'!B:C,2,0),"") -> บริษัท เกรียงศิริพัฒนา (1995) จำกัด | M10: =FALSE() -> 0 | O10: 12
A11: Standard | B11: RM-FUFIT-199 | C11: 114001 | D11: 114001 | E11: Joint | F11: Storable Product | G11: ติดตั้ง-0-0-ข้อต่อตรงscg 35 บาง สีฟ้า(1.1/4) | H11: Install-0-0-Straight Coupling scg 35 Thin Blue (1.1/4) | I11: ชิ้น | J11: PC | K11: AP-KSR001 | L11: =IFERROR(VLOOKUP(K11,'Supplier list'!B:C,2,0),"") -> บริษัท เกรียงศิริพัฒนา (1995) จำกัด | M11: =FALSE() -> 0 | O11: 10
A12: Standard | B12: RM-FUFIT-200 | C12: 114001 | D12: 114001 | E12: Joint | F12: Storable Product | G12: ติดตั้ง-0-0-ข้อ90 บาง ท่อน้ำไทย 3 สีฟ้า | H12: Install-0-0-Article 90 Bang Thai Water Pipe 3 Blue | I12: ชิ้น | J12: PC | L12: =IFERROR(VLOOKUP(K12,'Supplier list'!B:C,2,0),"") | M12: =FALSE() -> 0 | O12: 62
A13: Standard | B13: RM-FUFIT-201 | C13: 114001 | D13: 114001 | E13: Sink edge | F13: Storable Product | G13: บานซิงค์-0-0-ขอบบานซิงค์ บานคู่ 3.2 เมตร | H13: Sync Door-0-0-Edge of Sync Door, Double Door 3.2 m. | I13: เส้น | J13: STRIP | L13: =IFERROR(VLOOKUP(K13,'Supplier list'!B:C,2,0),"") | M13: =FALSE() -> 0 | O13: 990
A14: Standard | B14: RM-FUFIT-202 | C14: 114001 | D14: 114001 | E14: Joint | F14: Storable Product | G14: ติดตั้ง-0-0-สามทางPVC หนา สีฟ้า18(1/2) | H14: Install-0-0-Three Way PVC Thick Blue 18(1/2) | I14: ชิ้น | J14: PC | L14: =IFERROR(VLOOKUP(K14,'Supplier list'!B:C,2,0),"") | M14: =FALSE() -> 0 | O14: 9.5
A15: Standard | B15: RM-FUFIT-204 | C15: 114001 | D15: 114001 | E15: Screw | F15: Storable Product | G15: โครงตู้-0-HC990007-สกรูเกลียวปล่อยหัวแฉก 8*1.1/4 H | H15: Cabinet frame-0-HC990007-Plug head screw 8*1.1/4 H | I15: กล่อง | J15: BOX | K15: AP-KSR001 | L15: =IFERROR(VLOOKUP(K15,'Supplier list'!B:C,2,0),"") -> บริษัท เกรียงศิริพัฒนา (1995) จำกัด | M15: =FALSE() -> 0 | O15: 340
A16: Standard | B16: RM-FUFIT-205 | C16: 114001 | D16: 114001 | E16: Joint | F16: Storable Product | G16: ติดตั้ง-0-0-ข้อต่อตรงลด PVC 40*25(1.1/2*1) | H16: Install-0-0-Straight Coupling PVC 40*25(1.1/2*1) | I16: ชิ้น | J16: PC | L16: =IFERROR(VLOOKUP(K16,'Supplier list'!B:C,2,0),"") | M16: =FALSE() -> 0 | O16: 20
A17: Standard | B17: RM-FUFIT-206 | C17: 114001 | D17: 114001 | E17: Handle | F17: Storable Product | G17: มือจับ-FTT-0-1P004 1 | H17: Handle-FTT-0-1P004 1 | I17: ชิ้น | J17: PC | K17: AP-FTT000 | L17: =IFERROR(VLOOKUP(K17,'Supplier list'!B:C,2,0),"") -> บริษัท ฟิวเจอร์เทค อินเตอร์มาร์เก็ตติ้ง จำกัด | M17: =FALSE() -> 0 | O17: 0
A18: Standard | B18: RM-FUFIT-207 | C18: 114001 | D18: 114001 | E18: Drawer underlay | F18: Storable Product | G18: ติดตั้ง-จีน-0-แผ่นรองใต้ลิ้นชัก ม้วน0.5*15m. | H18: Install-China-0-Pad under the drawer roll 0.5*15m. | I18: เมตร | J18: M | L18: =IFERROR(VLOOKUP(K18,'Supplier list'!B:C,2,0),"") | M18: =FALSE() -> 0 | O18: 99
A19: Standard | B19: RM-FUFIT-208 | C19: 114001 | D19: 114001 | E19: Sticker | F19: Storable Product | G19: ติดตั้ง-จีน-0-สติกเกอร์ปิดเกือกมา สีOaK | H19: Install-China-0-Shoe Cover Sticker, Oak Color | I19: ดวง | J19: DISK | L19: =IFERROR(VLOOKUP(K19,'Supplier list'!B:C,2,0),"") | M19: =FALSE() -> 0 | O19: 30
A20: Standard | B20: RM-FUFIT-209 | C20: 114001 | D20: 114001 | E20: Joint | F20: Storable Product | G20: ติดตั้ง-0-0-ข้อต่อตรง หนา scg 18(1/2) สีฟ้า | H20: Install-0-0-Straight Coupling Thickness scg 18(1/2) Blue | I20: ชิ้น | J20: PC | L20: =IFERROR(VLOOKUP(K20,'Supplier list'!B:C,2,0),"") | M20: =FALSE() -> 0 | O20: 7
A21: Standard | B21: RM-FUFIT-211 | C21: 114001 | D21: 114001 | E21: Cabinet | F21: Storable Product | G21: โครงตู้-จีน-0-ตัวต่อแผ่นรองตู้ครัว9.5 ซม.มุม90 เทา | H21: Cabinet frame-China-0-Kitchen plate connector 9.5 cm. Corner 90 gray | I21: ชิ้น | J21: PC | L21: =IFERROR(VLOOKUP(K21,'Supplier list'!B:C,2,0),"") | M21: =FALSE() -> 0 | O21: 0
A22: Standard | B22: RM-FUFIT-212 | C22: 114001 | D22: 114001 | E22: Cabinet | F22: Storable Product | G22: โครงตู้-0-1C2 9131155-รางลิ้นชักลูกปืน2ตอน | H22: Cabinet Frame-0-1C2 9131155-Bearing drawer slides, 2 sections | I22: ชุด | J22: SET | K22: AP-HAF001 | L22: =IFERROR(VLOOKUP(K22,'Supplier list'!B:C,2,0),"") -> บริษัท เฮเฟเล่ (ประเทศไทย) จำกัด | M22: =FALSE() -> 0 | O22: 660
A23: Standard | B23: RM-FUFIT-213 | C23: 114001 | D23: 114001 | E23: Hinge | F23: Storable Product | G23: โครงตู้-0-1B19076462RC-บานพับถ้วยกระจกMM6204ในขอบ | H23: Cabinet frame-0-1B19076462RC-Glass cup hinge MM6204 in edge | I23: ชุด | J23: SET | K23: AP-HAF001 | L23: =IFERROR(VLOOKUP(K23,'Supplier list'!B:C,2,0),"") -> บริษัท เฮเฟเล่ (ประเทศไทย) จำกัด | M23: =FALSE() -> 0 | O23: 68
A24: Standard | B24: RM-FUFIT-214 | C24: 114001 | D24: 114001 | E24: Cabinet | F24: Storable Product | G24: โครงตู้-Haf-372.91.732-บานเปิดขึ้นFL FFREE FL | H24: 372.91.732 FLF FREE FLAP3.15 F ALU WH. | I24: ชุด | J24: SET | K24: AP-HAF001 | L24: =IFERROR(VLOOKUP(K24,'Supplier list'!B:C,2,0),"") -> บริษัท เฮเฟเล่ (ประเทศไทย) จำกัด | M24: =FALSE() -> 0 | O24: 3673
A25: Standard | B25: RM-FUFIT-215 | C25: 114001 | D25: 114001 | E25: Hinge | F25: Storable Product | G25: บานพับ-Haf-306.00.008-บานพับทับขอบNickleดำเงาsoft | H25: 306.00.008 DAMP.HIN.FULL.EXT.BL.GAL.35MM | I25: ชิ้น | J25: PC | K25: AP-HAF001 | L25: =IFERROR(VLOOKUP(K25,'Supplier list'!B:C,2,0),"") -> บริษัท เฮเฟเล่ (ประเทศไทย) จำกัด | M25: =FALSE() -> 0 | O25: 50
A26: Standard | B26: RM-FUFIT-216 | C26: 114001 | D26: 114001 | E26: Drawer Runners | F26: Storable Product | G26: 432.20.933 รางรับข้างปิดนุ่มนวลรับ นน. 30กก. 400มม | H26: 432.20.933 B-RUNNER S 30F+D GALV.400MM | I26: คู่ | J26: PAIR | K26: AP-HAF001 | L26: =IFERROR(VLOOKUP(K26,'Supplier list'!B:C,2,0),"") -> บริษัท เฮเฟเล่ (ประเทศไทย) จำกัด | M26: =TRUE() -> 1 | N26: 1600 | O26: 655
A27: Standard | B27: RM-FUFIT-217 | C27: 114001 | D27: 114001 | E27: Drawer Runners | F27: Storable Product | G27: ลิ้นชัก-Haf-432.20.935-รางลิ้นชักระบบสองตอน500mm. | H27: Drawer-Haf-432.20.935-Double-section drawer runner, 500mm. | I27: ชิ้น | J27: PC | K27: AP-HAF001 | L27: =IFERROR(VLOOKUP(K27,'Supplier list'!B:C,2,0),"") -> บริษัท เฮเฟเล่ (ประเทศไทย) จำกัด | M27: =TRUE() -> 1 | N27: 1800 | O27: 683
A28: Standard | B28: RM-FUFIT-218 | C28: 114001 | D28: 114001 | E28: Drawer Runners | F28: Storable Product | G28: 432.20.931 รางรับข้างสองตอนรับ นน. 30กก. 300มม. | H28: 432.20.931 B-RUNNER S 30F+D GALV.300MM | I28: คู่ | J28: PAIR | K28: AP-HAF001 | L28: =IFERROR(VLOOKUP(K28,'Supplier list'!B:C,2,0),"") -> บริษัท เฮเฟเล่ (ประเทศไทย) จำกัด | M28: =TRUE() -> 1 | N28: 1400 | O28: 608
A29: Standard | B29: RM-FUFIT-219 | C29: 114001 | D29: 114001 | E29: Drawer Runners | F29: Storable Product | G29: ลิ้นชัก-Haf-552.49.386-ชุดอุปกรณ์ราวด้านข้าง500mm. | H29: 552.49.386 SQUARE RAILLING500MM ST.ANT. | I29: ชุด | J29: SET | K29: AP-HAF001 | L29: =IFERROR(VLOOKUP(K29,'Supplier list'!B:C,2,0),"") -> บริษัท เฮเฟเล่ (ประเทศไทย) จำกัด | M29: =FALSE() -> 0 | O29: 80
A30: Standard | B30: RM-FUFIT-220 | C30: 114001 | D30: 114001 | E30: Drawer Runners | F30: Storable Product | G30: ลิ้นชัก-Haf-552.49.320-ราวขวางกันขวดยาว1200mm. | H30: 552.49.320 CROSS RAILING1200MM ALU.ANT. | I30: ชุด | J30: SET | K30: AP-HAF001 | L30: =IFERROR(VLOOKUP(K30,'Supplier list'!B:C,2,0),"") -> บริษัท เฮเฟเล่ (ประเทศไทย) จำกัด | M30: =FALSE() -> 0 | O30: 68
A31: Standard | B31: RM-FUFIT-221 | C31: 114001 | D31: 114001 | E31: Drawer Runners | F31: Storable Product | G31: ลิ้นชัก-Haf-552.49.325-ตัวยึดราวขวาง | H31: 552.49.325 T-CONNECTOR PLASTIC ANTHRACITE | I31: ชุด | J31: SET | K31: AP-HAF001 | L31: =IFERROR(VLOOKUP(K31,'Supplier list'!B:C,2,0),"") -> บริษัท เฮเฟเล่ (ประเทศไทย) จำกัด | M31: =FALSE() -> 0 | O31: 13
A32: Standard | B32: RM-FUFIT-222 | C32: 114001 | D32: 114001 | E32: Divider | F32: Storable Product | G32: ลิ้นชัก-Haf-552.49.590-อุปกรณ์แบ่งกั้นช่อง | H32: 552.49.590 SHORT PLASTIC DIVIDER ANT. | I32: ชิ้น | J32: PC | K32: AP-HAF001 | L32: =IFERROR(VLOOKUP(K32,'Supplier list'!B:C,2,0),"") -> บริษัท เฮเฟเล่ (ประเทศไทย) จำกัด | M32: =FALSE() -> 0 | O32: 15
A33: Standard | B33: RM-FUFIT-223 | C33: 114001 | D33: 114001 | E33: Cabinet | F33: Storable Product | G33: โครงตู้-0-0-เข้ามุมพลาสติกเคลือบอลูมิเนียมสูง10 ซม | H33: Cabinet frame-0-0-Aluminium-coated plastic corner, height 10 cm. | I33: เส้น | J33: STRIP | K33: AP-HAF001 | L33: =IFERROR(VLOOKUP(K33,'Supplier list'!B:C,2,0),"") -> บริษัท เฮเฟเล่ (ประเทศไทย) จำกัด | M33: =FALSE() -> 0 | O33: 14
A34: Standard | B34: RM-FUFIT-224 | C34: 114001 | D34: 114001 | E34: Cabinet | F34: Storable Product | G34: โครงตู้-0-1AL63300PG3-เฟรมสีพิ้งค์โกลด์แฮร์ลาย3.1M | H34: Cabinet Frame-0-1AL63300PG3-Pink Gold Hair Frame 3.1M Pattern | I34: เส้น | J34: STRIP | K34: AP-FTT000 | L34: =IFERROR(VLOOKUP(K34,'Supplier list'!B:C,2,0),"") -> บริษัท ฟิวเจอร์เทค อินเตอร์มาร์เก็ตติ้ง จำกัด | M34: =FALSE() -> 0 | O34: 0
A35: Standard | B35: RM-FUFIT-225 | C35: 114001 | D35: 114001 | E35: Cabinet | F35: Storable Product | G35: โครงตู้-0-1AL25-PEมุมเฟรม62x62x2.6mm.สีซิงค์ขาว250 | H35: Cabinet frame-0-1AL25-PE frame corner 62x62x2.6mm. White zinc color 250 | I35: ชิ้น | J35: PC | K35: AP-BEST00 | L35: =IFERROR(VLOOKUP(K35,'Supplier list'!B:C,2,0),"") -> Best Solid Surfaces Corp. | M35: =FALSE() -> 0 | O35: 7
A36: Standard | B36: RM-FUFIT-232 | C36: 114001 | D36: 114001 | E36: Cabinet | F36: Storable Product | G36: โครงตู้-TMC-HC991267-ปุ่มกันกระแทก | H36: Cabinet frame-TMC-HC991267-shock button | I36: ชิ้น | J36: PC | K36: AP-FTT000 | L36: =IFERROR(VLOOKUP(K36,'Supplier list'!B:C,2,0),"") -> บริษัท ฟิวเจอร์เทค อินเตอร์มาร์เก็ตติ้ง จำกัด | M36: =FALSE() -> 0 | O36: 1
A37: Standard | B37: RM-FUFIT-233 | C37: 114001 | D37: 114001 | E37: Cabinet | F37: Storable Product | G37: โครงตู้-Haf-564.53.182-Alusplashสีขาว | H37: 564.53.182 A.SPL.GRAPHITE GR ARC WH3100X1500MM | I37: แผ่น | J37: SHEET | K37: AP-HAF001 | L37: =IFERROR(VLOOKUP(K37,'Supplier list'!B:C,2,0),"") -> บริษัท เฮเฟเล่ (ประเทศไทย) จำกัด | M37: =FALSE() -> 0 | O37: 32552
A38: Standard | B38: RM-FUFIT-237 | C38: 114001 | D38: 114001 | E38: Angle bar | F38: Storable Product | G38: ติดตั้ง-FTT-BHD07 115 ZN-เหล็กฉากรูปตัวT | H38: Install-FTT-BHD07 115 ZN-T-angle steel | I38: ชิ้น | J38: PC | K38: AP-FTT000 | L38: =IFERROR(VLOOKUP(K38,'Supplier list'!B:C,2,0),"") -> บริษัท ฟิวเจอร์เทค อินเตอร์มาร์เก็ตติ้ง จำกัด | M38: =FALSE() -> 0 | O38: 60
A39: Standard | B39: RM-FUFIT-238 | C39: 114001 | D39: 114001 | E39: Drawer Runners | F39: Storable Product | G39: ลิ้นชัก-0-1C2 9221508-รางสีซิ้งค์ 40กก/400mm | H39: Drawer-0-1C2 9221508-Sink Rail 40kg/400mm | I39: ชุด | J39: SET | K39: AP-PCS000 | L39: =IFERROR(VLOOKUP(K39,'Supplier list'!B:C,2,0),"") -> บริษัท พรีซิชั่นไลน์ จำกัด | M39: =FALSE() -> 0 | O39: 205
A40: Standard | B40: RM-FUFIT-239 | C40: 114001 | D40: 114001 | E40: Cabinet | F40: Storable Product | G40: โครงตู้-IO-A06 03-คลิปเสียบขาตู้พลาสติกสีดำ-อลู | H40: Cabinet Frame-IO-A06 03-Plastic leg clip, black-aluminum | I40: ชิ้น | J40: PC | K40: AP-IOD000 | L40: =IFERROR(VLOOKUP(K40,'Supplier list'!B:C,2,0),"") -> บริษัท ไอ.โอ.ดีไซน์ แอนด์ โฮม จำกัด | M40: =FALSE() -> 0 | O40: 2.5
A41: Standard | B41: RM-FUFIT-240 | C41: 114001 | D41: 114001 | E41: Screw | F41: Storable Product | G41: โครงตู้-0-0-สกรูJF4 8ใช้สำหรับเฟรมกระจก | H41: Cabinet frame-0-0-Screw JF48 used for glass frame. | I41: กล่อง | J41: BOX | L41: =IFERROR(VLOOKUP(K41,'Supplier list'!B:C,2,0),"") | M41: =FALSE() -> 0 | O41: 20
A42: Standard | B42: RM-FUFIT-241 | C42: 114001 | D42: 114001 | E42: Screw | F42: Storable Product | G42: โครงตู้-0-0-สกรูเกลียวปล่อยหัวเตเปอร์แฉกสกรู #8*1F | H42: Cabinet frame-0-0-Taper head self-tapping screw #8*1F | I42: กล่อง | J42: BOX | K42: AP-KSR001 | L42: =IFERROR(VLOOKUP(K42,'Supplier list'!B:C,2,0),"") -> บริษัท เกรียงศิริพัฒนา (1995) จำกัด | M42: =FALSE() -> 0 | O42: 227
A43: Standard | B43: RM-FUFIT-242 | C43: 114001 | D43: 114001 | E43: Basket | F43: Storable Product | G43: ตะแกรง-PCS-7VS 7055 500-ชุดตู้สูงตะแกรง500mm. | H43: Grille-PCS-7VS 7055 500-Set of high cabinet grille 500mm. | I43: ชุด | J43: SET | K43: AP-PCS000 | L43: =IFERROR(VLOOKUP(K43,'Supplier list'!B:C,2,0),"") -> บริษัท พรีซิชั่นไลน์ จำกัด | M43: =FALSE() -> 0 | O43: 0
A44: Standard | B44: RM-FUFIT-243 | C44: 114001 | D44: 114001 | E44: Spoon tray | F44: Storable Product | G44: ถาดวางช้อน-PCS-7VS 7549 PL-ชุดตู้มุม ถาด900mm.ซ้าย | H44: Spoon tray-PCS-7VS 7549 BL- corner cabinet set, tray 900mm. left | I44: ชุด | J44: SET | K44: AP-PCS000 | L44: =IFERROR(VLOOKUP(K44,'Supplier list'!B:C,2,0),"") -> บริษัท พรีซิชั่นไลน์ จำกัด | M44: =FALSE() -> 0 | O44: 0
A45: Standard | B45: RM-FUFIT-244 | C45: 114001 | D45: 114001 | E45: Cabinet | F45: Storable Product | G45: ลิ้นชัก-Hettich-0-แผ่นหน้าลิ้นชักอะลูมิเนียม | H45: Drawer-Hettich-0-Aluminum drawer front | I45: เส้น | J45: STRIP | K45: AP-PCS000 | L45: =IFERROR(VLOOKUP(K45,'Supplier list'!B:C,2,0),"") -> บริษัท พรีซิชั่นไลน์ จำกัด | M45: =FALSE() -> 0 | O45: 550
A46: Standard | B46: RM-FUFIT-245 | C46: 114001 | D46: 114001 | E46: Hinge | F46: Storable Product | G46: บานพับ-Haf-306.00.010-บานพับในขอบ soft close | H46: 306.00.010 DAMP.HIN.INSET BL.GAL.35MM | I46: ชุด | J46: SET | K46: AP-HAF001 | L46: =IFERROR(VLOOKUP(K46,'Supplier list'!B:C,2,0),"") -> บริษัท เฮเฟเล่ (ประเทศไทย) จำกัด | M46: =FALSE() -> 0 | O46: 150
A47: Standard | B47: RM-FUFIT-246 | C47: 114001 | D47: 114001 | E47: Hinge | F47: Storable Product | G47: บานพับ-Haf-306.00.009-บานพับกลางขอบ soft close | H47: 306.00.009 DAMP.HIN.HALF OVE.BL.GAL.35MM | I47: ชุด | J47: SET | K47: AP-HAF001 | L47: =IFERROR(VLOOKUP(K47,'Supplier list'!B:C,2,0),"") -> บริษัท เฮเฟเล่ (ประเทศไทย) จำกัด | M47: =FALSE() -> 0 | O47: 150
A48: Standard | B48: RM-FUFIT-247 | C48: 114001 | D48: 114001 | E48: Cabinet | F48: Storable Product | G48: โครงตู้-จีน-0-อุปกรณ์ยึดหน้าบานกันโก่ง2.1ม สีทอง | H48: Cabinet frame-China-0-Anti-buckle front door fixing 2.1m gold color | I48: เส้น | J48: STRIP | L48: =IFERROR(VLOOKUP(K48,'Supplier list'!B:C,2,0),"") | M48: =FALSE() -> 0 | O48: 0
A49: Standard | B49: RM-FUFIT-248 | C49: 114001 | D49: 114001 | E49: Cabinet | F49: Storable Product | G49: โครงตู้-จีน-0-อุปกรณ์ยึดหน้าบานกันโก่ง2.44ม สีทอง | H49: Cabinet frame-China-0-Anti-buckle front door fixing 2.44 m gold | I49: เส้น | J49: STRIP | L49: =IFERROR(VLOOKUP(K49,'Supplier list'!B:C,2,0),"") | M49: =FALSE() -> 0 | O49: 0
A50: Standard | B50: RM-FUFIT-249 | C50: 114001 | D50: 114001 | E50: Cabinet | F50: Storable Product | G50: โครงตู้-จีน-0-อุปกรณ์ยึดหน้าบานกันโก่ง2.78ม สีทอง | H50: Cabinet frame-China-0-Anti-buckle front door fixing 2.78 m gold | I50: เส้น | J50: STRIP | L50: =IFERROR(VLOOKUP(K50,'Supplier list'!B:C,2,0),"") | M50: =FALSE() -> 0 | O50: 0
A51: Standard | B51: RM-FUFIT-250 | C51: 114001 | D51: 114001 | E51: Cabinet | F51: Storable Product | G51: โครงตู้-จีน-0-ใช้กับอุปกรณ์ยึดหน้าบานกันโก่ง | H51: Cabinet frame-China-0-Used with the device to fix the door to prevent deflection. | I51: ชุด | J51: SET | L51: =IFERROR(VLOOKUP(K51,'Supplier list'!B:C,2,0),"") | M51: =FALSE() -> 0 | O51: 0
A52: Standard | B52: RM-FUFIT-251 | C52: 114001 | D52: 114001 | E52: Aluminum | F52: Storable Product | G52: เส้นอะลูมิเนียมตู้ซิงค์ ยาว3ม.-จีน | H52: Chinese Cabinet Frame Line Aluminum for Sink Cabinet 3 mm. Gray | I52: เส้น | J52: STRIP | L52: =IFERROR(VLOOKUP(K52,'Supplier list'!B:C,2,0),"") | M52: =FALSE() -> 0 | O52: 0
A53: Standard | B53: RM-FUFIT-252 | C53: 114001 | D53: 114001 | E53: Cabinet | F53: Storable Product | G53: โครงตู้-จีน-0-กันกระแทกหน้าบาน 3ม สีใส ใช้กับอลู | H53: Cabinet frame-China-0-Anti-shock, front door 3 m, clear color, use with alu. | I53: เส้น | J53: STRIP | L53: =IFERROR(VLOOKUP(K53,'Supplier list'!B:C,2,0),"") | M53: =FALSE() -> 0 | O53: 0
A54: Standard | B54: RM-FUFIT-253 | C54: 114001 | D54: 114001 | E54: Cabinet | F54: Storable Product | G54: โครงตู้-จีน-0-ชุดอุปกรณ์ยึดหน้าบานกันโก่งพลาสติก | H54: Cabinet frame-China-0-Accessories for fixing the front of the plastic door | I54: ชิ้น | J54: PC | L54: =IFERROR(VLOOKUP(K54,'Supplier list'!B:C,2,0),"") | M54: =FALSE() -> 0 | O54: 0
A55: Standard | B55: RM-FUFIT-254 | C55: 114001 | D55: 114001 | E55: Cabinet | F55: Storable Product | G55: โครงตู้-จีน-0-ขาปรับตู้95 120 cm.สีดำ | H55: Cabinet frame-China-0-Adjustable legs 95 120 cm. Black | I55: ชิ้น | J55: PC | L55: =IFERROR(VLOOKUP(K55,'Supplier list'!B:C,2,0),"") | M55: =FALSE() -> 0 | O55: 0
A56: Standard | B56: RM-FUFIT-255 | C56: 114001 | D56: 114001 | E56: Clothesline | F56: Storable Product | G56: อลูมิเนียม-จีน-0-ราวแขวนเสื้อ 3ม สีดำ | H56: Aluminum-China-0-coat rack 3m black | I56: เส้น | J56: STRIP | L56: =IFERROR(VLOOKUP(K56,'Supplier list'!B:C,2,0),"") | M56: =FALSE() -> 0 | O56: 0
A57: Standard | B57: RM-FUFIT-256 | C57: 114001 | D57: 114001 | E57: Hanger | F57: Storable Product | G57: อลูมิเนียม-จีน-0-ตัวรับราวแขวนสีดำ | H57: Aluminum-China-0-Black Hanger Holder | I57: ชิ้น | J57: PC | L57: =IFERROR(VLOOKUP(K57,'Supplier list'!B:C,2,0),"") | M57: =FALSE() -> 0 | O57: 0
A58: Standard | B58: RM-FUFIT-257 | C58: 114001 | D58: 114001 | E58: Fall protection | F58: Storable Product | G58: อลูมิเนียม-จีน-0-อลูมิเนียมกันตก3ม สีเทา | H58: Aluminum-China-0-Aluminum Fall Protection 3m Gray | I58: เส้น | J58: STRIP | L58: =IFERROR(VLOOKUP(K58,'Supplier list'!B:C,2,0),"") | M58: =FALSE() -> 0 | O58: 0
A59: Standard | B59: RM-FUFIT-258 | C59: 114001 | D59: 114001 | E59: Aluminium Profiles | F59: Storable Product | G59: อลูมิเนียม-จีน-0-แผงปิดขาตู้ครัว+ยางปิดขาตู้3.6ดำ | H59: Aluminum-China-0-Kitchen Cabinet Leg Cover + Cabinet Leg Cover 3.6 Black | I59: เส้น | J59: STRIP | L59: =IFERROR(VLOOKUP(K59,'Supplier list'!B:C,2,0),"") | M59: =FALSE() -> 0 | O59: 0
... A80: Standard | B80: RM-FUFIT-280 | C80: 114001 | D80: 114001 | E80: Aluminium Profiles | F80: Storable Product | G80: อลูมิเนียม-จีน-0-เส้นต่อเป็นราวพาดกางเกงแบบใส่ไฟได | H80: Aluminum-China-0-Line is connected as a light-up trouser rail. | I80: เส้น | J80: STRIP | L80: =IFERROR(VLOOKUP(K80,'Supplier list'!B:C,2,0),"") | M80: =FALSE() -> 0 | O80: 0
A81: Standard | B81: RM-FUFIT-281 | C81: 114001 | D81: 114001 | E81: Plug | F81: Storable Product | G81: พุกไม้ 8*35 mm (5000 ตัว/ถุง) | H81: Wood Plug 8*35 mm (5000 pieces/bag) | I81: ชิ้น | J81: PC | K81: AP-TAJ000 | L81: =IFERROR(VLOOKUP(K81,'Supplier list'!B:C,2,0),"") -> บริษัท ต้าโจว อินดัสทรี จำกัด | M81: =FALSE() -> 0 | O81: 880
A82: Standard | B82: RM-FUFIT-285 | C82: 114001 | D82: 114001 | E82: Aluminium Profiles | F82: Storable Product | G82: โครงตู้-0-1AL46300PG3-โปรไฟล์อลูครัวแอล สีพิงค์โกล | H82: Cabinet frame-0-1AL46300PG3-Aluminum profile, pink gold color | I82: เส้น | J82: STRIP | L82: =IFERROR(VLOOKUP(K82,'Supplier list'!B:C,2,0),"") | M82: =FALSE() -> 0 | O82: 470
A83: Standard | B83: RM-FUFIT-287 | C83: 114001 | D83: 114001 | E83: Spoon tray | F83: Storable Product | G83: ถาดวางช้อน-Hettich-7VS 7549 PR-ชุดตู้มุม ถาด 900mm | H83: Spoon tray-Hettich-7VS 7549 PR-corner cabinet set 900mm tray | I83: ชุด | J83: SET | K83: AP-PCS000 | L83: =IFERROR(VLOOKUP(K83,'Supplier list'!B:C,2,0),"") -> บริษัท พรีซิชั่นไลน์ จำกัด | M83: =FALSE() -> 0 | O83: 0
A84: Standard | B84: RM-FUFIT-288 | C84: 114001 | D84: 114001 | E84: LED strip light | F84: Storable Product | G84: ไฟ-Haf-833.74.337-LED2062 12V/4.8W/M 30K/CRI90 | H84: 833.74.337 LED2062 12V/4.8W/M 30K/CRI90/5M | I84: ม้วน | J84: ROLL | K84: AP-HAF001 | L84: =IFERROR(VLOOKUP(K84,'Supplier list'!B:C,2,0),"") -> บริษัท เฮเฟเล่ (ประเทศไทย) จำกัด | M84: =FALSE() -> 0 | O84: 1500
A85: Standard | B85: RM-FUFIT-289 | C85: 114001 | D85: 114001 | E85: LED strip light | F85: Storable Product | G85: ไฟ-Haf-833.74.338-LED2062 12V/4.8W/M 40K/CRI90 | H85: 833.74.338 LED2062 12V/4.8W/M 40K/CRI90/5M | I85: ม้วน | J85: ROLL | K85: AP-HAF001 | L85: =IFERROR(VLOOKUP(K85,'Supplier list'!B:C,2,0),"") -> บริษัท เฮเฟเล่ (ประเทศไทย) จำกัด | M85: =FALSE() -> 0 | O85: 1500
A86: Standard | B86: RM-FUFIT-290 | C86: 114001 | D86: 114001 | E86: Drawer Runners | F86: Storable Product | G86: ลิ้นชัก-Haf-432.20.930-รางลิ้นชัก B RUNNER S | H86: Drawer-Haf-432.20.930-drawer runner B RUNNER S | I86: ชุด | J86: SET | K86: AP-HAF001 | L86: =IFERROR(VLOOKUP(K86,'Supplier list'!B:C,2,0),"") -> บริษัท เฮเฟเล่ (ประเทศไทย) จำกัด | M86: =FALSE() -> 0 | O86: 589
A87: Standard | B87: RM-FUFIT-291 | C87: 114001 | D87: 114001 | E87: Cabinet | F87: Storable Product | G87: โครงตู้-FTT-PA0003 BL-ตะปูตอกขาโต๊ะ | H87: Cabinet Frame-FTT-PA0003 BL-nail nailed table legs | I87: ชิ้น | J87: PC | K87: AP-FTT000 | L87: =IFERROR(VLOOKUP(K87,'Supplier list'!B:C,2,0),"") -> บริษัท ฟิวเจอร์เทค อินเตอร์มาร์เก็ตติ้ง จำกัด | M87: =FALSE() -> 0 | O87: 10
A88: Standard | B88: RM-FUFIT-292 | C88: 114001 | D88: 114001 | E88: Cabinet | F88: Storable Product | G88: โครงตู้-FTT-5501.1-แผ่นปิดขาตู้ครัวสีซิลเวอร์10x4 | H88: Cabinet Frame-FTT-5501.1-Kitchen Cabinet Leg Cover Silver 10x4 | I88: เส้น | J88: STRIP | K88: AP-FTT000 | L88: =IFERROR(VLOOKUP(K88,'Supplier list'!B:C,2,0),"") -> บริษัท ฟิวเจอร์เทค อินเตอร์มาร์เก็ตติ้ง จำกัด | M88: =FALSE() -> 0 | O88: 385
A89: Standard | B89: RM-FUFIT-293 | C89: 114001 | D89: 114001 | E89: Handle | F89: Storable Product | G89: อลูมิเนียม-Hettich-1AL2030300BL-มือจับอลูมิเนียม | H89: Aluminum-Hettich-1AL2030300BL-Aluminum handle | I89: เส้น | J89: STRIP | K89: AP-PCS000 | L89: =IFERROR(VLOOKUP(K89,'Supplier list'!B:C,2,0),"") -> บริษัท พรีซิชั่นไลน์ จำกัด | M89: =FALSE() -> 0 | O89: 139
A90: Standard | B90: RM-FUFIT-294 | C90: 114001 | D90: 114001 | E90: Basket | F90: Storable Product | G90: ตะแกรง-Haf-522.44.261-ตะแกรงคว่ำจานติดผนัง620mm | H90: 522.44.261 PLATE&FLAT RACK W.HOOK620MM | I90: ชุด | J90: SET | K90: AP-HAF001 | L90: =IFERROR(VLOOKUP(K90,'Supplier list'!B:C,2,0),"") -> บริษัท เฮเฟเล่ (ประเทศไทย) จำกัด | M90: =FALSE() -> 0 | O90: 4972
A91: Standard | B91: RM-FUFIT-295 | C91: 114001 | D91: 114001 | E91: Hanger | F91: Storable Product | G91: ตะแกรง-Haf-521.50.214-ราวแขวน 16/1200 mm. | H91: 521.50.214 RAILING SET CHR.POL. 16/1200MM | I91: ชุด | J91: SET | K91: AP-HAF001 | L91: =IFERROR(VLOOKUP(K91,'Supplier list'!B:C,2,0),"") -> บริษัท เฮเฟเล่ (ประเทศไทย) จำกัด | M91: =FALSE() -> 0 | O91: 1963
A92: Standard | B92: RM-FUFIT-296 | C92: 114001 | D92: 114001 | E92: Screw | F92: Storable Product | G92: โครงตู้-0-0-สกรูเกลียวปล่อยหัวเตเปอร์แฉกสกรู #8*11 | H92: Cabinet frame-0-0-Taper head self-tapping screw #8*11 | I92: กล่อง | J92: BOX | K92: AP-KSR001 | L92: =IFERROR(VLOOKUP(K92,'Supplier list'!B:C,2,0),"") -> บริษัท เกรียงศิริพัฒนา (1995) จำกัด | M92: =FALSE() -> 0 | O92: 239
A93: Standard | B93: RM-FUFIT-297 | C93: 114001 | D93: 114001 | E93: Cabinet | F93: Storable Product | G93: โครงตู้-จีน-0-ยางรองขาตู้ | H93: Cabinet frame-China-0-Rubber leg support | I93: ชิ้น | J93: PC | L93: =IFERROR(VLOOKUP(K93,'Supplier list'!B:C,2,0),"") | M93: =FALSE() -> 0 | O93: 10
A94: Standard | B94: RM-FUFIT-298 | C94: 114001 | D94: 114001 | E94: Basket | F94: Storable Product | G94: ตะแกรง-Hettich-7VS 7549 PR-ชุดตู้มุม150 | H94: Grille-Hettich-7VS 7549 PR-corner set 150 | I94: ชุด | J94: SET | K94: AP-PCS000 | L94: =IFERROR(VLOOKUP(K94,'Supplier list'!B:C,2,0),"") -> บริษัท พรีซิชั่นไลน์ จำกัด | M94: =FALSE() -> 0 | O94: 0
A95: Standard | B95: RM-FUFIT-300 | C95: 114001 | D95: 114001 | E95: Cabinet | F95: Storable Product | G95: โครงตู้-FTT-5502.1-ตัวต่อเข้ามุม 90 องศา | H95: Cabinet frame-FTT-5502.1-90 degree corner connector | I95: เมตร | J95: M | K95: AP-FTT000 | L95: =IFERROR(VLOOKUP(K95,'Supplier list'!B:C,2,0),"") -> บริษัท ฟิวเจอร์เทค อินเตอร์มาร์เก็ตติ้ง จำกัด | M95: =FALSE() -> 0 | O95: 15
A96: Standard | B96: RM-FUFIT-301 | C96: 114001 | D96: 114001 | E96: Waste bin | F96: Storable Product | G96: ติดตั้ง-Hettich-7VS 90003643-ถังขยะแบบดึง 500มม | H96: Fitted-Hettich-7VS 90003643-500mm pull bin | I96: ชุด | J96: SET | K96: AP-PCS000 | L96: =IFERROR(VLOOKUP(K96,'Supplier list'!B:C,2,0),"") -> บริษัท พรีซิชั่นไลน์ จำกัด | M96: =FALSE() -> 0 | O96: 190
A97: Standard | B97: RM-FUFIT-302 | C97: 114001 | D97: 114001 | E97: Basket | F97: Storable Product | G97: ตะแกรง-Hettich-7VS 90002894-ตะแกรงคว่ำจาน 900มม. | H97: Sieve-Hettich-7VS 90002894-Disher 900mm. | I97: ชุด | J97: SET | K97: AP-PCS000 | L97: =IFERROR(VLOOKUP(K97,'Supplier list'!B:C,2,0),"") -> บริษัท พรีซิชั่นไลน์ จำกัด | M97: =FALSE() -> 0 | O97: 5800
A98: Standard | B98: RM-FUFIT-303 | C98: 114001 | D98: 114001 | E98: Drawer Runners | F98: Storable Product | G98: ลิ้นชัก-Haf-433.10.445-รางลิ้นชักแบบซ่อน450mm. | H98: Drawer-Haf-433.10.445-hidden drawer slide 450mm. | I98: ชิ้น | J98: PC | K98: AP-HAF001 | L98: =IFERROR(VLOOKUP(K98,'Supplier list'!B:C,2,0),"") -> บริษัท เฮเฟเล่ (ประเทศไทย) จำกัด | M98: =FALSE() -> 0 | O98: 636
A99: Standard | B99: RM-FUFIT-304 | C99: 114001 | D99: 114001 | E99: Logo | F99: Storable Product | G99: โลโก้-0-0-LAVAREDO สีเงิน | H99: Logo-0-0-LAVAREDO Silver | I99: ชิ้น | J99: PC | K99: AP-QNL000 | L99: =IFERROR(VLOOKUP(K99,'Supplier list'!B:C,2,0),"") -> CO.,LTD QINGDAO NEW LIBERTY INT'L TRADING CO.LTD. | M99: =FALSE() -> 0 | O99: 0
A100: Standard | B100: RM-FUFIT-307 | C100: 114001 | D100: 114001 | E100: Cabinet | F100: Storable Product | G100: โครงตู้-SSW-เหล็กเส้น49.2cm-หนา5.3มิล+น๊อต1/4(4) | H100: Cabinet frame-SSW-Steel Line49.2 cm-thickness 5.3 mm + bolt 1/4 (4) | I100: เส้น | J100: STRIP | K100: AP-SSW000 | L100: =IFERROR(VLOOKUP(K100,'Supplier list'!B:C,2,0),"") -> หจก. ทรัพย์ศรีวงษ์ การช่าง | M100: =FALSE() -> 0 | O100: 0
A101: Standard | B101: RM-FUFIT-308 | C101: 114001 | D101: 114001 | E101: Cabinet | F101: Storable Product | G101: โครงตู้-Haf-489.41.006-ซีลประตูยาง EPDM รูปตัว | H101: 489.41.006 E SHAPE WHITE 3M ADHEN 2X2.5M | I101: เส้น | J101: STRIP | K101: AP-HAF001 | L101: =IFERROR(VLOOKUP(K101,'Supplier list'!B:C,2,0),"") -> บริษัท เฮเฟเล่ (ประเทศไทย) จำกัด | M101: =FALSE() -> 0 | O101: 281
A102: Standard | B102: RM-FUFIT-309 | C102: 114001 | D102: 114001 | E102: Cabinet | F102: Storable Product | G102: กล่อง-Haf-0-ใส่ตู้รองเท้า(ตู้ใหญ่) 2150*460*150 | H102: Box-Haf-0-insert shoe cabinet (big cabinet) 2150*460*150 | I102: กล่อง | J102: BOX | K102: AP-HAF001 | L102: =IFERROR(VLOOKUP(K102,'Supplier list'!B:C,2,0),"") -> บริษัท เฮเฟเล่ (ประเทศไทย) จำกัด | M102: =FALSE() -> 0 | O102: 0
A103: Standard | B103: RM-FUFIT-310 | C103: 114001 | D103: 114001 | E103: Cabinet | F103: Storable Product | G103: กล่อง-Haf-0-ใส่รองเท้า1770*460*150 mm | H103: Box-Haf-0-shoe holder 1770*460*150 mm | I103: ชิ้น | J103: PC | K103: AP-HAF001 | L103: =IFERROR(VLOOKUP(K103,'Supplier list'!B:C,2,0),"") -> บริษัท เฮเฟเล่ (ประเทศไทย) จำกัด | M103: =FALSE() -> 0 | O103: 0
A104: Standard | B104: RM-FUFIT-311 | C104: 114001 | D104: 114001 | E104: Layer box | F104: Storable Product | G104: กล่อง-0-0-Layer box 840*700*90 mm 3 ชั้น | H104: Box-0-0-Layer box 840*700*90 mm 3 layers | I104: ชิ้น | J104: PC | L104: =IFERROR(VLOOKUP(K104,'Supplier list'!B:C,2,0),"") | M104: =FALSE() -> 0 | O104: 0
A105: Standard | B105: RM-FUFIT-312 | C105: 114001 | D105: 114001 | E105: Layer box | F105: Storable Product | G105: กล่อง-0-0-Layer box 1435*700*90 mm 3 ชั้น | H105: Box-0-0-Layer box 1435*700*90 mm 3 layers | I105: ชิ้น | J105: PC | L105: =IFERROR(VLOOKUP(K105,'Supplier list'!B:C,2,0),"") | M105: =FALSE() -> 0 | O105: 0
A106: Standard | B106: RM-FUFIT-313 | C106: 114001 | D106: 114001 | E106: Layer box | F106: Storable Product | G106: กล่อง-0-0-Layer box 1135*700*90 mm 3 ชั้น | H106: Box-0-0-Layer box 1135*700*90 mm 3 layers | I106: ชิ้น | J106: PC | L106: =IFERROR(VLOOKUP(K106,'Supplier list'!B:C,2,0),"") | M106: =FALSE() -> 0 | O106: 0
A107: Standard | B107: RM-FUFIT-314 | C107: 114001 | D107: 114001 | E107: Sticker | F107: Storable Product | G107: ติดตั้ง-0-506-สติ๊กเกอร์ปิดเกือกม้าสีขาว1แผ่น/54ดว | H107: INSTALL-0-506-White horseshoe cover sticker 1 sheet/54D | I107: ดวง | J107: DISK | L107: =IFERROR(VLOOKUP(K107,'Supplier list'!B:C,2,0),"") | M107: =FALSE() -> 0 | O107: 30
A108: Standard | B108: RM-FUFIT-315 | C108: 114001 | D108: 114001 | E108: Sticker | F108: Storable Product | G108: ติดตั้ง-จีน-51-3สติ๊กเกอร์ปิดเกือกม้า สีGraphite | H108: Install-China-51-3 Horseshoe Cover Sticker Graphite Color | I108: ดวง | J108: DISK | L108: =IFERROR(VLOOKUP(K108,'Supplier list'!B:C,2,0),"") | M108: =FALSE() -> 0 | O108: 30
A109: Standard | B109: RM-FUFIT-316 | C109: 114001 | D109: 114001 | E109: Sticker | F109: Storable Product | G109: ติดตั้ง-จีน-352-สติ๊กเกอร์ปิดเกือกม้า สีAsh | H109: Install-China-352-Horseshoe Cover Sticker Ash Color | I109: ดวง | J109: DISK | L109: =IFERROR(VLOOKUP(K109,'Supplier list'!B:C,2,0),"") | M109: =FALSE() -> 0 | O109: 30
A110: Standard | B110: RM-FUFIT-317 | C110: 114001 | D110: 114001 | E110: Sticker | F110: Storable Product | G110: ติดตั้ง-จีน-524-สติ๊กเกอร์ปิดเกือกม้า สีTeak | H110: Install-China-524-Horseshoe Cover Sticker Teak Color | I110: ดวง | J110: DISK | L110: =IFERROR(VLOOKUP(K110,'Supplier list'!B:C,2,0),"") | M110: =FALSE() -> 0 | O110: 30
A111: Standard | B111: RM-FUFIT-318 | C111: 114001 | D111: 114001 | E111: Basket | F111: Storable Product | G111: ตะแกรง-จีน-0-ตะแกรงถังแก๊ส | H111: Grate-China-0-Gas tank grate | I111: แผ่น | J111: SHEET | L111: =IFERROR(VLOOKUP(K111,'Supplier list'!B:C,2,0),"") | M111: =FALSE() -> 0 | O111: 229
A112: Standard | B112: RM-FUFIT-319 | C112: 114001 | D112: 114001 | E112: Basket | F112: Storable Product | G112: ตะแกรง-จีน-0-ตะแกรงคว่ำจานตู้แขวน900 | H112: Rack-China-0-Dishes rack, hanging cabinet 900 | I112: ชิ้น | J112: PC | L112: =IFERROR(VLOOKUP(K112,'Supplier list'!B:C,2,0),"") | M112: =TRUE() -> 1 | N112: 3500 | O112: 1300
A113: Standard | B113: RM-FUFIT-320 | C113: 114001 | D113: 114001 | E113: Aluminium Profiles | F113: Storable Product | G113: ไฟ-Haf-833.89.300-รางไฟเฉียง | H113: 833.89.300 DIFFUSER LINEAR LENS | I113: ชุด | J113: SET | K113: AP-HAF001 | L113: =IFERROR(VLOOKUP(K113,'Supplier list'!B:C,2,0),"") -> บริษัท เฮเฟเล่ (ประเทศไทย) จำกัด | M113: =FALSE() -> 0 | O113: 840
A114: Standard | B114: RM-FUFIT-321 | C114: 114001 | D114: 114001 | E114: Angle bar | F114: Storable Product | G114: มือจับ-FTT-PB26 SS-ฉากแสตนเลส | H114: Handle-FITT-PB26 SS-stainless steel scene | I114: ชิ้น | J114: PC | K114: AP-FTT000 | L114: =IFERROR(VLOOKUP(K114,'Supplier list'!B:C,2,0),"") -> บริษัท ฟิวเจอร์เทค อินเตอร์มาร์เก็ตติ้ง จำกัด | M114: =FALSE() -> 0 | O114: 15
A115: Standard | B115: RM-FUFIT-322 | C115: 114001 | D115: 114001 | E115: Wire storage | F115: Storable Product | G115: ไฟ-FTT-CO 50 080-ช่องเก็บสายไฟ | H115: Fire-FTT-CO 50 080-Wire storage compartment | I115: ชิ้น | J115: PC | K115: AP-FTT000 | L115: =IFERROR(VLOOKUP(K115,'Supplier list'!B:C,2,0),"") -> บริษัท ฟิวเจอร์เทค อินเตอร์มาร์เก็ตติ้ง จำกัด | M115: =FALSE() -> 0 | O115: 90
A116: Standard | B116: RM-FUFIT-326 | C116: 114001 | D116: 114001 | E116: Paper box | F116: Storable Product | G116: กล่อง-SSP-เกรด KA125-กล่อง5ชั้น733x1346x73mm. | H116: Box-SSP-grade KA125-Box 5 layers 733x1346x73mm. | I116: ชิ้น | J116: PC | K116: AP-SSP000 | L116: =IFERROR(VLOOKUP(K116,'Supplier list'!B:C,2,0),"") -> บริษัท เอส.เอส.อุตสาหกรรมบรรจุภัณฑ์ จำกัด | M116: =FALSE() -> 0 | O116: 58
A117: Standard | B117: RM-FUFIT-327 | C117: 114001 | D117: 114001 | E117: Basket | F117: Storable Product | G117: ตะแกรง-Hettich-7VS 4525 300S-ตู้สูงแบบเซฟไฟร์300mm | H117: Grille-Hettich-7VS 4525 300S-Safefire 300mm high cabinet | I117: ชุด | J117: SET | K117: AP-PCS000 | L117: =IFERROR(VLOOKUP(K117,'Supplier list'!B:C,2,0),"") -> บริษัท พรีซิชั่นไลน์ จำกัด | M117: =FALSE() -> 0 | O117: 19600
A118: Standard | B118: RM-FUFIT-328 | C118: 114001 | D118: 114001 | E118: Handle | F118: Storable Product | G118: มือจับ-FTT-1AL2030300BL-โปร์ไฟล์อลูมิเนียม | H118: Handle-FTT-1AL2030300BL-Aluminum Profile | I118: ชิ้น | J118: PC | K118: AP-FTT000 | L118: =IFERROR(VLOOKUP(K118,'Supplier list'!B:C,2,0),"") -> บริษัท ฟิวเจอร์เทค อินเตอร์มาร์เก็ตติ้ง จำกัด | M118: =FALSE() -> 0 | O118: 420
A119: Standard | B119: RM-FUFIT-329 | C119: 114001 | D119: 114001 | E119: Drawer Runners | F119: Storable Product | G119: 432.20.932 รางรับข้างปิดนุ่มนวลรับ นน. 30กก. 350มม | H119: 432.20.932 B-RUNNER S 30F+D GALV.350MM | I119: คู่ | J119: PAIR | K119: AP-HAF001 | L119: =IFERROR(VLOOKUP(K119,'Supplier list'!B:C,2,0),"") -> บริษัท เฮเฟเล่ (ประเทศไทย) จำกัด | M119: =TRUE() -> 1 | N119: 1500 | O119: 636
A120: Standard | B120: RM-FUFIT-330 | C120: 114001 | D120: 114001 | E120: Drawer Runners | F120: Storable Product | G120: ลิ้นชัก-FTT-1C2 9221508-รางลิ้นชักลูกปืน 400 | H120: Drawer-FTT-1C2 9221508-Bearing drawer slide 400 | I120: คู่ | J120: PAIR | K120: AP-HAF001 | L120: =IFERROR(VLOOKUP(K120,'Supplier list'!B:C,2,0),"") -> บริษัท เฮเฟเล่ (ประเทศไทย) จำกัด | M120: =FALSE() -> 0 | O120: 480
...

Sheet 1301-1709
A1: Standardize | B1: Product Code | C1: Income Account | D1: Expense Account | E1: Product Category | F1: Product Type | G1: Product Name TH | H1: Product Name EN | I1: UOM TH | J1: UOM EN | K1: Code Supplier | L1: Supplier Name | M1: True/False | N1: Selling Price | O1: Cost Price
A2: Standard | B2: RM-FUFIT-884 | C2: 114001 | D2: 114001 | E2: Handle | F2: Storable Product | G2: 530011-6106S มือจับ 106ม. สีเงิน | H2: 530011-6106S Handle 106 m. Silver | I2: ชิ้น | J2: PC | K2: AP-PSN000 | L2: =IFERROR(VLOOKUP(K2,'Supplier list'!B:C,2,0),"") | M2: =TRUE() -> 1 | N2: 350 | O2: 180
A3: Standard | B3: RM-FUFIT-885 | C3: 114001 | D3: 114001 | E3: Handle | F3: Storable Product | G3: 530011-6106B มือจับ 106ม. สีดำ | H3: 530011-6106B Handle 106 m. Black | I3: ชิ้น | J3: PC | K3: AP-PSN000 | L3: =IFERROR(VLOOKUP(K3,'Supplier list'!B:C,2,0),"") | M3: =TRUE() -> 1 | N3: 350 | O3: 180
A4: Standard | B4: RM-FUFIT-886 | C4: 114001 | D4: 114001 | E4: Handle | F4: Storable Product | G4: 510026-4128 ปุ่มจับทองเหลือง P128มม. | H4: 510026-4128 Brass Knob P128mm. | I4: ชิ้น | J4: PC | K4: AP-PSN000 | L4: =IFERROR(VLOOKUP(K4,'Supplier list'!B:C,2,0),"") | M4: =TRUE() -> 1 | N4: 1500 | O4: 780
A5: Standard | B5: RM-FUFIT-887 | C5: 114001 | D5: 114001 | E5: Handle | F5: Storable Product | G5: 510026-4000 ปุ่มจับทองเหลือง | H5: 510026-4000 brass knob | I5: ชิ้น | J5: PC | K5: AP-PSN000 | L5: =IFERROR(VLOOKUP(K5,'Supplier list'!B:C,2,0),"") | M5: =TRUE() -> 1 | N5: 450 | O5: 260
A6: Standard | B6: RM-FUFIT-888 | C6: 114001 | D6: 114001 | E6: Handle | F6: Storable Product | G6: 510026-4220 มือจับทองเหลือง P220มม. | H6: 510026-4220 Brass handle P220mm. | I6: ชิ้น | J6: PC | K6: AP-PSN000 | L6: =IFERROR(VLOOKUP(K6,'Supplier list'!B:C,2,0),"") | M6: =TRUE() -> 1 | N6: 1900 | O6: 1220
A7: Standard | B7: RM-FUFIT-889 | C7: 114001 | D7: 114001 | E7: Handle | F7: Storable Product | G7: 520001-6148B มือจับ 148มม. สีดำ | H7: 52001-6148B Handle 148mm. Black | I7: ชิ้น | J7: PC | K7: AP-PSN000 | L7: =IFERROR(VLOOKUP(K7,'Supplier list'!B:C,2,0),"") | M7: =TRUE() -> 1 | N7: 350 | O7: 170
A8: Standard | B8: RM-FUFIT-890 | C8: 114001 | D8: 114001 | E8: Handle | F8: Storable Product | G8: 520001-61000B มือจับ 1000มม. สีดำ | H8: 520001-61000B Handle 1000mm. Black | I8: ชิ้น | J8: PC | K8: AP-PSN000 | L8: =IFERROR(VLOOKUP(K8,'Supplier list'!B:C,2,0),"") | M8: =FALSE() -> 0 | O8: 1300
A9: Standard | B9: RM-FUFIT-891 | C9: 114001 | D9: 114001 | E9: Basket | F9: Storable Product | G9: 546.27.310 ชุดตู้สูงบานดึง Dispensa 150มม. | H9: 546.27.310 Dispensa door pull-out height set, 150mm. | I9: ชุด | J9: SET | K9: AP-HAF001 | L9: =IFERROR(VLOOKUP(K9,'Supplier list'!B:C,2,0),"") -> บริษัท เฮเฟเล่ (ประเทศไทย) จำกัด | M9: =TRUE() -> 1 | N9: 29900 | O9: 17196.5
A10: Standard | B10: RM-FUFIT-892 | C10: 114001 | D10: 114001 | E10: Waste bin | F10: Storable Product | G10: จีน-ถังขยะตะแกรงบานดึง 400มม. | H10: China-Rubber sieve door 400mm. | I10: ชุด | J10: SET | L10: =IFERROR(VLOOKUP(K10,'Supplier list'!B:C,2,0),"") | M10: =TRUE() -> 1 | N10: 4500 | O10: 0
A11: Standard | B11: RM-FUFIT-893 | C11: 114001 | D11: 114001 | E11: Paper box | F11: Storable Product | G11: กล่องKT125/M ใส่ตู้สูง พิมพ์ตามแบบ | H11: Box KT125/M with high cabinet, printed according to the design | I11: ชิ้น | J11: PC | K11: AP-SPS001 | L11: =IFERROR(VLOOKUP(K11,'Supplier list'!B:C,2,0),"") | M11: =FALSE() -> 0 | O11: 124
A12: Standard | B12: RM-FUFIT-894 | C12: 114001 | D12: 114001 | E12: Handle | F12: Storable Product | G12: 1H00700596 มือจับ สีทอง 96มม. | H12: 1H00700596 Handle, gold, 96mm. | I12: ชิ้น | J12: PC | K12: AP-FTT000 | L12: =IFERROR(VLOOKUP(K12,'Supplier list'!B:C,2,0),"") -> บริษัท ฟิวเจอร์เทค อินเตอร์มาร์เก็ตติ้ง จำกัด | M12: =FALSE() -> 0 | O12: 52.5
A13: Standard | B13: RM-FURAW-001 | C13: 114001 | D13: 114001 | E13: Wood | F13: Storable Product | G13: ไม้-MDF E0 CARB-MKW5305 PL:011-Blond Oak-18mm.*4*8 | H13: Wood-MDF E0 CARB-MKW5305 PL:011-Blond Oak-18mm.*4*8 | I13: แผ่น | J13: SHEET | K13: AP-MKW000 | L13: =IFERROR(VLOOKUP(K13,'Supplier list'!B:C,2,0),"") -> บริษัท เอ็มเค วู้ดเทค จำกัด | M13: =FALSE() -> 0 | O13: 220
A14: Standard | B14: RM-FURAW-002 | C14: 114001 | D14: 114001 | E14: Wood | F14: Storable Product | G14: ไม้เปลือย-PB E0-18mm.*4*8 | H14: Bare wood-PB E0-18mm.*4*8 | I14: แผ่น | J14: SHEET | K14: AP-GRP000 | L14: =IFERROR(VLOOKUP(K14,'Supplier list'!B:C,2,0),"") -> บริษัท กรีนรีเวอร์ พาเนล (ประเทศไทย) จำกัด | M14: =FALSE() -> 0 | O14: 336
A15: Standard | B15: RM-FURAW-003 | C15: 114001 | D15: 114001 | E15: Wood | F15: Storable Product | G15: ไม้-MDF E0-MoccaWalnut-MKW5309 PL:06-18mm. | H15: Wood-MDF E0-MoccaWalnut-MKW5309 PL:06-18mm. | I15: แผ่น | J15: SHEET | K15: AP-MKW000 | L15: =IFERROR(VLOOKUP(K15,'Supplier list'!B:C,2,0),"") -> บริษัท เอ็มเค วู้ดเทค จำกัด | M15: =FALSE() -> 0 | O15: 9.1
A16: Standard | B16: RM-FURAW-004 | C16: 114001 | D16: 114001 | E16: Wood | F16: Storable Product | G16: ปิดขอบ-1mm.-28mm.-Hard Oak-MKW5305 | H16: Close the edge -1mm.-28mm.-Hard Oak-MKW5305 | I16: เมตร | J16: M | K16: AP-MKW000 | L16: =IFERROR(VLOOKUP(K16,'Supplier list'!B:C,2,0),"") -> บริษัท เอ็มเค วู้ดเทค จำกัด | M16: =FALSE() -> 0 | O16: 220
A17: Standard | B17: RM-FURAW-005 | C17: 114001 | D17: 114001 | E17: Wood | F17: Storable Product | G17: ปิดขอบ-1mm.-28mm.-Macca Walnut-MKW5309 | H17: Close the edge -1mm.-28mm.-Macca Walnut-MKW5309 | I17: เมตร | J17: M | K17: AP-MKW000 | L17: =IFERROR(VLOOKUP(K17,'Supplier list'!B:C,2,0),"") -> บริษัท เอ็มเค วู้ดเทค จำกัด | M17: =FALSE() -> 0 | O17: 9.1
A18: Standard | B18: RM-FURAW-006 | C18: 114001 | D18: 114001 | E18: Wood | F18: Storable Product | G18: ไม้เปลือย-MDF E2-25mm.*4*8 | H18: Bare-MDF E2-25mm.*4*8 | I18: แผ่น | J18: SHEET | K18: AP-TCH000 | L18: =IFERROR(VLOOKUP(K18,'Supplier list'!B:C,2,0),"") -> บริษัท ไท่ ชาง อินเตอร์เนชั่นแนล คอมเมอร์เชียล เทรด จำกัด | M18: =FALSE() -> 0 | O18: 0
A19: Standard | B19: RM-FURAW-007 | C19: 114001 | D19: 114001 | E19: Wood | F19: Storable Product | G19: ไม้-PB E0-MKW3258 PL:TMC02-Grey-16mm.*4*8 | H19: Wood-PB E0-MKW3258 PL:TMC02-Grey-16mm.*4*8 | I19: แผ่น | J19: SHEET | K19: AP-TCH000 | L19: =IFERROR(VLOOKUP(K19,'Supplier list'!B:C,2,0),"") -> บริษัท ไท่ ชาง อินเตอร์เนชั่นแนล คอมเมอร์เชียล เทรด จำกัด | M19: =FALSE() -> 0 | O19: 915
A20: Standard | B20: RM-FURAW-008 | C20: 114001 | D20: 114001 | E20: Wood | F20: Storable Product | G20: ไม้-MDF E0 CARB-MKW3200 PL:TMC03-Graphite-18mm. | H20: Wood-MDF E0 CARB-MKW3200 PL:TMC03-Graphite-18mm. | I20: แผ่น | J20: SHEET | K20: AP-MKW000 | L20: =IFERROR(VLOOKUP(K20,'Supplier list'!B:C,2,0),"") -> บริษัท เอ็มเค วู้ดเทค จำกัด | M20: =FALSE() -> 0 | O20: 620
A21: Standard | B21: RM-FURAW-009 | C21: 114001 | D21: 114001 | E21: Wood | F21: Storable Product | G21: ปิดขอบ-Honey Oak-TS 8003-1mm.-28mm. | H21: Close the edge of -oney oak-TS 8003-1mm. -8mm. | I21: เมตร | J21: M | K21: AP-9889000 | L21: =IFERROR(VLOOKUP(K21,'Supplier list'!B:C,2,0),"") -> บริษัท 9889 Thailnd | M21: =FALSE() -> 0 | O21: 8.1
A22: Standard | B22: RM-FURAW-010 | C22: 114001 | D22: 114001 | E22: Wood | F22: Storable Product | G22: ไม้-MDF E0 CARB-MKW12180 PL:06-Ash-18mm.*4*8 | H22: Wood-MDF E0 CARB-MKW12180 PL:06-Ash-18mm.*4*8 | I22: แผ่น | J22: SHEET | K22: AP-MKW000 | L22: =IFERROR(VLOOKUP(K22,'Supplier list'!B:C,2,0),"") -> บริษัท เอ็มเค วู้ดเทค จำกัด | M22: =FALSE() -> 0 | O22: 0
... A27: Standard | B27: RM-FURAW-015 | C27: 114001 | D27: 114001 | E27: Wood | F27: Storable Product | G27: ไม้-MDF E0 CARB-MKW5443 PL:011-Mocca Dak-18mm.*4*8 | H27: Wood-MDF E0 Carb-MKW543 PL: 011-Mocca Dak-18mm*4*8 | I27: แผ่น | J27: SHEET | K27: AP-MKW000 | L27: =IFERROR(VLOOKUP(K27,'Supplier list'!B:C,2,0),"") -> บริษัท เอ็มเค วู้ดเทค จำกัด | M27: =FALSE() -> 0 | O27: 0
A28: Standard | B28: RM-FURAW-016 | C28: 114001 | D28: 114001 | E28: Wood | F28: Storable Product | G28: ไม้-PLYWOOD-NANO-Platinum Silk-19mm.*4*8 | H28: Wood-PLYWOOD-NANO-Platinum Silk-1MM.*4*8 | I28: แผ่น | J28: SHEET | L28: =IFERROR(VLOOKUP(K28,'Supplier list'!B:C,2,0),"") | M28: =FALSE() -> 0 | O28: 0
A29: Standard | B29: RM-FURAW-017 | C29: 114001 | D29: 114001 | E29: Wood | F29: Storable Product | G29: ไม้-PLYWOOD-NANO-Coffee-19mm.*4*8 | H29: Wood -Plywood-nano-coffee-19mm.*4*8 | I29: แผ่น | J29: SHEET | L29: =IFERROR(VLOOKUP(K29,'Supplier list'!B:C,2,0),"") | M29: =FALSE() -> 0 | O29: 0
A30: Standard | B30: RM-FURAW-018 | C30: 114001 | D30: 114001 | E30: Wood | F30: Storable Product | G30: ไม้-PLYWOOD-NANO-Kahki-19mm.*4*8 | H30: Wood -Plywood-nano-kahki-19mm.*4*8 | I30: แผ่น | J30: SHEET | L30: =IFERROR(VLOOKUP(K30,'Supplier list'!B:C,2,0),"") | M30: =FALSE() -> 0 | O30: 0
A31: Standard | B31: RM-FURAW-019 | C31: 114001 | D31: 114001 | E31: Wood | F31: Storable Product | G31: ไม้-PLYWOOD-NANO-Nordic Silver-19mm.*4*8 | H31: Wood-PLYWOOD-NANO-Nordic Silver-19mm.*4*8 | I31: แผ่น | J31: SHEET | L31: =IFERROR(VLOOKUP(K31,'Supplier list'!B:C,2,0),"") | M31: =FALSE() -> 0 | O31: 0
A32: Standard | B32: RM-FURAW-020 | C32: 114001 | D32: 114001 | E32: Wood | F32: Storable Product | G32: ปิดขอบ-Graphite-MKW3200-0.8mm.-22mm. | H32: Close the edge of-graphite-mkw3200-0.8mm. -2mm. | I32: เมตร | J32: M | K32: AP-DXT000 | L32: =IFERROR(VLOOKUP(K32,'Supplier list'!B:C,2,0),"") -> บริษัท ดี.เอ็กซ์.เทคนิค จำกัด | M32: =FALSE() -> 0 | O32: 2.28
A33: Standard | B33: RM-FURAW-022 | C33: 114001 | D33: 114001 | E33: Wood | F33: Storable Product | G33: ปิดขอบ-สีCherry Cappucino-98 14040-1mm.-22mm. | H33: Close the edge-Cherry CAPPUCINO-98 14040-1mm. -2mm. | I33: เมตร | J33: M | K33: AP-9889000 | L33: =IFERROR(VLOOKUP(K33,'Supplier list'!B:C,2,0),"") -> บริษัท 9889 Thailnd | M33: =FALSE() -> 0 | O33: 0
A34: Standard | B34: RM-FURAW-023 | C34: 114001 | D34: 114001 | E34: Wood | F34: Storable Product | G34: ไม้-MDF E1-MKW4008 06-สีHard Oak-19mm.*4*8 | H34: Wood -MDF E1-MKW4008 06-Hard Oak-19mm.*4*8 | I34: แผ่น | J34: SHEET | K34: AP-MKW000 | L34: =IFERROR(VLOOKUP(K34,'Supplier list'!B:C,2,0),"") -> บริษัท เอ็มเค วู้ดเทค จำกัด | M34: =FALSE() -> 0 | O34: 0
A35: Standard | B35: RM-FURAW-024 | C35: 114001 | D35: 114001 | E35: Wood | F35: Storable Product | G35: ปิดขอบ-สีTeak Cabania-98 4192-1mm.-22mm. | H35: Close the edge-TEAK CABANIA-98 4192-1mm. -2mm. | I35: เมตร | J35: M | K35: AP-9889000 | L35: =IFERROR(VLOOKUP(K35,'Supplier list'!B:C,2,0),"") -> บริษัท 9889 Thailnd | M35: =FALSE() -> 0 | O35: 6.5
A36: Standard | B36: RM-FURAW-026 | C36: 114001 | D36: 114001 | E36: Wood | F36: Storable Product | G36: ปิดขอบ-สีHard Oak-98 12553-1mm.-22mm. | H36: Close the edge-hard oak-98 12553-1mm. -2mm. | I36: เมตร | J36: M | K36: AP-9889000 | L36: =IFERROR(VLOOKUP(K36,'Supplier list'!B:C,2,0),"") -> บริษัท 9889 Thailnd | M36: =FALSE() -> 0 | O36: 6.8
A37: Standard | B37: RM-FURAW-027 | C37: 114001 | D37: 114001 | E37: Wood | F37: Storable Product | G37: ไม้-PB E0 CARB-MKW101 PL:TMC02-White-18mm.*4*8 | H37: Wood-PB E0 Carb-MKW101 PL: TMC02-WHITE-18mm.*4*8 | I37: แผ่น | J37: SHEET | K37: AP-MKW000 | L37: =IFERROR(VLOOKUP(K37,'Supplier list'!B:C,2,0),"") -> บริษัท เอ็มเค วู้ดเทค จำกัด | M37: =FALSE() -> 0 | O37: 0
A38: Standard | B38: RM-FURAW-028 | C38: 114001 | D38: 114001 | E38: Wood | F38: Storable Product | G38: ไม้-PB E1-MKW3180 PL:06-Teak Cabania-16mm.*4*8 | H38: Wood-PB E1-MKW3180 PL: 06-Teak Cabania-16mm.*4*8 | I38: แผ่น | J38: SHEET | K38: AP-MKW000 | L38: =IFERROR(VLOOKUP(K38,'Supplier list'!B:C,2,0),"") -> บริษัท เอ็มเค วู้ดเทค จำกัด | M38: =FALSE() -> 0 | O38: 0
A39: Standard | B39: RM-FURAW-029 | C39: 114001 | D39: 114001 | E39: Wood | F39: Storable Product | G39: ไม้-MDF E0 CARB-MKW3258 PL:TMC02-Grey-6mm.*4*8 | H39: Wood-MDF E0 Carb-MKW3258 PL: TMC02-Gray-6mm.*4*8 | I39: แผ่น | J39: SHEET | K39: AP-MKW000 | L39: =IFERROR(VLOOKUP(K39,'Supplier list'!B:C,2,0),"") -> บริษัท เอ็มเค วู้ดเทค จำกัด | M39: =FALSE() -> 0 | O39: 0
A40: Standard | B40: RM-FURAW-030 | C40: 114001 | D40: 114001 | E40: Wood | F40: Storable Product | G40: ไม้-MDF E0 CARB-MKW3200 PL:TMC02-Graphite-6mm. | H40: Wood-MDF E0 Carb-MKW3200 PL: TMC02-Graphite-6mm. | I40: แผ่น | J40: SHEET | K40: AP-MKW000 | L40: =IFERROR(VLOOKUP(K40,'Supplier list'!B:C,2,0),"") -> บริษัท เอ็มเค วู้ดเทค จำกัด | M40: =FALSE() -> 0 | O40: 0
A41: Standard | B41: RM-FURAW-031 | C41: 114001 | D41: 114001 | E41: Wood | F41: Storable Product | G41: ไม้-PB E1-MKW4008 PL:06-Hard Oak-16mm.*4*8 | H41: Wood-PB E1-MKW4008 PL: 06-Hard Oak-16mm.*4*8 | I41: แผ่น | J41: SHEET | K41: AP-MKW000 | L41: =IFERROR(VLOOKUP(K41,'Supplier list'!B:C,2,0),"") -> บริษัท เอ็มเค วู้ดเทค จำกัด | M41: =FALSE() -> 0 | O41: 0
A42: Standard | B42: RM-FURAW-032 | C42: 114001 | D42: 114001 | E42: Wood | F42: Storable Product | G42: ปิดขอบ-Graphite-0-1mm.-22mm. | H42: Close the edge of-graphite-0-1mm. -2mm. | I42: เมตร | J42: M | K42: AP-9889000 | L42: =IFERROR(VLOOKUP(K42,'Supplier list'!B:C,2,0),"") -> บริษัท 9889 Thailnd | M42: =FALSE() -> 0 | O42: 5
A43: Standard | B43: RM-FURAW-034 | C43: 114001 | D43: 114001 | E43: Wood | F43: Storable Product | G43: ไม้-PB E0 CARB-MKW5309 PL:06-Mocca Walnut-18mm. | H43: Wood-PB E0 Carb-MKW5309 PL: 06-Mocca Walnut-18mm. | I43: แผ่น | J43: SHEET | K43: AP-MKW000 | L43: =IFERROR(VLOOKUP(K43,'Supplier list'!B:C,2,0),"") -> บริษัท เอ็มเค วู้ดเทค จำกัด | M43: =FALSE() -> 0 | O43: 0
... A47: Standard | B47: RM-FURAW-038 | C47: 114001 | D47: 114001 | E47: Wood | F47: Storable Product | G47: ไม้-HMR V70-MKW1125 PL:06-Cherry Capucino-18mm. | H47: Wood -HMR V70-MKW1125 PL: 06-Cherry Capucino-18mm. | I47: แผ่น | J47: SHEET | K47: AP-MKW000 | L47: =IFERROR(VLOOKUP(K47,'Supplier list'!B:C,2,0),"") -> บริษัท เอ็มเค วู้ดเทค จำกัด | M47: =FALSE() -> 0 | O47: 960
A48: Standard | B48: RM-FURAW-040 | C48: 114001 | D48: 114001 | E48: Wood | F48: Storable Product | G48: ปิดขอบ-ลายไม้Plywood-A0787TH00-2mm.-28mm. | H48: Close the edge-Plywood-A0787TH00-2MM. -8MM. | I48: เมตร | J48: M | L48: =IFERROR(VLOOKUP(K48,'Supplier list'!B:C,2,0),"") | M48: =FALSE() -> 0 | O48: 0
A49: Standard | B49: RM-FURAW-041 | C49: 114001 | D49: 114001 | E49: Wood | F49: Storable Product | G49: ไม้-PB E1-MKW5309 MKW06-Macca Walnut-16mm.*4*8 | H49: Wood-PB E1-MKW5309 MKW06-Macca Walnut-16mm.*4*8 | I49: แผ่น | J49: SHEET | K49: AP-MKW000 | L49: =IFERROR(VLOOKUP(K49,'Supplier list'!B:C,2,0),"") -> บริษัท เอ็มเค วู้ดเทค จำกัด | M49: =FALSE() -> 0 | O49: 0
A50: Standard | B50: RM-FURAW-042 | C50: 114001 | D50: 114001 | E50: Wood | F50: Storable Product | G50: ไม้-MDF E0 CARB-MKW101 PL:TMC02-White-16mm.*4*8 | H50: Wood-MDF E0 Carb-MKW101 PL: TMC02-WHITE-16mm.*4*8 | I50: แผ่น | J50: SHEET | K50: AP-MKW000 | L50: =IFERROR(VLOOKUP(K50,'Supplier list'!B:C,2,0),"") -> บริษัท เอ็มเค วู้ดเทค จำกัด | M50: =FALSE() -> 0 | O50: 565
A51: Standard | B51: RM-FURAW-043 | C51: 114001 | D51: 114001 | E51: Wood | F51: Storable Product | G51: ไม้-PB E1-MKW4031 MKW06-Textural Siamea-16mm.*4*8 | H51: Wood-PB E1-MKW4031 MKW06-TEXTURAL SIAMEA-16mm.*4*8 | I51: แผ่น | J51: SHEET | K51: AP-MKW000 | L51: =IFERROR(VLOOKUP(K51,'Supplier list'!B:C,2,0),"") -> บริษัท เอ็มเค วู้ดเทค จำกัด | M51: =FALSE() -> 0 | O51: 0
A52: Standard | B52: RM-FURAW-044 | C52: 114001 | D52: 114001 | E52: Wood | F52: Storable Product | G52: ปิดขอบ-Brown Oak-0-1mm.-22mm. | H52: Close the edge --brown oak-0-1mm. -2mm. | I52: แผ่น | J52: SHEET | L52: =IFERROR(VLOOKUP(K52,'Supplier list'!B:C,2,0),"") | M52: =FALSE() -> 0 | O52: 0
A53: Standard | B53: RM-FURAW-045 | C53: 114001 | D53: 114001 | E53: Wood | F53: Storable Product | G53: ไม้-PB E1-MKW1125 MKW06-Cherry Capucino-16mm.*4*8 | H53: Wood-PB E1-MKW1125 MKW06-Cherry Capucino-16mm.*4*8 | I53: แผ่น | J53: SHEET | K53: AP-MKW000 | L53: =IFERROR(VLOOKUP(K53,'Supplier list'!B:C,2,0),"") -> บริษัท เอ็มเค วู้ดเทค จำกัด | M53: =FALSE() -> 0 | O53: 0
A54: Standard | B54: RM-FURAW-047 | C54: 114001 | D54: 114001 | E54: Wood | F54: Storable Product | G54: ไม้-PB E1-MKW12180/MKW101 PL:06-Ash/White-16mm. | H54: Wood-PB E1-MKW12180/MKW101 PL: 06-SH/White-16mm. | I54: แผ่น | J54: SHEET | K54: AP-MKW000 | L54: =IFERROR(VLOOKUP(K54,'Supplier list'!B:C,2,0),"") -> บริษัท เอ็มเค วู้ดเทค จำกัด | M54: =FALSE() -> 0 | O54: 0
A55: Standard | B55: RM-FURAW-048 | C55: 114001 | D55: 114001 | E55: Wood | F55: Storable Product | G55: ไม้-PBE1-MKW5309/MKW101 PL:06-ScuroWallnut/W-16mm. | H55: Wood-PBE1-MKW5309/MKW101 PL: 06-Scurrowallnut/W-16mm. | I55: แผ่น | J55: SHEET | K55: AP-MKW000 | L55: =IFERROR(VLOOKUP(K55,'Supplier list'!B:C,2,0),"") -> บริษัท เอ็มเค วู้ดเทค จำกัด | M55: =FALSE() -> 0 | O55: 0
A56: Standard | B56: RM-FURAW-049 | C56: 114001 | D56: 114001 | E56: Wood | F56: Storable Product | G56: ไม้-PB E1-MKW4008/MKW101 PL:06-HardOak/White-16mm. | H56: Wood-PB E1-MKW4008/MKW101 PL: 06-Hardoak/White-16mm. | I56: แผ่น | J56: SHEET | K56: AP-MKW000 | L56: =IFERROR(VLOOKUP(K56,'Supplier list'!B:C,2,0),"") -> บริษัท เอ็มเค วู้ดเทค จำกัด | M56: =FALSE() -> 0 | O56: 0
A57: Standard | B57: RM-FURAW-050 | C57: 114001 | D57: 114001 | E57: Wood | F57: Storable Product | G57: ไม้-PBE1-MKW4031/MKW101PL:06-TexturalSiameaW-16mm. | H57: Wood-PBE1-MKW4031/MKW101PL: 06-TEXTURARSIAMEAW-16mm. | I57: แผ่น | J57: SHEET | K57: AP-MKW000 | L57: =IFERROR(VLOOKUP(K57,'Supplier list'!B:C,2,0),"") -> บริษัท เอ็มเค วู้ดเทค จำกัด | M57: =FALSE() -> 0 | O57: 0
A58: Standard | B58: RM-FURAW-051 | C58: 114001 | D58: 114001 | E58: Wood | F58: Storable Product | G58: ไม้-PB E1-MKW3180/MKW101 PL:06-Teak Cabania/W-16mm | H58: Wood-PB E1-MKW3180/MKW101 PL: 06-Teak Cabania/W-16mm | I58: แผ่น | J58: SHEET | K58: AP-MKW000 | L58: =IFERROR(VLOOKUP(K58,'Supplier list'!B:C,2,0),"") -> บริษัท เอ็มเค วู้ดเทค จำกัด | M58: =FALSE() -> 0 | O58: 0
A59: Standard | B59: RM-FURAW-052 | C59: 114001 | D59: 114001 | E59: Wood | F59: Storable Product | G59: ไม้-PBE1-MKW1125MKW101PL:06-CherryCappucinoW-16mm. | H59: Wood-PBE1-MKW1125MKW101PL: 06-SHERRYCAPPUCINOW-16mm. | I59: แผ่น | J59: SHEET | K59: AP-MKW000 | L59: =IFERROR(VLOOKUP(K59,'Supplier list'!B:C,2,0),"") -> บริษัท เอ็มเค วู้ดเทค จำกัด | M59: =FALSE() -> 0 | O59: 0
A60: Standard | B60: RM-FURAW-054 | C60: 114001 | D60: 114001 | E60: Wood | F60: Storable Product | G60: ไม้-MDF E0 CARB-MKW12180 PL:06-Ash-6mm.*4*8 | H60: Wood -MDF E0 Carb-MKW12180 Pl: 06-SH-6mm.*4*8 | I60: แผ่น | J60: SHEET | K60: AP-MKW000 | L60: =IFERROR(VLOOKUP(K60,'Supplier list'!B:C,2,0),"") -> บริษัท เอ็มเค วู้ดเทค จำกัด | M60: =FALSE() -> 0 | O60: 0
A61: Standard | B61: RM-FURAW-055 | C61: 114001 | D61: 114001 | E61: Wood | F61: Storable Product | G61: ไม้-MDF E0 CARB-MKW5309 PL:06-Scuro Wallnut-6mm. | H61: Wood-MDF E0 Carb-MKW5309 PL: 06-Scuro Wallnut-6mm. | I61: แผ่น | J61: SHEET | K61: AP-MKW000 | L61: =IFERROR(VLOOKUP(K61,'Supplier list'!B:C,2,0),"") -> บริษัท เอ็มเค วู้ดเทค จำกัด | M61: =FALSE() -> 0 | O61: 0
A62: Standard | B62: RM-FURAW-056 | C62: 114001 | D62: 114001 | E62: Wood | F62: Storable Product | G62: ไม้-MDF E0 CARB-MKW4008 PL:06-Hard Oak-6mm.*4*8 | H62: Wood-MDF E0 Carb-MKW4008 PL: 06-Hard Oak-6mm.*4*8 | I62: แผ่น | J62: SHEET | K62: AP-MKW000 | L62: =IFERROR(VLOOKUP(K62,'Supplier list'!B:C,2,0),"") -> บริษัท เอ็มเค วู้ดเทค จำกัด | M62: =FALSE() -> 0 | O62: 0
A63: Standard | B63: RM-FURAW-057 | C63: 114001 | D63: 114001 | E63: Wood | F63: Storable Product | G63: ไม้-MDF E0 CARB-MKW4031 PL:06-Textural Siamea-6mm. | H63: Wood-MDF E0 Carb-MKW4031 PL: 06-TEXTural Siamea-6MM. | I63: แผ่น | J63: SHEET | K63: AP-MKW000 | L63: =IFERROR(VLOOKUP(K63,'Supplier list'!B:C,2,0),"") -> บริษัท เอ็มเค วู้ดเทค จำกัด | M63: =FALSE() -> 0 | O63: 0
A64: Standard | B64: RM-FURAW-058 | C64: 114001 | D64: 114001 | E64: Wood | F64: Storable Product | G64: ไม้-MDF E0 CARB-MKW3180 PL:06-Teak Cabania-6mm. | H64: Wood-MDF E0 Carb-MKW3180 PL: 06-Teak Cabania-6mm. | I64: แผ่น | J64: SHEET | K64: AP-MKW000 | L64: =IFERROR(VLOOKUP(K64,'Supplier list'!B:C,2,0),"") -> บริษัท เอ็มเค วู้ดเทค จำกัด | M64: =FALSE() -> 0 | O64: 0
... A94: Standard | B94: RM-FURAW-088 | C94: 114001 | D94: 114001 | E94: Wood | F94: Storable Product | G94: ปิดขอบ-Cherry Cappucino-MKW1125-1mm.-28mm. | H94: Close the edge -cherry CAPPUCINO-MKW1125-1mm.-8MM. | I94: เมตร | J94: M | K94: AP-9889000 | L94: =IFERROR(VLOOKUP(K94,'Supplier list'!B:C,2,0),"") -> บริษัท 9889 Thailnd | M94: =FALSE() -> 0 | O94: 0
A95: Standard | B95: RM-FURAW-089 | C95: 114001 | D95: 114001 | E95: Wood | F95: Storable Product | G95: ปิดขอบ-Platinum Silk-NANO 01-1mm.-22mm. | H95: Close the edge-PLATINUM Silk-nano 01-1mm. -2mm. | I95: เมตร | J95: M | L95: =IFERROR(VLOOKUP(K95,'Supplier list'!B:C,2,0),"") | M95: =FALSE() -> 0 | O95: 0
A96: Standard | B96: RM-FURAW-090 | C96: 114001 | D96: 114001 | E96: Wood | F96: Storable Product | G96: ปิดขอบ-Coffee-NANO 02-1mm.-22mm. | H96: Close the edge-coffee-nano 02-1mm.-22mm. | I96: เมตร | J96: M | L96: =IFERROR(VLOOKUP(K96,'Supplier list'!B:C,2,0),"") | M96: =FALSE() -> 0 | O96: 0
A97: Standard | B97: RM-FURAW-091 | C97: 114001 | D97: 114001 | E97: Wood | F97: Storable Product | G97: ปิดขอบ-Kahki-NANO 11-1mm.-22mm. | H97: Close the edge -Kahki-nano 11-1mm.-22mm. | I97: เมตร | J97: M | L97: =IFERROR(VLOOKUP(K97,'Supplier list'!B:C,2,0),"") | M97: =FALSE() -> 0 | O97: 0
A98: Standard | B98: RM-FURAW-092 | C98: 114001 | D98: 114001 | E98: Wood | F98: Storable Product | G98: ปิดขอบ-Nordic Silver-NANO 15-1mm.-22mm. | H98: Close the edge of-nordic silver-nano 15-1mm. -2mm. | I98: เมตร | J98: M | L98: =IFERROR(VLOOKUP(K98,'Supplier list'!B:C,2,0),"") | M98: =FALSE() -> 0 | O98: 0
A99: Standard | B99: RM-FURAW-093 | C99: 114001 | D99: 114001 | E99: Wood | F99: Storable Product | G99: ปิดขอบ-Grey-MKW3258-1mm.-19mm. | H99: Close-Grey-MKW3258-1mm.-19mm. | I99: เมตร | J99: M | K99: AP-MKW000 | L99: =IFERROR(VLOOKUP(K99,'Supplier list'!B:C,2,0),"") -> บริษัท เอ็มเค วู้ดเทค จำกัด | M99: =FALSE() -> 0 | O99: 0
A100: Standard | B100: RM-FURAW-094 | C100: 114001 | D100: 114001 | E100: Wood | F100: Storable Product | G100: ลามิเนต-Hermes Marcello Walnut-WY5217D-0.7mm.-4*8 | H100: Laminate-Hermes Marcello Walnut-Wy5217D-0.7mm.-4*8 | I100: แผ่น | J100: SHEET | K100: AP-TAK000 | L100: =IFERROR(VLOOKUP(K100,'Supplier list'!B:C,2,0),"") -> บริษัท ทีเอเคโพรดัคส์ แอนด์ เซอร์วิสเซส จำกัด | M100: =FALSE() -> 0 | O100: 0
A101: Standard | B101: RM-FURAW-095 | C101: 114001 | D101: 114001 | E101: Wood | F101: Storable Product | G101: ไม้-MDF MR1-MKW101 PL:TMC02-White-6mm. | H101: Wood-MDF MR1-MKW101 PL: TMC02-WHITE-6MM. | I101: แผ่น | J101: SHEET | K101: AP-MKW000 | L101: =IFERROR(VLOOKUP(K101,'Supplier list'!B:C,2,0),"") -> บริษัท เอ็มเค วู้ดเทค จำกัด | M101: =FALSE() -> 0 | O101: 0
A102: Standard | B102: RM-FURAW-096 | C102: 114001 | D102: 114001 | E102: Wood | F102: Storable Product | G102: ไม้-PB E0 CARB-MKW3200 PL:TMC02-Graphite-18mm.*4*8 | H102: Wood-PB E0 Carb-MKW3200 PL: TMC02-Graphite-18mm.*4*8 | I102: แผ่น | J102: SHEET | K102: AP-MKW000 | L102: =IFERROR(VLOOKUP(K102,'Supplier list'!B:C,2,0),"") -> บริษัท เอ็มเค วู้ดเทค จำกัด | M102: =FALSE() -> 0 | O102: 0
A103: Standard | B103: RM-FURAW-097 | C103: 114001 | D103: 114001 | E103: Wood | F103: Storable Product | G103: ไม้เปลือย-MDF E0 CARB-18mm.*4*8 | H103: Bare-MDF E0 Carb-18mm.*4*8 | I103: แผ่น | J103: SHEET | K103: AP-AGF000 | L103: =IFERROR(VLOOKUP(K103,'Supplier list'!B:C,2,0),"") | M103: =FALSE() -> 0 | O103: 550
A104: Standard | B104: RM-FURAW-098 | C104: 114001 | D104: 114001 | E104: Wood | F104: Storable Product | G104: ไม้-MDF E0 CARB-MKW101 PL:TMC03-White-18mm.*4*8 | H104: Wood-MDF E0 Carb-MKW101 PL: TMC03-WHITE-18mm.*4*8 | I104: แผ่น | J104: SHEET | K104: AP-MKW000 | L104: =IFERROR(VLOOKUP(K104,'Supplier list'!B:C,2,0),"") -> บริษัท เอ็มเค วู้ดเทค จำกัด | M104: =FALSE() -> 0 | O104: 0
A105: Standard | B105: RM-FURAW-099 | C105: 114001 | D105: 114001 | E105: Wood | F105: Storable Product | G105: ปิดขอบ-Grey-MKW3258-1mm.-22mm. | H105: Close-Grey-MKW3258-1mm. -2mm. | I105: เมตร | J105: M | K105: AP-MKW000 | L105: =IFERROR(VLOOKUP(K105,'Supplier list'!B:C,2,0),"") -> บริษัท เอ็มเค วู้ดเทค จำกัด | M105: =FALSE() -> 0 | O105: 6
A106: Standard | B106: RM-FURAW-100 | C106: 114001 | D106: 114001 | E106: Wood | F106: Storable Product | G106: ไม้-PVC-UV Waterproof Boad-White-18mm.*4*8 | H106: Wood-PVC-UV Waterproof BOAD-WHITE-18mm.*4*8 | I106: แผ่น | J106: SHEET | L106: =IFERROR(VLOOKUP(K106,'Supplier list'!B:C,2,0),"") | M106: =FALSE() -> 0 | O106: 0
A107: Standard | B107: RM-FURAW-101 | C107: 114001 | D107: 114001 | E107: Wood | F107: Storable Product | G107: ไม้-PB E0 CARB-LW112-Brazilien Rosewood-18mm.*4*8 | H107: Wood-PB E0 Carb-LW112-RAZILIEN ROSEWOOD-18mm.*4*8 | I107: แผ่น | J107: SHEET | L107: =IFERROR(VLOOKUP(K107,'Supplier list'!B:C,2,0),"") | M107: =FALSE() -> 0 | O107: 0
A108: Standard | B108: RM-FURAW-102 | C108: 114001 | D108: 114001 | E108: Wood | F108: Storable Product | G108: ไม้-PB E0 CARB-LW110-Honey Oak-18mm.*4*8 | H108: Wood-PB E0 Carb-LW110-Roney Oak-18mm.*4*8 | I108: แผ่น | J108: SHEET | L108: =IFERROR(VLOOKUP(K108,'Supplier list'!B:C,2,0),"") | M108: =FALSE() -> 0 | O108: 0
A109: Standard | B109: RM-FURAW-103 | C109: 114001 | D109: 114001 | E109: Wood | F109: Storable Product | G109: ไม้-MDF E0 CARB-LW114-Higloss Lava-18mm.*4*8 | H109: Wood-MDF E0 Carb-LW114-Higloss Lava-18mm.*4*8 | I109: แผ่น | J109: SHEET | L109: =IFERROR(VLOOKUP(K109,'Supplier list'!B:C,2,0),"") | M109: =FALSE() -> 0 | O109: 0
A110: Standard | B110: RM-FURAW-104 | C110: 114001 | D110: 114001 | E110: Wood | F110: Storable Product | G110: ลามิเนต-stainless-PM9031B-0.7mm.-4*8 | H110: Laminte-Stainless-PM9031B-0.7mm.-4*8 | I110: แผ่น | J110: SHEET | K110: AP-SCT000 | L110: =IFERROR(VLOOKUP(K110,'Supplier list'!B:C,2,0),"") | M110: =FALSE() -> 0 | O110: 0
A111: Standard | B111: RM-FURAW-105 | C111: 114001 | D111: 114001 | E111: Wood | F111: Storable Product | G111: ลามิเนต-High Gloss Chalk-GPC1144-0.7mm.-4*8 | H111: Laminate -High Gloss chalk-GPC1144-0.7mm.-4*8 | I111: แผ่น | J111: SHEET | L111: =IFERROR(VLOOKUP(K111,'Supplier list'!B:C,2,0),"") | M111: =FALSE() -> 0 | O111: 0
A112: Standard | B112: RM-FURAW-106 | C112: 114001 | D112: 114001 | E112: Wood | F112: Storable Product | G112: ไม้-MDF E0 CARB-MKW3305 PL:02-Woodland Oak-18mm. | H112: Wood-MDF E0 Carb-MKW3305 PL: 02-Woodland Oak-18mm. | I112: แผ่น | J112: SHEET | K112: AP-MKW000 | L112: =IFERROR(VLOOKUP(K112,'Supplier list'!B:C,2,0),"") -> บริษัท เอ็มเค วู้ดเทค จำกัด | M112: =FALSE() -> 0 | O112: 0
A113: Standard | B113: RM-FURAW-107 | C113: 114001 | D113: 114001 | E113: Wood | F113: Storable Product | G113: ปิดขอบ-Brazilien Rosewood-WQ655-1mm.-22mm. | H113: Close the edge-BRAZILIEN Rosewood-WQ655-1mm. -2mm. | I113: เมตร | J113: M | L113: =IFERROR(VLOOKUP(K113,'Supplier list'!B:C,2,0),"") | M113: =FALSE() -> 0 | O113: 0
A114: Standard | B114: RM-FURAW-108 | C114: 114001 | D114: 114001 | E114: Wood | F114: Storable Product | G114: ปิดขอบ-Honey Oak-WQ8E0718-1mm.-22mm. | H114: Close the edge. -WQ8E0718-1mm. -2mm. | I114: เมตร | J114: M | L114: =IFERROR(VLOOKUP(K114,'Supplier list'!B:C,2,0),"") | M114: =FALSE() -> 0 | O114: 0
A115: Standard | B115: RM-FURAW-109 | C115: 114001 | D115: 114001 | E115: Wood | F115: Storable Product | G115: ปิดขอบ-White-White Matt-1mm.-19mm. | H115: Close -White-WHITE Matt-1mm.-19mm. | I115: ม้วน | J115: ROLL | K115: AP-9889000 | L115: =IFERROR(VLOOKUP(K115,'Supplier list'!B:C,2,0),"") -> บริษัท 9889 Thailnd | M115: =FALSE() -> 0 | O115: 0
A116: Standard | B116: RM-FURAW-111 | C116: 114001 | D116: 114001 | E116: Wood | F116: Storable Product | G116: ปิดขอบ-Higloss Lava-WQ63004-1mm.-22mm. | H116: Close the edge -Higloss Lava-wQ63004-1mm. -2mm. | I116: เมตร | J116: M | L116: =IFERROR(VLOOKUP(K116,'Supplier list'!B:C,2,0),"") | M116: =FALSE() -> 0 | O116: 0
A117: Standard | B117: RM-FURAW-112 | C117: 114001 | D117: 114001 | E117: Wood | F117: Storable Product | G117: ลามิเนต-LINA FLORETINA MARBLE-DXP4318G-0.7mm.-4*8 | H117: Laminate -Lina Floretina Marble-DXP4318G-0.7mm.-4*8 | I117: แผ่น | J117: SHEET | K117: AP-TAK000 | L117: =IFERROR(VLOOKUP(K117,'Supplier list'!B:C,2,0),"") -> บริษัท ทีเอเคโพรดัคส์ แอนด์ เซอร์วิสเซส จำกัด | M117: =FALSE() -> 0 | O117: 0
A118: Standard | B118: RM-FURAW-113 | C118: 114001 | D118: 114001 | E118: Wood | F118: Storable Product | G118: ลามิเนต-Gray-GSC132-0.7mm.-4*8 | H118: Laminate -Gray-GSC132-0.7mm.-4*8 | I118: แผ่น | J118: SHEET | K118: AP-JRP000 | L118: =IFERROR(VLOOKUP(K118,'Supplier list'!B:C,2,0),"") -> หจก. เจอาร์พีฟลอร์ จำกัด | M118: =FALSE() -> 0 | O118: 0
A119: Standard | B119: RM-FURAW-114 | C119: 114001 | D119: 114001 | E119: Wood | F119: Storable Product | G119: ไม้-MDF E0 CARB-TL6025-TMC03-Graphite-21mm. | H119: Wood-MDF E0 Carb-TL6025-TMC03-Graphite-21mm. | I119: แผ่น | J119: SHEET | K119: AP-TCH000 | L119: =IFERROR(VLOOKUP(K119,'Supplier list'!B:C,2,0),"") | M119: =FALSE() -> 0 | O119: 0
A120: Standard | B120: RM-FURAW-116 | C120: 114001 | D120: 114001 | E120: Wood | F120: Storable Product | G120: ไม้-MDF E0 CARB-TL6024-TMC03-White-21mm.*4*8 | H120: Wood -MDF E0 Carb-TL6024-TMC03-WHITE-21mm.*4*8 | I120: แผ่น | J120: SHEET | K120: AP-TCH000 | L120: =IFERROR(VLOOKUP(K120,'Supplier list'!B:C,2,0),"") | M120: =FALSE() -> 0 | O120: 0
A121: Standard | B121: RM-FURAW-117 | C121: 114001 | D121: 114001 | E121: Wood | F121: Storable Product | G121: ปิดขอบ-Ash-MKW12180-0.45mm.-22mm. | H121: Close the edge -ASH-MKW12180-0.45mm. -2mm. | I121: เส้น | J121: STRIP | K121: AP-MKW000 | L121: =IFERROR(VLOOKUP(K121,'Supplier list'!B:C,2,0),"") -> บริษัท เอ็มเค วู้ดเทค จำกัด | M121: =FALSE() -> 0 | O121: 8.1
A122: Standard | B122: RM-FURAW-118 | C122: 114001 | D122: 114001 | E122: Wood | F122: Storable Product | G122: ลามิเนต-Berger Bavarian Oak-WY4238X-0.7mm.-4*8 | H122: Laminate -berger Bavarian Oak-Wy4238X-0.7mm.-4*8 | I122: แผ่น | J122: SHEET | K122: AP-TAK000 | L122: =IFERROR(VLOOKUP(K122,'Supplier list'!B:C,2,0),"") -> บริษัท ทีเอเคโพรดัคส์ แอนด์ เซอร์วิสเซส จำกัด | M122: =FALSE() -> 0 | O122: 0
A123: Standard | B123: RM-FURAW-120 | C123: 114001 | D123: 114001 | E123: Wood | F123: Storable Product | G123: ไม้-PB E0 CARB-MKW3258 PL:TMC02-Grey-18mm.*4*8 | H123: Wood-PB E0 Carb-MKW3258 PL: TMC02-Gray-18mm.*4*8 | I123: แผ่น | J123: SHEET | K123: AP-MKW000 | L123: =IFERROR(VLOOKUP(K123,'Supplier list'!B:C,2,0),"") -> บริษัท เอ็มเค วู้ดเทค จำกัด | M123: =FALSE() -> 0 | O123: 0
A124: Standard | B124: RM-FURAW-121 | C124: 114001 | D124: 114001 | E124: Wood | F124: Storable Product | G124: ไม้-PB E0 CARB-MKW3180 PL:06-Teak Cabania-18mm. | H124: Wood-PB E0 Carb-MKW3180 PL: 06-Teak Cabania-18mm. | I124: แผ่น | J124: SHEET | K124: AP-MKW000 | L124: =IFERROR(VLOOKUP(K124,'Supplier list'!B:C,2,0),"") -> บริษัท เอ็มเค วู้ดเทค จำกัด | M124: =FALSE() -> 0 | O124: 0
A125: Standard | B125: RM-FURAW-122 | C125: 114001 | D125: 114001 | E125: Wood | F125: Storable Product | G125: ปิดขอบ-Graphite-MKW3200-1mm.-19mm. | H125: Close -Graphite-MKW3200-1mm.-19mm. | I125: เมตร | J125: M | K125: AP-9889000 | L125: =IFERROR(VLOOKUP(K125,'Supplier list'!B:C,2,0),"") -> บริษัท 9889 Thailnd | M125: =FALSE() -> 0 | O125: 0
A126: Standard | B126: RM-FURAW-123 | C126: 114001 | D126: 114001 | E126: Wood | F126: Storable Product | G126: ปิดขอบ-White-ผิวส้ม-0.8mm.-22mm.1BOX=5ม้วน@200m. | H126: Close -White-orange skin -0.8mm. -2mm.1box = 5 rolls@200m. | I126: เมตร | J126: M | K126: AP-DXT000 | L126: =IFERROR(VLOOKUP(K126,'Supplier list'!B:C,2,0),"") | M126: =FALSE() -> 0 | O126: 2.28
A127: Standard | B127: RM-FURAW-124 | C127: 114001 | D127: 114001 | E127: Wood | F127: Storable Product | G127: ปิดขอบ-White Duraboard-ผิวเรียบเงา-1mm.-22mm. | H127: Close the edge of -White Duraboard-smooth surface -1mm. -2mm. | I127: เมตร | J127: M | K127: AP-TMK000 | L127: =IFERROR(VLOOKUP(K127,'Supplier list'!B:C,2,0),"") -> บริษัท ไทย เมก้าแคบ จำกัด | M127: =FALSE() -> 0 | O127: 8.72
A128: Standard | B128: RM-FURAW-125 | C128: 114001 | D128: 114001 | E128: Wood | F128: Storable Product | G128: ไม้เปลือย-PB E1-16mm.*4*8 | H128: Bare wood-PB E1-16mm.*4*8 | I128: แผ่น | J128: SHEET | K128: AP-QNL000 | L128: =IFERROR(VLOOKUP(K128,'Supplier list'!B:C,2,0),"") -> CO.,LTD QINGDAO NEW LIBERTY INT'L TRADING CO.LTD. | M128: =FALSE() -> 0 | O128: 375
... A151: Standard | B151: RM-FURAW-149 | C151: 114001 | D151: 114001 | E151: Wood | F151: Storable Product | G151: ปิดขอบ-White-ผิวลายหนัง-0.8mm.-22mm. | H151: Closed -White-skin pattern skin -0.8mm. -2mm. | I151: เมตร | J151: M | K151: AP-TMK000 | L151: =IFERROR(VLOOKUP(K151,'Supplier list'!B:C,2,0),"") -> บริษัท ไทย เมก้าแคบ จำกัด | M151: =FALSE() -> 0 | O151: 1.835
A152: Standard | B152: RM-FURAW-150 | C152: 114001 | D152: 114001 | E152: Malamine Paper | F152: Storable Product | G152: กระดาษ-Melamine Paper Cream White-0 | H152: Paper-MELAMINE Paper Cream White-0 | I152: ม้วน | J152: ROLL | L152: =IFERROR(VLOOKUP(K152,'Supplier list'!B:C,2,0),"") | M152: =FALSE() -> 0 | O152: 0
A153: Standard | B153: RM-FURAW-152 | C153: 114001 | D153: 114001 | E153: Wood | F153: Storable Product | G153: ไม้-MDF-MKW3258-ผิวTMC03สี Grey-21mm.*4*8 | H153: Wood -MDF-MKW3258-Skin TMC03 Color Gray-21mm.*4*8 | I153: แผ่น | J153: SHEET | K153: AP-MKW000 | L153: =IFERROR(VLOOKUP(K153,'Supplier list'!B:C,2,0),"") -> บริษัท เอ็มเค วู้ดเทค จำกัด | M153: =FALSE() -> 0 | O153: 0
A154: Standard | B154: RM-FURAW-153 | C154: 114001 | D154: 114001 | E154: Wood | F154: Storable Product | G154: ไม้-HMR V70-TL6024-TMC03-White-18mm.(2หน้ | H154: Wood -HMR V70-TL6024-TMC03-WHITE-18mm. (2 pages | I154: แผ่น | J154: SHEET | K154: AP-MKW000 | L154: =IFERROR(VLOOKUP(K154,'Supplier list'!B:C,2,0),"") -> บริษัท เอ็มเค วู้ดเทค จำกัด | M154: =FALSE() -> 0 | O154: 900
A155: Standard | B155: RM-FURAW-154 | C155: 114001 | D155: 114001 | E155: Wood | F155: Storable Product | G155: ปิดขอบ-9889-98 4238(MKW2281)-1mm.-22mm. | H155: Close the edge -9889-98 4238 (MKW2281) -1mm. -2mm. | I155: ม้วน | J155: ROLL | K155: AP-9889000 | L155: =IFERROR(VLOOKUP(K155,'Supplier list'!B:C,2,0),"") -> บริษัท 9889 Thailnd | M155: =FALSE() -> 0 | O155: 6.8
A156: Standard | B156: RM-FURAW-156 | C156: 114001 | D156: 114001 | E156: Wood | F156: Storable Product | G156: ลามิเนต-WY4240X-0-0.7mm.-4*8 | H156: Laminate -Wy4240x-0.7mm.-4*8 | I156: แผ่น | J156: SHEET | K156: AP-TAK000 | L156: =IFERROR(VLOOKUP(K156,'Supplier list'!B:C,2,0),"") -> บริษัท ทีเอเคโพรดัคส์ แอนด์ เซอร์วิสเซส จำกัด | M156: =FALSE() -> 0 | O156: 1400
A157: Standard | B157: RM-FURAW-157 | C157: 114001 | D157: 114001 | E157: Wood | F157: Storable Product | G157: ปิดขอบ-9889-98 17475(MKW5072)-1mm.-22mm. | H157: Close the edge -9889-98 17475 (MKW5072) -1mm. -2mm. | I157: เมตร | J157: M | K157: AP-9889000 | L157: =IFERROR(VLOOKUP(K157,'Supplier list'!B:C,2,0),"") -> บริษัท 9889 Thailnd | M157: =FALSE() -> 0 | O157: 6.8
A158: Standard | B158: RM-FURAW-158 | C158: 114001 | D158: 114001 | E158: Wood | F158: Storable Product | G158: ปิดขอบ-9889-98 B14TG109(MKW5617)-1mm.-22mm. | H158: Close the edge -9889-98 B14TG109 (MKW5617) -1mm. -2mm. | I158: เมตร | J158: M | K158: AP-9889000 | L158: =IFERROR(VLOOKUP(K158,'Supplier list'!B:C,2,0),"") -> บริษัท 9889 Thailnd | M158: =FALSE() -> 0 | O158: 6.8
...
